Workbook

Sheet Top 25
A2: Top 25 expansion targets
A3: Highest-priority candidates not marked already served. Food-access estimates guide the first outreach and verification round.
A4: Ranking weights | E4: Review as of | H4: Review valid days | J4: Oldest retrieval
B5: Baseline | E5: =TODAY() -> 46316 | H5: 180 | J5: =MIN(DATEVALUE(Data!O2),DATEVALUE(Data!H1531),DATEVALUE(Data!K1021)) -> 46304
A7: Eligible candidates | D7: Matching schools | G7: Top 25 enrollment | J7: Marked served
B8: =COUNTIFS(Data!$H$2051:$H$2550,"Yes") -> 305 | E8: =SUM(Data!$AP$2051:$AP$2550) -> 45 | H8: =SUM(E13:E37) -> 14077 | K8: =COUNTIFS(Data!$H$2051:$H$2550,"Yes",Data!$J$2051:$J$2550,"Yes") -> 0
A9: School type | D9: School level | G9: Sort by | J9: Direction | L9: Contacts: blanks = not provided in source
A10: District | D10: Elementary | G10: Priority score | J10: Descending
A11: =IF(E8=0,"No matching schools. Change the filters above.","Showing "&MIN(25,E8)&" of "&E8&" matching schools not marked served. Select All to reset each filter.") -> Showing 25 of 45 matching schools not marked served. Select All to reset each filter.
A12: Order | B12: School | C12: Type | D12: Economic % | E12: Enrollment | F12: Fresh miles | G12: Resources ≤1mi | H12: Score /85 | I12: Food evidence | J12: Why it needs attention | K12: Review row | L12: Contact no.
A13: =IF($N13=0,"",1) -> 1 | B13: =IF($N13=0,"",INDEX(Data!$B$2051:$B$2550,$N13)) -> Rhawnhurst School | C13: =IF($N13=0,"",INDEX(Data!$C$2051:$C$2550,$N13)) -> District | D13: =IF($N13=0,"",INDEX(Data!$G$2051:$G$2550,$N13)) -> 0.7637 | E13: =IF($N13=0,"",INDEX(Data!$F$2051:$F$2550,$N13)) -> 584 | F13: =IF($N13=0,"",INDEX(Data!$K$2051:$K$2550,$N13)) -> 0.51437216 | G13: =IF($N13=0,"",INDEX(Data!$L$2051:$L$2550,$N13)) -> 0 | H13: =IF($N13=0,"",INDEX(Data!$T$2051:$T$2550,$N13)) -> 64 | I13: =IF($N13=0,"",INDEX(Data!$U$2051:$U$2550,$N13)) -> Listed | J13: =IF($N13=0,"",INDEX(Data!$AA$2051:$AA$2550,$N13)) -> 76% economic need; 0.51 mi fresh access; 0 nearby resources | K13: =IF($N13=0,"",IF(INDEX(Data!$I$2051:$I$2550,$N13)=0,"Add ID","Row "&(INDEX(Data!$I$2051:$I$2550,$N13)+7))) -> Row 254 | L13: =IF($N13=0,"",IF(INDEX(Data!$AN$2051:$AN$2550,$N13)=0,"",IF(INDEX(Data!$U$41:$U$540,INDEX(Data!$AN$2051:$AN$2550,$N13))="","",INDEX(Data!$U$41:$U$540,INDEX(Data!$AN$2051:$AN$2550,$N13))))) -> 215-400-3220 | N13: =IF(COUNTIFS(Data!$AR$2051:$AR$2550,1)=1,MATCH(1,Data!$AR$2051:$AR$2550,0),0) -> 309
A14: =IF($N14=0,"",2) -> 2 | B14: =IF($N14=0,"",INDEX(Data!$B$2051:$B$2550,$N14)) -> Kennedy C. Crossan School | C14: =IF($N14=0,"",INDEX(Data!$C$2051:$C$2550,$N14)) -> District | D14: =IF($N14=0,"",INDEX(Data!$G$2051:$G$2550,$N14)) -> 0.7358 | E14: =IF($N14=0,"",INDEX(Data!$F$2051:$F$2550,$N14)) -> 318 | F14: =IF($N14=0,"",INDEX(Data!$K$2051:$K$2550,$N14)) -> 0.82466884 | G14: =IF($N14=0,"",INDEX(Data!$L$2051:$L$2550,$N14)) -> 2 | H14: =IF($N14=0,"",INDEX(Data!$T$2051:$T$2550,$N14)) -> 57 | I14: =IF($N14=0,"",INDEX(Data!$U$2051:$U$2550,$N14)) -> Listed | J14: =IF($N14=0,"",INDEX(Data!$AA$2051:$AA$2550,$N14)) -> 74% economic need; 0.82 mi fresh access; 2 nearby resources | K14: =IF($N14=0,"",IF(INDEX(Data!$I$2051:$I$2550,$N14)=0,"Add ID","Row "&(INDEX(Data!$I$2051:$I$2550,$N14)+7))) -> Row 163 | L14: =IF($N14=0,"",IF(INDEX(Data!$AN$2051:$AN$2550,$N14)=0,"",IF(INDEX(Data!$U$41:$U$540,INDEX(Data!$AN$2051:$AN$2550,$N14))="","",INDEX(Data!$U$41:$U$540,INDEX(Data!$AN$2051:$AN$2550,$N14))))) -> 215-400-3160 | N14: =IF(COUNTIFS(Data!$AR$2051:$AR$2550,2)=1,MATCH(2,Data!$AR$2051:$AR$2550,0),0) -> 300
A15: =IF($N15=0,"",3) -> 3 | B15: =IF($N15=0,"",INDEX(Data!$B$2051:$B$2550,$N15)) -> Edwin Forrest School | C15: =IF($N15=0,"",INDEX(Data!$C$2051:$C$2550,$N15)) -> District | D15: =IF($N15=0,"",INDEX(Data!$G$2051:$G$2550,$N15)) -> 0.776 | E15: =IF($N15=0,"",INDEX(Data!$F$2051:$F$2550,$N15)) -> 798 | F15: =IF($N15=0,"",INDEX(Data!$K$2051:$K$2550,$N15)) -> 0.77034598 | G15: =IF($N15=0,"",INDEX(Data!$L$2051:$L$2550,$N15)) -> 3 | H15: =IF($N15=0,"",INDEX(Data!$T$2051:$T$2550,$N15)) -> 55 | I15: =IF($N15=0,"",INDEX(Data!$U$2051:$U$2550,$N15)) -> Listed | J15: =IF($N15=0,"",INDEX(Data!$AA$2051:$AA$2550,$N15)) -> 78% economic need; 0.77 mi fresh access; 3 nearby resources | K15: =IF($N15=0,"",IF(INDEX(Data!$I$2051:$I$2550,$N15)=0,"Add ID","Row "&(INDEX(Data!$I$2051:$I$2550,$N15)+7))) -> Row 65 | L15: =IF($N15=0,"",IF(INDEX(Data!$AN$2051:$AN$2550,$N15)=0,"",IF(INDEX(Data!$U$41:$U$540,INDEX(Data!$AN$2051:$AN$2550,$N15))="","",INDEX(Data!$U$41:$U$540,INDEX(Data!$AN$2051:$AN$2550,$N15))))) -> 215-400-3330 | N15: =IF(COUNTIFS(Data!$AR$2051:$AR$2550,3)=1,MATCH(3,Data!$AR$2051:$AR$2550,0),0) -> 302
A16: =IF($N16=0,"",4) -> 4 | B16: =IF($N16=0,"",INDEX(Data!$B$2051:$B$2550,$N16)) -> Fox Chase School | C16: =IF($N16=0,"",INDEX(Data!$C$2051:$C$2550,$N16)) -> District | D16: =IF($N16=0,"",INDEX(Data!$G$2051:$G$2550,$N16)) -> 0.6847 | E16: =IF($N16=0,"",INDEX(Data!$F$2051:$F$2550,$N16)) -> 500 | F16: =IF($N16=0,"",INDEX(Data!$K$2051:$K$2550,$N16)) -> 0.86765672 | G16: =IF($N16=0,"",INDEX(Data!$L$2051:$L$2550,$N16)) -> 2 | H16: =IF($N16=0,"",INDEX(Data!$T$2051:$T$2550,$N16)) -> 54 | I16: =IF($N16=0,"",INDEX(Data!$U$2051:$U$2550,$N16)) -> Listed | J16: =IF($N16=0,"",INDEX(Data!$AA$2051:$AA$2550,$N16)) -> 68% economic need; 0.87 mi fresh access; 2 nearby resources | K16: =IF($N16=0,"",IF(INDEX(Data!$I$2051:$I$2550,$N16)=0,"Add ID","Row "&(INDEX(Data!$I$2051:$I$2550,$N16)+7))) -> Row 85 | L16: =IF($N16=0,"",IF(INDEX(Data!$AN$2051:$AN$2550,$N16)=0,"",IF(INDEX(Data!$U$41:$U$540,INDEX(Data!$AN$2051:$AN$2550,$N16))="","",INDEX(Data!$U$41:$U$540,INDEX(Data!$AN$2051:$AN$2550,$N16))))) -> 215-400-3170 | N16: =IF(COUNTIFS(Data!$AR$2051:$AR$2550,4)=1,MATCH(4,Data!$AR$2051:$AR$2550,0),0) -> 303
A17: =IF($N17=0,"",5) -> 5 | B17: =IF($N17=0,"",INDEX(Data!$B$2051:$B$2550,$N17)) -> John M. Patterson School | C17: =IF($N17=0,"",INDEX(Data!$C$2051:$C$2550,$N17)) -> District | D17: =IF($N17=0,"",INDEX(Data!$G$2051:$G$2550,$N17)) -> 0.8425 | E17: =IF($N17=0,"",INDEX(Data!$F$2051:$F$2550,$N17)) -> 353 | F17: =IF($N17=0,"",INDEX(Data!$K$2051:$K$2550,$N17)) -> 0.73087419 | G17: =IF($N17=0,"",INDEX(Data!$L$2051:$L$2550,$N17)) -> 3 | H17: =IF($N17=0,"",INDEX(Data!$T$2051:$T$2550,$N17)) -> 53 | I17: =IF($N17=0,"",INDEX(Data!$U$2051:$U$2550,$N17)) -> Listed | J17: =IF($N17=0,"",INDEX(Data!$AA$2051:$AA$2550,$N17)) -> 84% economic need; 0.73 mi fresh access; 3 nearby resources | K17: =IF($N17=0,"",IF(INDEX(Data!$I$2051:$I$2550,$N17)=0,"Add ID","Row "&(INDEX(Data!$I$2051:$I$2550,$N17)+7))) -> Row 148 | L17: =IF($N17=0,"",IF(INDEX(Data!$AN$2051:$AN$2550,$N17)=0,"",IF(INDEX(Data!$U$41:$U$540,INDEX(Data!$AN$2051:$AN$2550,$N17))="","",INDEX(Data!$U$41:$U$540,INDEX(Data!$AN$2051:$AN$2550,$N17))))) -> 215-400-8190 | N17: =IF(COUNTIFS(Data!$AR$2051:$AR$2550,5)=1,MATCH(5,Data!$AR$2051:$AR$2550,0),0) -> 21
A18: =IF($N18=0,"",6) -> 6 | B18: =IF($N18=0,"",INDEX(Data!$B$2051:$B$2550,$N18)) -> J. Hampton Moore School | C18: =IF($N18=0,"",INDEX(Data!$C$2051:$C$2550,$N18)) -> District | D18: =IF($N18=0,"",INDEX(Data!$G$2051:$G$2550,$N18)) -> 0.7795 | E18: =IF($N18=0,"",INDEX(Data!$F$2051:$F$2550,$N18)) -> 1162 | F18: =IF($N18=0,"",INDEX(Data!$K$2051:$K$2550,$N18)) -> 0.48677922 | G18: =IF($N18=0,"",INDEX(Data!$L$2051:$L$2550,$N18)) -> 2 | H18: =IF($N18=0,"",INDEX(Data!$T$2051:$T$2550,$N18)) -> 50 | I18: =IF($N18=0,"",INDEX(Data!$U$2051:$U$2550,$N18)) -> Listed | J18: =IF($N18=0,"",INDEX(Data!$AA$2051:$AA$2550,$N18)) -> 78% economic need; 0.49 mi fresh access; 2 nearby resources | K18: =IF($N18=0,"",IF(INDEX(Data!$I$2051:$I$2550,$N18)=0,"Add ID","Row "&(INDEX(Data!$I$2051:$I$2550,$N18)+7))) -> Row 131 | L18: =IF($N18=0,"",IF(INDEX(Data!$AN$2051:$AN$2550,$N18)=0,"",IF(INDEX(Data!$U$41:$U$540,INDEX(Data!$AN$2051:$AN$2550,$N18))="","",INDEX(Data!$U$41:$U$540,INDEX(Data!$AN$2051:$AN$2550,$N18))))) -> 215-400-3180 | N18: =IF(COUNTIFS(Data!$AR$2051:$AR$2550,6)=1,MATCH(6,Data!$AR$2051:$AR$2550,0),0) -> 306
A19: =IF($N19=0,"",7) -> 7 | B19: =IF($N19=0,"",INDEX(Data!$B$2051:$B$2550,$N19)) -> Henry W. Lawton School | C19: =IF($N19=0,"",INDEX(Data!$C$2051:$C$2550,$N19)) -> District | D19: =IF($N19=0,"",INDEX(Data!$G$2051:$G$2550,$N19)) -> 0.8275 | E19: =IF($N19=0,"",INDEX(Data!$F$2051:$F$2550,$N19)) -> 513 | F19: =IF($N19=0,"",INDEX(Data!$K$2051:$K$2550,$N19)) -> 0.36615105 | G19: =IF($N19=0,"",INDEX(Data!$L$2051:$L$2550,$N19)) -> 3 | H19: =IF($N19=0,"",INDEX(Data!$T$2051:$T$2550,$N19)) -> 49 | I19: =IF($N19=0,"",INDEX(Data!$U$2051:$U$2550,$N19)) -> Listed | J19: =IF($N19=0,"",INDEX(Data!$AA$2051:$AA$2550,$N19)) -> 83% economic need; 0.37 mi fresh access; 3 nearby resources | K19: =IF($N19=0,"",IF(INDEX(Data!$I$2051:$I$2550,$N19)=0,"Add ID","Row "&(INDEX(Data!$I$2051:$I$2550,$N19)+7))) -> Row 119 | L19: =IF($N19=0,"",IF(INDEX(Data!$AN$2051:$AN$2550,$N19)=0,"",IF(INDEX(Data!$U$41:$U$540,INDEX(Data!$AN$2051:$AN$2550,$N19))="","",INDEX(Data!$U$41:$U$540,INDEX(Data!$AN$2051:$AN$2550,$N19))))) -> 215-400-3340 | N19: =IF(COUNTIFS(Data!$AR$2051:$AR$2550,7)=1,MATCH(7,Data!$AR$2051:$AR$2550,0),0) -> 270
A20: =IF($N20=0,"",8) -> 8 | B20: =IF($N20=0,"",INDEX(Data!$B$2051:$B$2550,$N20)) -> Watson Comly School | C20: =IF($N20=0,"",INDEX(Data!$C$2051:$C$2550,$N20)) -> District | D20: =IF($N20=0,"",INDEX(Data!$G$2051:$G$2550,$N20)) -> 0.6656 | E20: =IF($N20=0,"",INDEX(Data!$F$2051:$F$2550,$N20)) -> 660 | F20: =IF($N20=0,"",INDEX(Data!$K$2051:$K$2550,$N20)) -> 0.42671827 | G20: =IF($N20=0,"",INDEX(Data!$L$2051:$L$2550,$N20)) -> 1 | H20: =IF($N20=0,"",INDEX(Data!$T$2051:$T$2550,$N20)) -> 49 | I20: =IF($N20=0,"",INDEX(Data!$U$2051:$U$2550,$N20)) -> Listed | J20: =IF($N20=0,"",INDEX(Data!$AA$2051:$AA$2550,$N20)) -> 67% economic need; 0.43 mi fresh access; 1 nearby resources | K20: =IF($N20=0,"",IF(INDEX(Data!$I$2051:$I$2550,$N20)=0,"Add ID","Row "&(INDEX(Data!$I$2051:$I$2550,$N20)+7))) -> Row 314 | L20: =IF($N20=0,"",IF(INDEX(Data!$AN$2051:$AN$2550,$N20)=0,"",IF(INDEX(Data!$U$41:$U$540,INDEX(Data!$AN$2051:$AN$2550,$N20))="","",INDEX(Data!$U$41:$U$540,INDEX(Data!$AN$2051:$AN$2550,$N20))))) -> 215-400-3010 | N20: =IF(COUNTIFS(Data!$AR$2051:$AR$2550,8)=1,MATCH(8,Data!$AR$2051:$AR$2550,0),0) -> 310
A21: =IF($N21=0,"",9) -> 9 | B21: =IF($N21=0,"",INDEX(Data!$B$2051:$B$2550,$N21)) -> Frances E. Willard School | C21: =IF($N21=0,"",INDEX(Data!$C$2051:$C$2550,$N21)) -> District | D21: =IF($N21=0,"",INDEX(Data!$G$2051:$G$2550,$N21)) -> 0.9342 | E21: =IF($N21=0,"",INDEX(Data!$F$2051:$F$2550,$N21)) -> 352 | F21: =IF($N21=0,"",INDEX(Data!$K$2051:$K$2550,$N21)) -> 0.64030942 | G21: =IF($N21=0,"",INDEX(Data!$L$2051:$L$2550,$N21)) -> 12 | H21: =IF($N21=0,"",INDEX(Data!$T$2051:$T$2550,$N21)) -> 48 | I21: =IF($N21=0,"",INDEX(Data!$U$2051:$U$2550,$N21)) -> Listed | J21: =IF($N21=0,"",INDEX(Data!$AA$2051:$AA$2550,$N21)) -> 93% economic need; 0.64 mi fresh access; 12 nearby resources | K21: =IF($N21=0,"",IF(INDEX(Data!$I$2051:$I$2550,$N21)=0,"Add ID","Row "&(INDEX(Data!$I$2051:$I$2550,$N21)+7))) -> Row 86 | L21: =IF($N21=0,"",IF(INDEX(Data!$AN$2051:$AN$2550,$N21)=0,"",IF(INDEX(Data!$U$41:$U$540,INDEX(Data!$AN$2051:$AN$2550,$N21))="","",INDEX(Data!$U$41:$U$540,INDEX(Data!$AN$2051:$AN$2550,$N21))))) -> 215-400-7180 | N21: =IF(COUNTIFS(Data!$AR$2051:$AR$2550,9)=1,MATCH(9,Data!$AR$2051:$AR$2550,0),0) -> 205
A22: =IF($N22=0,"",10) -> 10 | B22: =IF($N22=0,"",INDEX(Data!$B$2051:$B$2550,$N22)) -> James R. Lowell School | C22: =IF($N22=0,"",INDEX(Data!$C$2051:$C$2550,$N22)) -> District | D22: =IF($N22=0,"",INDEX(Data!$G$2051:$G$2550,$N22)) -> 0.8768 | E22: =IF($N22=0,"",INDEX(Data!$F$2051:$F$2550,$N22)) -> 430 | F22: =IF($N22=0,"",INDEX(Data!$K$2051:$K$2550,$N22)) -> 0.54540436 | G22: =IF($N22=0,"",INDEX(Data!$L$2051:$L$2550,$N22)) -> 4 | H22: =IF($N22=0,"",INDEX(Data!$T$2051:$T$2550,$N22)) -> 48 | I22: =IF($N22=0,"",INDEX(Data!$U$2051:$U$2550,$N22)) -> Listed | J22: =IF($N22=0,"",INDEX(Data!$AA$2051:$AA$2550,$N22)) -> 88% economic need; 0.55 mi fresh access; 4 nearby resources | K22: =IF($N22=0,"",IF(INDEX(Data!$I$2051:$I$2550,$N22)=0,"Add ID","Row "&(INDEX(Data!$I$2051:$I$2550,$N22)+7))) -> Row 136 | L22: =IF($N22=0,"",IF(INDEX(Data!$AN$2051:$AN$2550,$N22)=0,"",IF(INDEX(Data!$U$41:$U$540,INDEX(Data!$AN$2051:$AN$2550,$N22))="","",INDEX(Data!$U$41:$U$540,INDEX(Data!$AN$2051:$AN$2550,$N22))))) -> 215-400-3740 | N22: =IF(COUNTIFS(Data!$AR$2051:$AR$2550,10)=1,MATCH(10,Data!$AR$2051:$AR$2550,0),0) -> 271
A23: =IF($N23=0,"",11) -> 11 | B23: =IF($N23=0,"",INDEX(Data!$B$2051:$B$2550,$N23)) -> James Logan School | C23: =IF($N23=0,"",INDEX(Data!$C$2051:$C$2550,$N23)) -> District | D23: =IF($N23=0,"",INDEX(Data!$G$2051:$G$2550,$N23)) -> 0.9023 | E23: =IF($N23=0,"",INDEX(Data!$F$2051:$F$2550,$N23)) -> 223 | F23: =IF($N23=0,"",INDEX(Data!$K$2051:$K$2550,$N23)) -> 0.69701528 | G23: =IF($N23=0,"",INDEX(Data!$L$2051:$L$2550,$N23)) -> 8 | H23: =IF($N23=0,"",INDEX(Data!$T$2051:$T$2550,$N23)) -> 47 | I23: =IF($N23=0,"",INDEX(Data!$U$2051:$U$2550,$N23)) -> Listed | J23: =IF($N23=0,"",INDEX(Data!$AA$2051:$AA$2550,$N23)) -> 90% economic need; 0.70 mi fresh access; 8 nearby resources | K23: =IF($N23=0,"",IF(INDEX(Data!$I$2051:$I$2550,$N23)=0,"Add ID","Row "&(INDEX(Data!$I$2051:$I$2550,$N23)+7))) -> Row 135 | L23: =IF($N23=0,"",IF(INDEX(Data!$AN$2051:$AN$2550,$N23)=0,"",IF(INDEX(Data!$U$41:$U$540,INDEX(Data!$AN$2051:$AN$2550,$N23))="","",INDEX(Data!$U$41:$U$540,INDEX(Data!$AN$2051:$AN$2550,$N23))))) -> 215-400-3670 | N23: =IF(COUNTIFS(Data!$AR$2051:$AR$2550,11)=1,MATCH(11,Data!$AR$2051:$AR$2550,0),0) -> 236
A24: =IF($N24=0,"",12) -> 12 | B24: =IF($N24=0,"",INDEX(Data!$B$2051:$B$2550,$N24)) -> Solomon Solis-Cohen School | C24: =IF($N24=0,"",INDEX(Data!$C$2051:$C$2550,$N24)) -> District | D24: =IF($N24=0,"",INDEX(Data!$G$2051:$G$2550,$N24)) -> 0.7902 | E24: =IF($N24=0,"",INDEX(Data!$F$2051:$F$2550,$N24)) -> 1354 | F24: =IF($N24=0,"",INDEX(Data!$K$2051:$K$2550,$N24)) -> 0.36391859 | G24: =IF($N24=0,"",INDEX(Data!$L$2051:$L$2550,$N24)) -> 3 | H24: =IF($N24=0,"",INDEX(Data!$T$2051:$T$2550,$N24)) -> 45 | I24: =IF($N24=0,"",INDEX(Data!$U$2051:$U$2550,$N24)) -> Listed | J24: =IF($N24=0,"",INDEX(Data!$AA$2051:$AA$2550,$N24)) -> 79% economic need; 0.36 mi fresh access; 3 nearby resources | K24: =IF($N24=0,"",IF(INDEX(Data!$I$2051:$I$2550,$N24)=0,"Add ID","Row "&(INDEX(Data!$I$2051:$I$2550,$N24)+7))) -> Row 276 | L24: =IF($N24=0,"",IF(INDEX(Data!$AN$2051:$AN$2550,$N24)=0,"",IF(INDEX(Data!$U$41:$U$540,INDEX(Data!$AN$2051:$AN$2550,$N24))="","",INDEX(Data!$U$41:$U$540,INDEX(Data!$AN$2051:$AN$2550,$N24))))) -> 215-400-3250 | N24: =IF(COUNTIFS(Data!$AR$2051:$AR$2550,12)=1,MATCH(12,Data!$AR$2051:$AR$2550,0),0) -> 307
A25: =IF($N25=0,"",13) -> 13 | B25: =IF($N25=0,"",INDEX(Data!$B$2051:$B$2550,$N25)) -> Anne Frank School | C25: =IF($N25=0,"",INDEX(Data!$C$2051:$C$2550,$N25)) -> District | D25: =IF($N25=0,"",INDEX(Data!$G$2051:$G$2550,$N25)) -> 0.6848 | E25: =IF($N25=0,"",INDEX(Data!$F$2051:$F$2550,$N25)) -> 1687 | F25: =IF($N25=0,"",INDEX(Data!$K$2051:$K$2550,$N25)) -> 0.3258615 | G25: =IF($N25=0,"",INDEX(Data!$L$2051:$L$2550,$N25)) -> 2 | H25: =IF($N25=0,"",INDEX(Data!$T$2051:$T$2550,$N25)) -> 45 | I25: =IF($N25=0,"",INDEX(Data!$U$2051:$U$2550,$N25)) -> Listed | J25: =IF($N25=0,"",INDEX(Data!$AA$2051:$AA$2550,$N25)) -> 68% economic need; 0.33 mi fresh access; 2 nearby resources | K25: =IF($N25=0,"",IF(INDEX(Data!$I$2051:$I$2550,$N25)=0,"Add ID","Row "&(INDEX(Data!$I$2051:$I$2550,$N25)+7))) -> Row 29 | L25: =IF($N25=0,"",IF(INDEX(Data!$AN$2051:$AN$2550,$N25)=0,"",IF(INDEX(Data!$U$41:$U$540,INDEX(Data!$AN$2051:$AN$2550,$N25))="","",INDEX(Data!$U$41:$U$540,INDEX(Data!$AN$2051:$AN$2550,$N25))))) -> 215-400-3070 | N25: =IF(COUNTIFS(Data!$AR$2051:$AR$2550,13)=1,MATCH(13,Data!$AR$2051:$AR$2550,0),0) -> 313
A26: =IF($N26=0,"",14) -> 14 | B26: =IF($N26=0,"",INDEX(Data!$B$2051:$B$2550,$N26)) -> Lewis Elkin School | C26: =IF($N26=0,"",INDEX(Data!$C$2051:$C$2550,$N26)) -> District | D26: =IF($N26=0,"",INDEX(Data!$G$2051:$G$2550,$N26)) -> 0.9069 | E26: =IF($N26=0,"",INDEX(Data!$F$2051:$F$2550,$N26)) -> 431 | F26: =IF($N26=0,"",INDEX(Data!$K$2051:$K$2550,$N26)) -> 0.32714422 | G26: =IF($N26=0,"",INDEX(Data!$L$2051:$L$2550,$N26)) -> 10 | H26: =IF($N26=0,"",INDEX(Data!$T$2051:$T$2550,$N26)) -> 43 | I26: =IF($N26=0,"",INDEX(Data!$U$2051:$U$2550,$N26)) -> Listed | J26: =IF($N26=0,"",INDEX(Data!$AA$2051:$AA$2550,$N26)) -> 91% economic need; 0.33 mi fresh access; 10 nearby resources | K26: =IF($N26=0,"",IF(INDEX(Data!$I$2051:$I$2550,$N26)=0,"Add ID","Row "&(INDEX(Data!$I$2051:$I$2550,$N26)+7))) -> Row 178 | L26: =IF($N26=0,"",IF(INDEX(Data!$AN$2051:$AN$2550,$N26)=0,"",IF(INDEX(Data!$U$41:$U$540,INDEX(Data!$AN$2051:$AN$2550,$N26))="","",INDEX(Data!$U$41:$U$540,INDEX(Data!$AN$2051:$AN$2550,$N26))))) -> 215-400-7140 | N26: =IF(COUNTIFS(Data!$AR$2051:$AR$2550,14)=1,MATCH(14,Data!$AR$2051:$AR$2550,0),0) -> 193
A27: =IF($N27=0,"",15) -> 15 | B27: =IF($N27=0,"",INDEX(Data!$B$2051:$B$2550,$N27)) -> Thomas M. Peirce School | C27: =IF($N27=0,"",INDEX(Data!$C$2051:$C$2550,$N27)) -> District | D27: =IF($N27=0,"",INDEX(Data!$G$2051:$G$2550,$N27)) -> 0.9375 | E27: =IF($N27=0,"",INDEX(Data!$F$2051:$F$2550,$N27)) -> 292 | F27: =IF($N27=0,"",INDEX(Data!$K$2051:$K$2550,$N27)) -> 0.26794265 | G27: =IF($N27=0,"",INDEX(Data!$L$2051:$L$2550,$N27)) -> 12 | H27: =IF($N27=0,"",INDEX(Data!$T$2051:$T$2550,$N27)) -> 42 | I27: =IF($N27=0,"",INDEX(Data!$U$2051:$U$2550,$N27)) -> Listed | J27: =IF($N27=0,"",INDEX(Data!$AA$2051:$AA$2550,$N27)) -> 94% economic need; 0.27 mi fresh access; 12 nearby resources | K27: =IF($N27=0,"",IF(INDEX(Data!$I$2051:$I$2550,$N27)=0,"Add ID","Row "&(INDEX(Data!$I$2051:$I$2550,$N27)+7))) -> Row 303 | L27: =IF($N27=0,"",IF(INDEX(Data!$AN$2051:$AN$2550,$N27)=0,"",IF(INDEX(Data!$U$41:$U$540,INDEX(Data!$AN$2051:$AN$2550,$N27))="","",INDEX(Data!$U$41:$U$540,INDEX(Data!$AN$2051:$AN$2550,$N27))))) -> 215-400-7020 | N27: =IF(COUNTIFS(Data!$AR$2051:$AR$2550,15)=1,MATCH(15,Data!$AR$2051:$AR$2550,0),0) -> 170
A28: =IF($N28=0,"",16) -> 16 | B28: =IF($N28=0,"",INDEX(Data!$B$2051:$B$2550,$N28)) -> Prince Hall School | C28: =IF($N28=0,"",INDEX(Data!$C$2051:$C$2550,$N28)) -> District | D28: =IF($N28=0,"",INDEX(Data!$G$2051:$G$2550,$N28)) -> 0.9169 | E28: =IF($N28=0,"",INDEX(Data!$F$2051:$F$2550,$N28)) -> 317 | F28: =IF($N28=0,"",INDEX(Data!$K$2051:$K$2550,$N28)) -> 0.35373086 | G28: =IF($N28=0,"",INDEX(Data!$L$2051:$L$2550,$N28)) -> 12 | H28: =IF($N28=0,"",INDEX(Data!$T$2051:$T$2550,$N28)) -> 42 | I28: =IF($N28=0,"",INDEX(Data!$U$2051:$U$2550,$N28)) -> Listed | J28: =IF($N28=0,"",INDEX(Data!$AA$2051:$AA$2550,$N28)) -> 92% economic need; 0.35 mi fresh access; 12 nearby resources | K28: =IF($N28=0,"",IF(INDEX(Data!$I$2051:$I$2550,$N28)=0,"Add ID","Row "&(INDEX(Data!$I$2051:$I$2550,$N28)+7))) -> Row 252 | L28: =IF($N28=0,"",IF(INDEX(Data!$AN$2051:$AN$2550,$N28)=0,"",IF(INDEX(Data!$U$41:$U$540,INDEX(Data!$AN$2051:$AN$2550,$N28))="","",INDEX(Data!$U$41:$U$540,INDEX(Data!$AN$2051:$AN$2550,$N28))))) -> 215-400-3690 | N28: =IF(COUNTIFS(Data!$AR$2051:$AR$2550,16)=1,MATCH(16,Data!$AR$2051:$AR$2550,0),0) -> 281
A29: =IF($N29=0,"",17) -> 17 | B29: =IF($N29=0,"",INDEX(Data!$B$2051:$B$2550,$N29)) -> William Cramp School | C29: =IF($N29=0,"",INDEX(Data!$C$2051:$C$2550,$N29)) -> District | D29: =IF($N29=0,"",INDEX(Data!$G$2051:$G$2550,$N29)) -> 0.9028 | E29: =IF($N29=0,"",INDEX(Data!$F$2051:$F$2550,$N29)) -> 317 | F29: =IF($N29=0,"",INDEX(Data!$K$2051:$K$2550,$N29)) -> 0.33933365 | G29: =IF($N29=0,"",INDEX(Data!$L$2051:$L$2550,$N29)) -> 13 | H29: =IF($N29=0,"",INDEX(Data!$T$2051:$T$2550,$N29)) -> 42 | I29: =IF($N29=0,"",INDEX(Data!$U$2051:$U$2550,$N29)) -> Listed | J29: =IF($N29=0,"",INDEX(Data!$AA$2051:$AA$2550,$N29)) -> 90% economic need; 0.34 mi fresh access; 13 nearby resources | K29: =IF($N29=0,"",IF(INDEX(Data!$I$2051:$I$2550,$N29)=0,"Add ID","Row "&(INDEX(Data!$I$2051:$I$2550,$N29)+7))) -> Row 321 | L29: =IF($N29=0,"",IF(INDEX(Data!$AN$2051:$AN$2550,$N29)=0,"",IF(INDEX(Data!$U$41:$U$540,INDEX(Data!$AN$2051:$AN$2550,$N29))="","",INDEX(Data!$U$41:$U$540,INDEX(Data!$AN$2051:$AN$2550,$N29))))) -> 215-400-3860 | N29: =IF(COUNTIFS(Data!$AR$2051:$AR$2550,17)=1,MATCH(17,Data!$AR$2051:$AR$2550,0),0) -> 206
A30: =IF($N30=0,"",18) -> 18 | B30: =IF($N30=0,"",INDEX(Data!$B$2051:$B$2550,$N30)) -> John B. Kelly School | C30: =IF($N30=0,"",INDEX(Data!$C$2051:$C$2550,$N30)) -> District | D30: =IF($N30=0,"",INDEX(Data!$G$2051:$G$2550,$N30)) -> 0.8699 | E30: =IF($N30=0,"",INDEX(Data!$F$2051:$F$2550,$N30)) -> 346 | F30: =IF($N30=0,"",INDEX(Data!$K$2051:$K$2550,$N30)) -> 0.63546307 | G30: =IF($N30=0,"",INDEX(Data!$L$2051:$L$2550,$N30)) -> 11 | H30: =IF($N30=0,"",INDEX(Data!$T$2051:$T$2550,$N30)) -> 42 | I30: =IF($N30=0,"",INDEX(Data!$U$2051:$U$2550,$N30)) -> Listed | J30: =IF($N30=0,"",INDEX(Data!$AA$2051:$AA$2550,$N30)) -> 87% economic need; 0.64 mi fresh access; 11 nearby resources | K30: =IF($N30=0,"",IF(INDEX(Data!$I$2051:$I$2550,$N30)=0,"Add ID","Row "&(INDEX(Data!$I$2051:$I$2550,$N30)+7))) -> Row 140 | L30: =IF($N30=0,"",IF(INDEX(Data!$AN$2051:$AN$2550,$N30)=0,"",IF(INDEX(Data!$U$41:$U$540,INDEX(Data!$AN$2051:$AN$2550,$N30))="","",INDEX(Data!$U$41:$U$540,INDEX(Data!$AN$2051:$AN$2550,$N30))))) -> 215-400-3580 | N30: =IF(COUNTIFS(Data!$AR$2051:$AR$2550,18)=1,MATCH(18,Data!$AR$2051:$AR$2550,0),0) -> 249
A31: =IF($N31=0,"",19) -> 19 | B31: =IF($N31=0,"",INDEX(Data!$B$2051:$B$2550,$N31)) -> John Marshall School | C31: =IF($N31=0,"",INDEX(Data!$C$2051:$C$2550,$N31)) -> District | D31: =IF($N31=0,"",INDEX(Data!$G$2051:$G$2550,$N31)) -> 0.8641 | E31: =IF($N31=0,"",INDEX(Data!$F$2051:$F$2550,$N31)) -> 243 | F31: =IF($N31=0,"",INDEX(Data!$K$2051:$K$2550,$N31)) -> 0.57437948 | G31: =IF($N31=0,"",INDEX(Data!$L$2051:$L$2550,$N31)) -> 7 | H31: =IF($N31=0,"",INDEX(Data!$T$2051:$T$2550,$N31)) -> 42 | I31: =IF($N31=0,"",INDEX(Data!$U$2051:$U$2550,$N31)) -> Listed | J31: =IF($N31=0,"",INDEX(Data!$AA$2051:$AA$2550,$N31)) -> 86% economic need; 0.57 mi fresh access; 7 nearby resources | K31: =IF($N31=0,"",IF(INDEX(Data!$I$2051:$I$2550,$N31)=0,"Add ID","Row "&(INDEX(Data!$I$2051:$I$2550,$N31)+7))) -> Row 149 | L31: =IF($N31=0,"",IF(INDEX(Data!$AN$2051:$AN$2550,$N31)=0,"",IF(INDEX(Data!$U$41:$U$540,INDEX(Data!$AN$2051:$AN$2550,$N31))="","",INDEX(Data!$U$41:$U$540,INDEX(Data!$AN$2051:$AN$2550,$N31))))) -> 215-400-3950 | N31: =IF(COUNTIFS(Data!$AR$2051:$AR$2550,19)=1,MATCH(19,Data!$AR$2051:$AR$2550,0),0) -> 272
A32: =IF($N32=0,"",20) -> 20 | B32: =IF($N32=0,"",INDEX(Data!$B$2051:$B$2550,$N32)) -> William Rowen School | C32: =IF($N32=0,"",INDEX(Data!$C$2051:$C$2550,$N32)) -> District | D32: =IF($N32=0,"",INDEX(Data!$G$2051:$G$2550,$N32)) -> 0.8357 | E32: =IF($N32=0,"",INDEX(Data!$F$2051:$F$2550,$N32)) -> 272 | F32: =IF($N32=0,"",INDEX(Data!$K$2051:$K$2550,$N32)) -> 0.69579035 | G32: =IF($N32=0,"",INDEX(Data!$L$2051:$L$2550,$N32)) -> 9 | H32: =IF($N32=0,"",INDEX(Data!$T$2051:$T$2550,$N32)) -> 42 | I32: =IF($N32=0,"",INDEX(Data!$U$2051:$U$2550,$N32)) -> Listed | J32: =IF($N32=0,"",INDEX(Data!$AA$2051:$AA$2550,$N32)) -> 84% economic need; 0.70 mi fresh access; 9 nearby resources | K32: =IF($N32=0,"",IF(INDEX(Data!$I$2051:$I$2550,$N32)=0,"Add ID","Row "&(INDEX(Data!$I$2051:$I$2550,$N32)+7))) -> Row 330 | L32: =IF($N32=0,"",IF(INDEX(Data!$AN$2051:$AN$2550,$N32)=0,"",IF(INDEX(Data!$U$41:$U$540,INDEX(Data!$AN$2051:$AN$2550,$N32))="","",INDEX(Data!$U$41:$U$540,INDEX(Data!$AN$2051:$AN$2550,$N32))))) -> 215-400-3550 | N32: =IF(COUNTIFS(Data!$AR$2051:$AR$2550,20)=1,MATCH(20,Data!$AR$2051:$AR$2550,0),0) -> 284
A33: =IF($N33=0,"",21) -> 21 | B33: =IF($N33=0,"",INDEX(Data!$B$2051:$B$2550,$N33)) -> Richmond School | C33: =IF($N33=0,"",INDEX(Data!$C$2051:$C$2550,$N33)) -> District | D33: =IF($N33=0,"",INDEX(Data!$G$2051:$G$2550,$N33)) -> 0.8192 | E33: =IF($N33=0,"",INDEX(Data!$F$2051:$F$2550,$N33)) -> 332 | F33: =IF($N33=0,"",INDEX(Data!$K$2051:$K$2550,$N33)) -> 0.57120741 | G33: =IF($N33=0,"",INDEX(Data!$L$2051:$L$2550,$N33)) -> 6 | H33: =IF($N33=0,"",INDEX(Data!$T$2051:$T$2550,$N33)) -> 42 | I33: =IF($N33=0,"",INDEX(Data!$U$2051:$U$2550,$N33)) -> Listed | J33: =IF($N33=0,"",INDEX(Data!$AA$2051:$AA$2550,$N33)) -> 82% economic need; 0.57 mi fresh access; 6 nearby resources | K33: =IF($N33=0,"",IF(INDEX(Data!$I$2051:$I$2550,$N33)=0,"Add ID","Row "&(INDEX(Data!$I$2051:$I$2550,$N33)+7))) -> Row 257 | L33: =IF($N33=0,"",IF(INDEX(Data!$AN$2051:$AN$2550,$N33)=0,"",IF(INDEX(Data!$U$41:$U$540,INDEX(Data!$AN$2051:$AN$2550,$N33))="","",INDEX(Data!$U$41:$U$540,INDEX(Data!$AN$2051:$AN$2550,$N33))))) -> 215-400-7150 | N33: =IF(COUNTIFS(Data!$AR$2051:$AR$2550,21)=1,MATCH(21,Data!$AR$2051:$AR$2550,0),0) -> 201
A34: =IF($N34=0,"",22) -> 22 | B34: =IF($N34=0,"",INDEX(Data!$B$2051:$B$2550,$N34)) -> Ellwood School | C34: =IF($N34=0,"",INDEX(Data!$C$2051:$C$2550,$N34)) -> District | D34: =IF($N34=0,"",INDEX(Data!$G$2051:$G$2550,$N34)) -> 0.8007 | E34: =IF($N34=0,"",INDEX(Data!$F$2051:$F$2550,$N34)) -> 252 | F34: =IF($N34=0,"",INDEX(Data!$K$2051:$K$2550,$N34)) -> 0.5681186 | G34: =IF($N34=0,"",INDEX(Data!$L$2051:$L$2550,$N34)) -> 7 | H34: =IF($N34=0,"",INDEX(Data!$T$2051:$T$2550,$N34)) -> 42 | I34: =IF($N34=0,"",INDEX(Data!$U$2051:$U$2550,$N34)) -> Listed | J34: =IF($N34=0,"",INDEX(Data!$AA$2051:$AA$2550,$N34)) -> 80% economic need; 0.57 mi fresh access; 7 nearby resources | K34: =IF($N34=0,"",IF(INDEX(Data!$I$2051:$I$2550,$N34)=0,"Add ID","Row "&(INDEX(Data!$I$2051:$I$2550,$N34)+7))) -> Row 70 | L34: =IF($N34=0,"",IF(INDEX(Data!$AN$2051:$AN$2550,$N34)=0,"",IF(INDEX(Data!$U$41:$U$540,INDEX(Data!$AN$2051:$AN$2550,$N34))="","",INDEX(Data!$U$41:$U$540,INDEX(Data!$AN$2051:$AN$2550,$N34))))) -> 215-400-3540 | N34: =IF(COUNTIFS(Data!$AR$2051:$AR$2550,22)=1,MATCH(22,Data!$AR$2051:$AR$2550,0),0) -> 263
A35: =IF($N35=0,"",23) -> 23 | B35: =IF($N35=0,"",INDEX(Data!$B$2051:$B$2550,$N35)) -> William H. Loesche School | C35: =IF($N35=0,"",INDEX(Data!$C$2051:$C$2550,$N35)) -> District | D35: =IF($N35=0,"",INDEX(Data!$G$2051:$G$2550,$N35)) -> 0.7346 | E35: =IF($N35=0,"",INDEX(Data!$F$2051:$F$2550,$N35)) -> 1276 | F35: =IF($N35=0,"",INDEX(Data!$K$2051:$K$2550,$N35)) -> 0.45647318 | G35: =IF($N35=0,"",INDEX(Data!$L$2051:$L$2550,$N35)) -> 4 | H35: =IF($N35=0,"",INDEX(Data!$T$2051:$T$2550,$N35)) -> 40 | I35: =IF($N35=0,"",INDEX(Data!$U$2051:$U$2550,$N35)) -> Listed | J35: =IF($N35=0,"",INDEX(Data!$AA$2051:$AA$2550,$N35)) -> 73% economic need; 0.46 mi fresh access; 4 nearby resources | K35: =IF($N35=0,"",IF(INDEX(Data!$I$2051:$I$2550,$N35)=0,"Add ID","Row "&(INDEX(Data!$I$2051:$I$2550,$N35)+7))) -> Row 325 | L35: =IF($N35=0,"",IF(INDEX(Data!$AN$2051:$AN$2550,$N35)=0,"",IF(INDEX(Data!$U$41:$U$540,INDEX(Data!$AN$2051:$AN$2550,$N35))="","",INDEX(Data!$U$41:$U$540,INDEX(Data!$AN$2051:$AN$2550,$N35))))) -> 215-400-3020 | N35: =IF(COUNTIFS(Data!$AR$2051:$AR$2550,23)=1,MATCH(23,Data!$AR$2051:$AR$2550,0),0) -> 317
A36: =IF($N36=0,"",24) -> 24 | B36: =IF($N36=0,"",INDEX(Data!$B$2051:$B$2550,$N36)) -> Laura H. Carnell School | C36: =IF($N36=0,"",INDEX(Data!$C$2051:$C$2550,$N36)) -> District | D36: =IF($N36=0,"",INDEX(Data!$G$2051:$G$2550,$N36)) -> 0.7636 | E36: =IF($N36=0,"",INDEX(Data!$F$2051:$F$2550,$N36)) -> 652 | F36: =IF($N36=0,"",INDEX(Data!$K$2051:$K$2550,$N36)) -> 0.38637814 | G36: =IF($N36=0,"",INDEX(Data!$L$2051:$L$2550,$N36)) -> 4 | H36: =IF($N36=0,"",INDEX(Data!$T$2051:$T$2550,$N36)) -> 39 | I36: =IF($N36=0,"",INDEX(Data!$U$2051:$U$2550,$N36)) -> Listed | J36: =IF($N36=0,"",INDEX(Data!$AA$2051:$AA$2550,$N36)) -> 76% economic need; 0.39 mi fresh access; 4 nearby resources | K36: =IF($N36=0,"",IF(INDEX(Data!$I$2051:$I$2550,$N36)=0,"Add ID","Row "&(INDEX(Data!$I$2051:$I$2550,$N36)+7))) -> Row 175 | L36: =IF($N36=0,"",IF(INDEX(Data!$AN$2051:$AN$2550,$N36)=0,"",IF(INDEX(Data!$U$41:$U$540,INDEX(Data!$AN$2051:$AN$2550,$N36))="","",INDEX(Data!$U$41:$U$540,INDEX(Data!$AN$2051:$AN$2550,$N36))))) -> 215-400-3150 | N36: =IF(COUNTIFS(Data!$AR$2051:$AR$2550,24)=1,MATCH(24,Data!$AR$2051:$AR$2550,0),0) -> 262
A37: =IF($N37=0,"",25) -> 25 | B37: =IF($N37=0,"",INDEX(Data!$B$2051:$B$2550,$N37)) -> John H. Webster School | C37: =IF($N37=0,"",INDEX(Data!$C$2051:$C$2550,$N37)) -> District | D37: =IF($N37=0,"",INDEX(Data!$G$2051:$G$2550,$N37)) -> 0.8997 | E37: =IF($N37=0,"",INDEX(Data!$F$2051:$F$2550,$N37)) -> 413 | F37: =IF($N37=0,"",INDEX(Data!$K$2051:$K$2550,$N37)) -> 0.37561574 | G37: =IF($N37=0,"",INDEX(Data!$L$2051:$L$2550,$N37)) -> 7 | H37: =IF($N37=0,"",INDEX(Data!$T$2051:$T$2550,$N37)) -> 38 | I37: =IF($N37=0,"",INDEX(Data!$U$2051:$U$2550,$N37)) -> Listed | J37: =IF($N37=0,"",INDEX(Data!$AA$2051:$AA$2550,$N37)) -> 90% economic need; 0.38 mi fresh access; 7 nearby resources | K37: =IF($N37=0,"",IF(INDEX(Data!$I$2051:$I$2550,$N37)=0,"Add ID","Row "&(INDEX(Data!$I$2051:$I$2550,$N37)+7))) -> Row 147 | L37: =IF($N37=0,"",IF(INDEX(Data!$AN$2051:$AN$2550,$N37)=0,"",IF(INDEX(Data!$U$41:$U$540,INDEX(Data!$AN$2051:$AN$2550,$N37))="","",INDEX(Data!$U$41:$U$540,INDEX(Data!$AN$2051:$AN$2550,$N37))))) -> 215-400-7170 | N37: =IF(COUNTIFS(Data!$AR$2051:$AR$2550,25)=1,MATCH(25,Data!$AR$2051:$AR$2550,0),0) -> 216
A40: Missing-data queue
B41: =COUNTIFS(Data!$H$2051:$H$2550,"Yes",Data!$V$2051:$V$2550,"Missing data")&" schools have no complete score. Find them using School Search > Missing data." -> 12 schools have no complete score. Find them using School Search > Missing data.
A44: Weights | B44: Economic need | C44: Fresh access | D44: Resource gap | E44: Reach
A45: Active | B45: =IF($B$5="Baseline",B46,B47) -> 30 | C45: =IF($B$5="Baseline",C46,C47) -> 25 | D45: =IF($B$5="Baseline",D46,D47) -> 25 | E45: =IF($B$5="Baseline",E46,E47) -> 5
A46: Baseline | B46: 30 | C46: 25 | D46: 25 | E46: 5
A47: Custom | B47: 30 | C47: 25 | D47: 25 | E47: 5
A49: Set Already served to Yes at the indicated Staff Review row. The next candidate replaces it automatically. No means unchecked.
A51: Refresh status | B51: Snapshot 2026-10-09. Install the supplied Windows refresh setup once, then use Data > Refresh All.
A53: Directory 2026–27. Demographics 2025–26. Charter Title I uses last populated 2025–26 designation; confirm before commitment.
A54: Ties follow priority score, economic need, enrollment, then school ID. Level filters match the school classification exactly.

Sheet School Search
A2: School search
A3: Search a name, ZIP or ID. Results update when you press Enter. Top 25 remains independent of these filters.
A4: Search name / ZIP / ID | D4: School type | G4: Results | J4: Page
D5: All | G5: Not marked served | J5: 1
A7: =SUM(Data!$Y$2051:$Y$2550)&" matches. Page "&J5&" of "&MAX(1,ROUNDUP(SUM(Data!$Y$2051:$Y$2550)/20,0)) -> 305 matches. Page 1 of 16
A8: Listed food access is provisional. Blank scores identify missing source data. Open School Profile for the evidence.
A10: Need rank | B10: School | C10: Type | D10: Economic % | E10: Enrollment | F10: Score /85 | G10: Already served | H10: Food evidence | I10: Status | J10: School ID | K10: Review row
A11: =IF($M11=0,"",IF(ISNUMBER(INDEX(Data!$X$2051:$X$2550,$M11)),INDEX(Data!$X$2051:$X$2550,$M11),"")) -> 1 | B11: =IF($M11=0,"",INDEX(Data!$B$2051:$B$2550,$M11)) -> Tacony Academy Charter School | C11: =IF($M11=0,"",INDEX(Data!$C$2051:$C$2550,$M11)) -> Charter | D11: =IF($M11=0,"",IF(ISNUMBER(INDEX(Data!$G$2051:$G$2550,$M11)),INDEX(Data!$G$2051:$G$2550,$M11),"")) -> 0.7204 | E11: =IF($M11=0,"",IF(ISNUMBER(INDEX(Data!$F$2051:$F$2550,$M11)),INDEX(Data!$F$2051:$F$2550,$M11),"")) -> 1090 | F11: =IF($M11=0,"",IF(ISNUMBER(INDEX(Data!$T$2051:$T$2550,$M11)),INDEX(Data!$T$2051:$T$2550,$M11),"")) -> 70 | G11: =IF($M11=0,"",INDEX(Data!$J$2051:$J$2550,$M11)) -> No | H11: =IF($M11=0,"",INDEX(Data!$U$2051:$U$2550,$M11)) -> Listed | I11: =IF($M11=0,"",INDEX(Data!$V$2051:$V$2550,$M11)) -> Candidate | J11: =IF($M11=0,"",INDEX(Data!$A$2051:$A$2550,$M11)) -> 3404 | K11: =IF($M11=0,"",IF(INDEX(Data!$I$2051:$I$2550,$M11)=0,"Add ID","Row "&(INDEX(Data!$I$2051:$I$2550,$M11)+7))) -> Row 287 | M11: =IF(COUNTIFS(Data!$Z$2051:$Z$2550,($J$5-1)*20+1)=1,MATCH(($J$5-1)*20+1,Data!$Z$2051:$Z$2550,0),0) -> 126
A12: =IF($M12=0,"",IF(ISNUMBER(INDEX(Data!$X$2051:$X$2550,$M12)),INDEX(Data!$X$2051:$X$2550,$M12),"")) -> 2 | B12: =IF($M12=0,"",INDEX(Data!$B$2051:$B$2550,$M12)) -> Joseph H. Brown School | C12: =IF($M12=0,"",INDEX(Data!$C$2051:$C$2550,$M12)) -> District | D12: =IF($M12=0,"",IF(ISNUMBER(INDEX(Data!$G$2051:$G$2550,$M12)),INDEX(Data!$G$2051:$G$2550,$M12),"")) -> 0.8056 | E12: =IF($M12=0,"",IF(ISNUMBER(INDEX(Data!$F$2051:$F$2550,$M12)),INDEX(Data!$F$2051:$F$2550,$M12),"")) -> 427 | F12: =IF($M12=0,"",IF(ISNUMBER(INDEX(Data!$T$2051:$T$2550,$M12)),INDEX(Data!$T$2051:$T$2550,$M12),"")) -> 68 | G12: =IF($M12=0,"",INDEX(Data!$J$2051:$J$2550,$M12)) -> No | H12: =IF($M12=0,"",INDEX(Data!$U$2051:$U$2550,$M12)) -> Listed | I12: =IF($M12=0,"",INDEX(Data!$V$2051:$V$2550,$M12)) -> Candidate | J12: =IF($M12=0,"",INDEX(Data!$A$2051:$A$2550,$M12)) -> 8210 | K12: =IF($M12=0,"",IF(INDEX(Data!$I$2051:$I$2550,$M12)=0,"Add ID","Row "&(INDEX(Data!$I$2051:$I$2550,$M12)+7))) -> Row 154 | M12: =IF(COUNTIFS(Data!$Z$2051:$Z$2550,($J$5-1)*20+2)=1,MATCH(($J$5-1)*20+2,Data!$Z$2051:$Z$2550,0),0) -> 299
A13: =IF($M13=0,"",IF(ISNUMBER(INDEX(Data!$X$2051:$X$2550,$M13)),INDEX(Data!$X$2051:$X$2550,$M13),"")) -> 3 | B13: =IF($M13=0,"",INDEX(Data!$B$2051:$B$2550,$M13)) -> New Foundations Charter School | C13: =IF($M13=0,"",INDEX(Data!$C$2051:$C$2550,$M13)) -> Charter | D13: =IF($M13=0,"",IF(ISNUMBER(INDEX(Data!$G$2051:$G$2550,$M13)),INDEX(Data!$G$2051:$G$2550,$M13),"")) -> 0.7084 | E13: =IF($M13=0,"",IF(ISNUMBER(INDEX(Data!$F$2051:$F$2550,$M13)),INDEX(Data!$F$2051:$F$2550,$M13),"")) -> 1538 | F13: =IF($M13=0,"",IF(ISNUMBER(INDEX(Data!$T$2051:$T$2550,$M13)),INDEX(Data!$T$2051:$T$2550,$M13),"")) -> 65 | G13: =IF($M13=0,"",INDEX(Data!$J$2051:$J$2550,$M13)) -> No | H13: =IF($M13=0,"",INDEX(Data!$U$2051:$U$2550,$M13)) -> Listed | I13: =IF($M13=0,"",INDEX(Data!$V$2051:$V$2550,$M13)) -> Candidate | J13: =IF($M13=0,"",INDEX(Data!$A$2051:$A$2550,$M13)) -> 3334 | K13: =IF($M13=0,"",IF(INDEX(Data!$I$2051:$I$2550,$M13)=0,"Add ID","Row "&(INDEX(Data!$I$2051:$I$2550,$M13)+7))) -> Row 211 | M13: =IF(COUNTIFS(Data!$Z$2051:$Z$2550,($J$5-1)*20+3)=1,MATCH(($J$5-1)*20+3,Data!$Z$2051:$Z$2550,0),0) -> 94
A14: =IF($M14=0,"",IF(ISNUMBER(INDEX(Data!$X$2051:$X$2550,$M14)),INDEX(Data!$X$2051:$X$2550,$M14),"")) -> 4 | B14: =IF($M14=0,"",INDEX(Data!$B$2051:$B$2550,$M14)) -> Southwest Leadership Academy Charter School | C14: =IF($M14=0,"",INDEX(Data!$C$2051:$C$2550,$M14)) -> Charter | D14: =IF($M14=0,"",IF(ISNUMBER(INDEX(Data!$G$2051:$G$2550,$M14)),INDEX(Data!$G$2051:$G$2550,$M14),"")) -> 1 | E14: =IF($M14=0,"",IF(ISNUMBER(INDEX(Data!$F$2051:$F$2550,$M14)),INDEX(Data!$F$2051:$F$2550,$M14),"")) -> 690 | F14: =IF($M14=0,"",IF(ISNUMBER(INDEX(Data!$T$2051:$T$2550,$M14)),INDEX(Data!$T$2051:$T$2550,$M14),"")) -> 64 | G14: =IF($M14=0,"",INDEX(Data!$J$2051:$J$2550,$M14)) -> No | H14: =IF($M14=0,"",INDEX(Data!$U$2051:$U$2550,$M14)) -> Listed | I14: =IF($M14=0,"",INDEX(Data!$V$2051:$V$2550,$M14)) -> Candidate | J14: =IF($M14=0,"",INDEX(Data!$A$2051:$A$2550,$M14)) -> 3392 | K14: =IF($M14=0,"",IF(INDEX(Data!$I$2051:$I$2550,$M14)=0,"Add ID","Row "&(INDEX(Data!$I$2051:$I$2550,$M14)+7))) -> Row 280 | M14: =IF(COUNTIFS(Data!$Z$2051:$Z$2550,($J$5-1)*20+4)=1,MATCH(($J$5-1)*20+4,Data!$Z$2051:$Z$2550,0),0) -> 120
A15: =IF($M15=0,"",IF(ISNUMBER(INDEX(Data!$X$2051:$X$2550,$M15)),INDEX(Data!$X$2051:$X$2550,$M15),"")) -> 4 | B15: =IF($M15=0,"",INDEX(Data!$B$2051:$B$2550,$M15)) -> Ad Prima Charter School | C15: =IF($M15=0,"",INDEX(Data!$C$2051:$C$2550,$M15)) -> Charter | D15: =IF($M15=0,"",IF(ISNUMBER(INDEX(Data!$G$2051:$G$2550,$M15)),INDEX(Data!$G$2051:$G$2550,$M15),"")) -> 0.9274 | E15: =IF($M15=0,"",IF(ISNUMBER(INDEX(Data!$F$2051:$F$2550,$M15)),INDEX(Data!$F$2051:$F$2550,$M15),"")) -> 617 | F15: =IF($M15=0,"",IF(ISNUMBER(INDEX(Data!$T$2051:$T$2550,$M15)),INDEX(Data!$T$2051:$T$2550,$M15),"")) -> 64 | G15: =IF($M15=0,"",INDEX(Data!$J$2051:$J$2550,$M15)) -> No | H15: =IF($M15=0,"",INDEX(Data!$U$2051:$U$2550,$M15)) -> Listed | I15: =IF($M15=0,"",INDEX(Data!$V$2051:$V$2550,$M15)) -> Candidate | J15: =IF($M15=0,"",INDEX(Data!$A$2051:$A$2550,$M15)) -> 3379 | K15: =IF($M15=0,"",IF(INDEX(Data!$I$2051:$I$2550,$M15)=0,"Add ID","Row "&(INDEX(Data!$I$2051:$I$2550,$M15)+7))) -> Row 15 | M15: =IF(COUNTIFS(Data!$Z$2051:$Z$2550,($J$5-1)*20+5)=1,MATCH(($J$5-1)*20+5,Data!$Z$2051:$Z$2550,0),0) -> 113
A16: =IF($M16=0,"",IF(ISNUMBER(INDEX(Data!$X$2051:$X$2550,$M16)),INDEX(Data!$X$2051:$X$2550,$M16),"")) -> 4 | B16: =IF($M16=0,"",INDEX(Data!$B$2051:$B$2550,$M16)) -> Rhawnhurst School | C16: =IF($M16=0,"",INDEX(Data!$C$2051:$C$2550,$M16)) -> District | D16: =IF($M16=0,"",IF(ISNUMBER(INDEX(Data!$G$2051:$G$2550,$M16)),INDEX(Data!$G$2051:$G$2550,$M16),"")) -> 0.7637 | E16: =IF($M16=0,"",IF(ISNUMBER(INDEX(Data!$F$2051:$F$2550,$M16)),INDEX(Data!$F$2051:$F$2550,$M16),"")) -> 584 | F16: =IF($M16=0,"",IF(ISNUMBER(INDEX(Data!$T$2051:$T$2550,$M16)),INDEX(Data!$T$2051:$T$2550,$M16),"")) -> 64 | G16: =IF($M16=0,"",INDEX(Data!$J$2051:$J$2550,$M16)) -> No | H16: =IF($M16=0,"",INDEX(Data!$U$2051:$U$2550,$M16)) -> Listed | I16: =IF($M16=0,"",INDEX(Data!$V$2051:$V$2550,$M16)) -> Candidate | J16: =IF($M16=0,"",INDEX(Data!$A$2051:$A$2550,$M16)) -> 8360 | K16: =IF($M16=0,"",IF(INDEX(Data!$I$2051:$I$2550,$M16)=0,"Add ID","Row "&(INDEX(Data!$I$2051:$I$2550,$M16)+7))) -> Row 254 | M16: =IF(COUNTIFS(Data!$Z$2051:$Z$2550,($J$5-1)*20+6)=1,MATCH(($J$5-1)*20+6,Data!$Z$2051:$Z$2550,0),0) -> 309
A17: =IF($M17=0,"",IF(ISNUMBER(INDEX(Data!$X$2051:$X$2550,$M17)),INDEX(Data!$X$2051:$X$2550,$M17),"")) -> 7 | B17: =IF($M17=0,"",INDEX(Data!$B$2051:$B$2550,$M17)) -> Penrose School | C17: =IF($M17=0,"",INDEX(Data!$C$2051:$C$2550,$M17)) -> District | D17: =IF($M17=0,"",IF(ISNUMBER(INDEX(Data!$G$2051:$G$2550,$M17)),INDEX(Data!$G$2051:$G$2550,$M17),"")) -> 0.8372 | E17: =IF($M17=0,"",IF(ISNUMBER(INDEX(Data!$F$2051:$F$2550,$M17)),INDEX(Data!$F$2051:$F$2550,$M17),"")) -> 429 | F17: =IF($M17=0,"",IF(ISNUMBER(INDEX(Data!$T$2051:$T$2550,$M17)),INDEX(Data!$T$2051:$T$2550,$M17),"")) -> 63 | G17: =IF($M17=0,"",INDEX(Data!$J$2051:$J$2550,$M17)) -> No | H17: =IF($M17=0,"",INDEX(Data!$U$2051:$U$2550,$M17)) -> Listed | I17: =IF($M17=0,"",INDEX(Data!$V$2051:$V$2550,$M17)) -> Candidate | J17: =IF($M17=0,"",INDEX(Data!$A$2051:$A$2550,$M17)) -> 1440 | K17: =IF($M17=0,"",IF(INDEX(Data!$I$2051:$I$2550,$M17)=0,"Add ID","Row "&(INDEX(Data!$I$2051:$I$2550,$M17)+7))) -> Row 236 | M17: =IF(COUNTIFS(Data!$Z$2051:$Z$2550,($J$5-1)*20+7)=1,MATCH(($J$5-1)*20+7,Data!$Z$2051:$Z$2550,0),0) -> 24
A18: =IF($M18=0,"",IF(ISNUMBER(INDEX(Data!$X$2051:$X$2550,$M18)),INDEX(Data!$X$2051:$X$2550,$M18),"")) -> 7 | B18: =IF($M18=0,"",INDEX(Data!$B$2051:$B$2550,$M18)) -> Robert E. Lamberton School | C18: =IF($M18=0,"",INDEX(Data!$C$2051:$C$2550,$M18)) -> District | D18: =IF($M18=0,"",IF(ISNUMBER(INDEX(Data!$G$2051:$G$2550,$M18)),INDEX(Data!$G$2051:$G$2550,$M18),"")) -> 0.8355 | E18: =IF($M18=0,"",IF(ISNUMBER(INDEX(Data!$F$2051:$F$2550,$M18)),INDEX(Data!$F$2051:$F$2550,$M18),"")) -> 362 | F18: =IF($M18=0,"",IF(ISNUMBER(INDEX(Data!$T$2051:$T$2550,$M18)),INDEX(Data!$T$2051:$T$2550,$M18),"")) -> 63 | G18: =IF($M18=0,"",INDEX(Data!$J$2051:$J$2550,$M18)) -> No | H18: =IF($M18=0,"",INDEX(Data!$U$2051:$U$2550,$M18)) -> Listed | I18: =IF($M18=0,"",INDEX(Data!$V$2051:$V$2550,$M18)) -> Candidate | J18: =IF($M18=0,"",INDEX(Data!$A$2051:$A$2550,$M18)) -> 4320 | K18: =IF($M18=0,"",IF(INDEX(Data!$I$2051:$I$2550,$M18)=0,"Add ID","Row "&(INDEX(Data!$I$2051:$I$2550,$M18)+7))) -> Row 259 | M18: =IF(COUNTIFS(Data!$Z$2051:$Z$2550,($J$5-1)*20+8)=1,MATCH(($J$5-1)*20+8,Data!$Z$2051:$Z$2550,0),0) -> 166
A19: =IF($M19=0,"",IF(ISNUMBER(INDEX(Data!$X$2051:$X$2550,$M19)),INDEX(Data!$X$2051:$X$2550,$M19),"")) -> 9 | B19: =IF($M19=0,"",INDEX(Data!$B$2051:$B$2550,$M19)) -> Lankenau High School | C19: =IF($M19=0,"",INDEX(Data!$C$2051:$C$2550,$M19)) -> District | D19: =IF($M19=0,"",IF(ISNUMBER(INDEX(Data!$G$2051:$G$2550,$M19)),INDEX(Data!$G$2051:$G$2550,$M19),"")) -> 0.64 | E19: =IF($M19=0,"",IF(ISNUMBER(INDEX(Data!$F$2051:$F$2550,$M19)),INDEX(Data!$F$2051:$F$2550,$M19),"")) -> 225 | F19: =IF($M19=0,"",IF(ISNUMBER(INDEX(Data!$T$2051:$T$2550,$M19)),INDEX(Data!$T$2051:$T$2550,$M19),"")) -> 62 | G19: =IF($M19=0,"",INDEX(Data!$J$2051:$J$2550,$M19)) -> No | H19: =IF($M19=0,"",INDEX(Data!$U$2051:$U$2550,$M19)) -> Listed | I19: =IF($M19=0,"",INDEX(Data!$V$2051:$V$2550,$M19)) -> Candidate | J19: =IF($M19=0,"",INDEX(Data!$A$2051:$A$2550,$M19)) -> 6540 | K19: =IF($M19=0,"",IF(INDEX(Data!$I$2051:$I$2550,$M19)=0,"Add ID","Row "&(INDEX(Data!$I$2051:$I$2550,$M19)+7))) -> Row 174 | M19: =IF(COUNTIFS(Data!$Z$2051:$Z$2550,($J$5-1)*20+9)=1,MATCH(($J$5-1)*20+9,Data!$Z$2051:$Z$2550,0),0) -> 251
A20: =IF($M20=0,"",IF(ISNUMBER(INDEX(Data!$X$2051:$X$2550,$M20)),INDEX(Data!$X$2051:$X$2550,$M20),"")) -> 10 | B20: =IF($M20=0,"",INDEX(Data!$B$2051:$B$2550,$M20)) -> Robert B. Pollock School | C20: =IF($M20=0,"",INDEX(Data!$C$2051:$C$2550,$M20)) -> District | D20: =IF($M20=0,"",IF(ISNUMBER(INDEX(Data!$G$2051:$G$2550,$M20)),INDEX(Data!$G$2051:$G$2550,$M20),"")) -> 0.7341 | E20: =IF($M20=0,"",IF(ISNUMBER(INDEX(Data!$F$2051:$F$2550,$M20)),INDEX(Data!$F$2051:$F$2550,$M20),"")) -> 900 | F20: =IF($M20=0,"",IF(ISNUMBER(INDEX(Data!$T$2051:$T$2550,$M20)),INDEX(Data!$T$2051:$T$2550,$M20),"")) -> 60 | G20: =IF($M20=0,"",INDEX(Data!$J$2051:$J$2550,$M20)) -> No | H20: =IF($M20=0,"",INDEX(Data!$U$2051:$U$2550,$M20)) -> Listed | I20: =IF($M20=0,"",INDEX(Data!$V$2051:$V$2550,$M20)) -> Candidate | J20: =IF($M20=0,"",INDEX(Data!$A$2051:$A$2550,$M20)) -> 8410 | K20: =IF($M20=0,"",IF(INDEX(Data!$I$2051:$I$2550,$M20)=0,"Add ID","Row "&(INDEX(Data!$I$2051:$I$2550,$M20)+7))) -> Row 258 | M20: =IF(COUNTIFS(Data!$Z$2051:$Z$2550,($J$5-1)*20+10)=1,MATCH(($J$5-1)*20+10,Data!$Z$2051:$Z$2550,0),0) -> 314
A21: =IF($M21=0,"",IF(ISNUMBER(INDEX(Data!$X$2051:$X$2550,$M21)),INDEX(Data!$X$2051:$X$2550,$M21),"")) -> 10 | B21: =IF($M21=0,"",INDEX(Data!$B$2051:$B$2550,$M21)) -> Northeast High School | C21: =IF($M21=0,"",INDEX(Data!$C$2051:$C$2550,$M21)) -> District | D21: =IF($M21=0,"",IF(ISNUMBER(INDEX(Data!$G$2051:$G$2550,$M21)),INDEX(Data!$G$2051:$G$2550,$M21),"")) -> 0.7192 | E21: =IF($M21=0,"",IF(ISNUMBER(INDEX(Data!$F$2051:$F$2550,$M21)),INDEX(Data!$F$2051:$F$2550,$M21),"")) -> 3541 | F21: =IF($M21=0,"",IF(ISNUMBER(INDEX(Data!$T$2051:$T$2550,$M21)),INDEX(Data!$T$2051:$T$2550,$M21),"")) -> 60 | G21: =IF($M21=0,"",INDEX(Data!$J$2051:$J$2550,$M21)) -> No | H21: =IF($M21=0,"",INDEX(Data!$U$2051:$U$2550,$M21)) -> Listed | I21: =IF($M21=0,"",INDEX(Data!$V$2051:$V$2550,$M21)) -> Candidate | J21: =IF($M21=0,"",INDEX(Data!$A$2051:$A$2550,$M21)) -> 8020 | K21: =IF($M21=0,"",IF(INDEX(Data!$I$2051:$I$2550,$M21)=0,"Add ID","Row "&(INDEX(Data!$I$2051:$I$2550,$M21)+7))) -> Row 213 | M21: =IF(COUNTIFS(Data!$Z$2051:$Z$2550,($J$5-1)*20+11)=1,MATCH(($J$5-1)*20+11,Data!$Z$2051:$Z$2550,0),0) -> 287
A22: =IF($M22=0,"",IF(ISNUMBER(INDEX(Data!$X$2051:$X$2550,$M22)),INDEX(Data!$X$2051:$X$2550,$M22),"")) -> 10 | B22: =IF($M22=0,"",INDEX(Data!$B$2051:$B$2550,$M22)) -> Aloysius L. Fitzpatrick School | C22: =IF($M22=0,"",INDEX(Data!$C$2051:$C$2550,$M22)) -> District | D22: =IF($M22=0,"",IF(ISNUMBER(INDEX(Data!$G$2051:$G$2550,$M22)),INDEX(Data!$G$2051:$G$2550,$M22),"")) -> 0.7176 | E22: =IF($M22=0,"",IF(ISNUMBER(INDEX(Data!$F$2051:$F$2550,$M22)),INDEX(Data!$F$2051:$F$2550,$M22),"")) -> 868 | F22: =IF($M22=0,"",IF(ISNUMBER(INDEX(Data!$T$2051:$T$2550,$M22)),INDEX(Data!$T$2051:$T$2550,$M22),"")) -> 60 | G22: =IF($M22=0,"",INDEX(Data!$J$2051:$J$2550,$M22)) -> No | H22: =IF($M22=0,"",INDEX(Data!$U$2051:$U$2550,$M22)) -> Listed | I22: =IF($M22=0,"",INDEX(Data!$V$2051:$V$2550,$M22)) -> Candidate | J22: =IF($M22=0,"",INDEX(Data!$A$2051:$A$2550,$M22)) -> 8390 | K22: =IF($M22=0,"",IF(INDEX(Data!$I$2051:$I$2550,$M22)=0,"Add ID","Row "&(INDEX(Data!$I$2051:$I$2550,$M22)+7))) -> Row 23 | M22: =IF(COUNTIFS(Data!$Z$2051:$Z$2550,($J$5-1)*20+12)=1,MATCH(($J$5-1)*20+12,Data!$Z$2051:$Z$2550,0),0) -> 312
A23: =IF($M23=0,"",IF(ISNUMBER(INDEX(Data!$X$2051:$X$2550,$M23)),INDEX(Data!$X$2051:$X$2550,$M23),"")) -> 10 | B23: =IF($M23=0,"",INDEX(Data!$B$2051:$B$2550,$M23)) -> Franklin Towne Charter Elementary School | C23: =IF($M23=0,"",INDEX(Data!$C$2051:$C$2550,$M23)) -> Charter | D23: =IF($M23=0,"",IF(ISNUMBER(INDEX(Data!$G$2051:$G$2550,$M23)),INDEX(Data!$G$2051:$G$2550,$M23),"")) -> 0.6767 | E23: =IF($M23=0,"",IF(ISNUMBER(INDEX(Data!$F$2051:$F$2550,$M23)),INDEX(Data!$F$2051:$F$2550,$M23),"")) -> 958 | F23: =IF($M23=0,"",IF(ISNUMBER(INDEX(Data!$T$2051:$T$2550,$M23)),INDEX(Data!$T$2051:$T$2550,$M23),"")) -> 60 | G23: =IF($M23=0,"",INDEX(Data!$J$2051:$J$2550,$M23)) -> No | H23: =IF($M23=0,"",INDEX(Data!$U$2051:$U$2550,$M23)) -> Listed | I23: =IF($M23=0,"",INDEX(Data!$V$2051:$V$2550,$M23)) -> Candidate | J23: =IF($M23=0,"",INDEX(Data!$A$2051:$A$2550,$M23)) -> 3403 | K23: =IF($M23=0,"",IF(INDEX(Data!$I$2051:$I$2550,$M23)=0,"Add ID","Row "&(INDEX(Data!$I$2051:$I$2550,$M23)+7))) -> Row 92 | M23: =IF(COUNTIFS(Data!$Z$2051:$Z$2550,($J$5-1)*20+13)=1,MATCH(($J$5-1)*20+13,Data!$Z$2051:$Z$2550,0),0) -> 125
A24: =IF($M24=0,"",IF(ISNUMBER(INDEX(Data!$X$2051:$X$2550,$M24)),INDEX(Data!$X$2051:$X$2550,$M24),"")) -> 10 | B24: =IF($M24=0,"",INDEX(Data!$B$2051:$B$2550,$M24)) -> Charles C.A. Baldi Middle School | C24: =IF($M24=0,"",INDEX(Data!$C$2051:$C$2550,$M24)) -> District | D24: =IF($M24=0,"",IF(ISNUMBER(INDEX(Data!$G$2051:$G$2550,$M24)),INDEX(Data!$G$2051:$G$2550,$M24),"")) -> 0.6683 | E24: =IF($M24=0,"",IF(ISNUMBER(INDEX(Data!$F$2051:$F$2550,$M24)),INDEX(Data!$F$2051:$F$2550,$M24),"")) -> 1424 | F24: =IF($M24=0,"",IF(ISNUMBER(INDEX(Data!$T$2051:$T$2550,$M24)),INDEX(Data!$T$2051:$T$2550,$M24),"")) -> 60 | G24: =IF($M24=0,"",INDEX(Data!$J$2051:$J$2550,$M24)) -> No | H24: =IF($M24=0,"",INDEX(Data!$U$2051:$U$2550,$M24)) -> Listed | I24: =IF($M24=0,"",INDEX(Data!$V$2051:$V$2550,$M24)) -> Candidate | J24: =IF($M24=0,"",INDEX(Data!$A$2051:$A$2550,$M24)) -> 8160 | K24: =IF($M24=0,"",IF(INDEX(Data!$I$2051:$I$2550,$M24)=0,"Add ID","Row "&(INDEX(Data!$I$2051:$I$2550,$M24)+7))) -> Row 47 | M24: =IF(COUNTIFS(Data!$Z$2051:$Z$2550,($J$5-1)*20+14)=1,MATCH(($J$5-1)*20+14,Data!$Z$2051:$Z$2550,0),0) -> 296
A25: =IF($M25=0,"",IF(ISNUMBER(INDEX(Data!$X$2051:$X$2550,$M25)),INDEX(Data!$X$2051:$X$2550,$M25),"")) -> 10 | B25: =IF($M25=0,"",INDEX(Data!$B$2051:$B$2550,$M25)) -> Joseph Greenberg School | C25: =IF($M25=0,"",INDEX(Data!$C$2051:$C$2550,$M25)) -> District | D25: =IF($M25=0,"",IF(ISNUMBER(INDEX(Data!$G$2051:$G$2550,$M25)),INDEX(Data!$G$2051:$G$2550,$M25),"")) -> 0.5234 | E25: =IF($M25=0,"",IF(ISNUMBER(INDEX(Data!$F$2051:$F$2550,$M25)),INDEX(Data!$F$2051:$F$2550,$M25),"")) -> 1048 | F25: =IF($M25=0,"",IF(ISNUMBER(INDEX(Data!$T$2051:$T$2550,$M25)),INDEX(Data!$T$2051:$T$2550,$M25),"")) -> 60 | G25: =IF($M25=0,"",INDEX(Data!$J$2051:$J$2550,$M25)) -> No | H25: =IF($M25=0,"",INDEX(Data!$U$2051:$U$2550,$M25)) -> Listed | I25: =IF($M25=0,"",INDEX(Data!$V$2051:$V$2550,$M25)) -> Candidate | J25: =IF($M25=0,"",INDEX(Data!$A$2051:$A$2550,$M25)) -> 8430 | K25: =IF($M25=0,"",IF(INDEX(Data!$I$2051:$I$2550,$M25)=0,"Add ID","Row "&(INDEX(Data!$I$2051:$I$2550,$M25)+7))) -> Row 153 | M25: =IF(COUNTIFS(Data!$Z$2051:$Z$2550,($J$5-1)*20+15)=1,MATCH(($J$5-1)*20+15,Data!$Z$2051:$Z$2550,0),0) -> 316
A26: =IF($M26=0,"",IF(ISNUMBER(INDEX(Data!$X$2051:$X$2550,$M26)),INDEX(Data!$X$2051:$X$2550,$M26),"")) -> 16 | B26: =IF($M26=0,"",INDEX(Data!$B$2051:$B$2550,$M26)) -> Bridesburg School | C26: =IF($M26=0,"",INDEX(Data!$C$2051:$C$2550,$M26)) -> District | D26: =IF($M26=0,"",IF(ISNUMBER(INDEX(Data!$G$2051:$G$2550,$M26)),INDEX(Data!$G$2051:$G$2550,$M26),"")) -> 0.6934 | E26: =IF($M26=0,"",IF(ISNUMBER(INDEX(Data!$F$2051:$F$2550,$M26)),INDEX(Data!$F$2051:$F$2550,$M26),"")) -> 522 | F26: =IF($M26=0,"",IF(ISNUMBER(INDEX(Data!$T$2051:$T$2550,$M26)),INDEX(Data!$T$2051:$T$2550,$M26),"")) -> 59 | G26: =IF($M26=0,"",INDEX(Data!$J$2051:$J$2550,$M26)) -> No | H26: =IF($M26=0,"",INDEX(Data!$U$2051:$U$2550,$M26)) -> Listed | I26: =IF($M26=0,"",INDEX(Data!$V$2051:$V$2550,$M26)) -> Candidate | J26: =IF($M26=0,"",INDEX(Data!$A$2051:$A$2550,$M26)) -> 7470 | K26: =IF($M26=0,"",IF(INDEX(Data!$I$2051:$I$2550,$M26)=0,"Add ID","Row "&(INDEX(Data!$I$2051:$I$2550,$M26)+7))) -> Row 41 | M26: =IF(COUNTIFS(Data!$Z$2051:$Z$2550,($J$5-1)*20+16)=1,MATCH(($J$5-1)*20+16,Data!$Z$2051:$Z$2550,0),0) -> 280
A27: =IF($M27=0,"",IF(ISNUMBER(INDEX(Data!$X$2051:$X$2550,$M27)),INDEX(Data!$X$2051:$X$2550,$M27),"")) -> 17 | B27: =IF($M27=0,"",INDEX(Data!$B$2051:$B$2550,$M27)) -> Kensington High School | C27: =IF($M27=0,"",INDEX(Data!$C$2051:$C$2550,$M27)) -> District | D27: =IF($M27=0,"",IF(ISNUMBER(INDEX(Data!$G$2051:$G$2550,$M27)),INDEX(Data!$G$2051:$G$2550,$M27),"")) -> 0.8519 | E27: =IF($M27=0,"",IF(ISNUMBER(INDEX(Data!$F$2051:$F$2550,$M27)),INDEX(Data!$F$2051:$F$2550,$M27),"")) -> 447 | F27: =IF($M27=0,"",IF(ISNUMBER(INDEX(Data!$T$2051:$T$2550,$M27)),INDEX(Data!$T$2051:$T$2550,$M27),"")) -> 58 | G27: =IF($M27=0,"",INDEX(Data!$J$2051:$J$2550,$M27)) -> No | H27: =IF($M27=0,"",INDEX(Data!$U$2051:$U$2550,$M27)) -> Listed | I27: =IF($M27=0,"",INDEX(Data!$V$2051:$V$2550,$M27)) -> Candidate | J27: =IF($M27=0,"",INDEX(Data!$A$2051:$A$2550,$M27)) -> 5700 | K27: =IF($M27=0,"",IF(INDEX(Data!$I$2051:$I$2550,$M27)=0,"Add ID","Row "&(INDEX(Data!$I$2051:$I$2550,$M27)+7))) -> Row 165 | M27: =IF(COUNTIFS(Data!$Z$2051:$Z$2550,($J$5-1)*20+17)=1,MATCH(($J$5-1)*20+17,Data!$Z$2051:$Z$2550,0),0) -> 221
A28: =IF($M28=0,"",IF(ISNUMBER(INDEX(Data!$X$2051:$X$2550,$M28)),INDEX(Data!$X$2051:$X$2550,$M28),"")) -> 17 | B28: =IF($M28=0,"",INDEX(Data!$B$2051:$B$2550,$M28)) -> Walter B. Saul High School | C28: =IF($M28=0,"",INDEX(Data!$C$2051:$C$2550,$M28)) -> District | D28: =IF($M28=0,"",IF(ISNUMBER(INDEX(Data!$G$2051:$G$2550,$M28)),INDEX(Data!$G$2051:$G$2550,$M28),"")) -> 0.674 | E28: =IF($M28=0,"",IF(ISNUMBER(INDEX(Data!$F$2051:$F$2550,$M28)),INDEX(Data!$F$2051:$F$2550,$M28),"")) -> 406 | F28: =IF($M28=0,"",IF(ISNUMBER(INDEX(Data!$T$2051:$T$2550,$M28)),INDEX(Data!$T$2051:$T$2550,$M28),"")) -> 58 | G28: =IF($M28=0,"",INDEX(Data!$J$2051:$J$2550,$M28)) -> No | H28: =IF($M28=0,"",INDEX(Data!$U$2051:$U$2550,$M28)) -> Listed | I28: =IF($M28=0,"",INDEX(Data!$V$2051:$V$2550,$M28)) -> Candidate | J28: =IF($M28=0,"",INDEX(Data!$A$2051:$A$2550,$M28)) -> 6040 | K28: =IF($M28=0,"",IF(INDEX(Data!$I$2051:$I$2550,$M28)=0,"Add ID","Row "&(INDEX(Data!$I$2051:$I$2550,$M28)+7))) -> Row 312 | M28: =IF(COUNTIFS(Data!$Z$2051:$Z$2550,($J$5-1)*20+18)=1,MATCH(($J$5-1)*20+18,Data!$Z$2051:$Z$2550,0),0) -> 225
A29: =IF($M29=0,"",IF(ISNUMBER(INDEX(Data!$X$2051:$X$2550,$M29)),INDEX(Data!$X$2051:$X$2550,$M29),"")) -> 17 | B29: =IF($M29=0,"",INDEX(Data!$B$2051:$B$2550,$M29)) -> Shawmont School | C29: =IF($M29=0,"",INDEX(Data!$C$2051:$C$2550,$M29)) -> District | D29: =IF($M29=0,"",IF(ISNUMBER(INDEX(Data!$G$2051:$G$2550,$M29)),INDEX(Data!$G$2051:$G$2550,$M29),"")) -> 0.6284 | E29: =IF($M29=0,"",IF(ISNUMBER(INDEX(Data!$F$2051:$F$2550,$M29)),INDEX(Data!$F$2051:$F$2550,$M29),"")) -> 457 | F29: =IF($M29=0,"",IF(ISNUMBER(INDEX(Data!$T$2051:$T$2550,$M29)),INDEX(Data!$T$2051:$T$2550,$M29),"")) -> 58 | G29: =IF($M29=0,"",INDEX(Data!$J$2051:$J$2550,$M29)) -> No | H29: =IF($M29=0,"",INDEX(Data!$U$2051:$U$2550,$M29)) -> Listed | I29: =IF($M29=0,"",INDEX(Data!$V$2051:$V$2550,$M29)) -> Candidate | J29: =IF($M29=0,"",INDEX(Data!$A$2051:$A$2550,$M29)) -> 6380 | K29: =IF($M29=0,"",IF(INDEX(Data!$I$2051:$I$2550,$M29)=0,"Add ID","Row "&(INDEX(Data!$I$2051:$I$2550,$M29)+7))) -> Row 275 | M29: =IF(COUNTIFS(Data!$Z$2051:$Z$2550,($J$5-1)*20+19)=1,MATCH(($J$5-1)*20+19,Data!$Z$2051:$Z$2550,0),0) -> 242
A30: =IF($M30=0,"",IF(ISNUMBER(INDEX(Data!$X$2051:$X$2550,$M30)),INDEX(Data!$X$2051:$X$2550,$M30),"")) -> 20 | B30: =IF($M30=0,"",INDEX(Data!$B$2051:$B$2550,$M30)) -> John F. McCloskey School | C30: =IF($M30=0,"",INDEX(Data!$C$2051:$C$2550,$M30)) -> District | D30: =IF($M30=0,"",IF(ISNUMBER(INDEX(Data!$G$2051:$G$2550,$M30)),INDEX(Data!$G$2051:$G$2550,$M30),"")) -> 0.7557 | E30: =IF($M30=0,"",IF(ISNUMBER(INDEX(Data!$F$2051:$F$2550,$M30)),INDEX(Data!$F$2051:$F$2550,$M30),"")) -> 217 | F30: =IF($M30=0,"",IF(ISNUMBER(INDEX(Data!$T$2051:$T$2550,$M30)),INDEX(Data!$T$2051:$T$2550,$M30),"")) -> 57 | G30: =IF($M30=0,"",INDEX(Data!$J$2051:$J$2550,$M30)) -> No | H30: =IF($M30=0,"",INDEX(Data!$U$2051:$U$2550,$M30)) -> Listed | I30: =IF($M30=0,"",INDEX(Data!$V$2051:$V$2550,$M30)) -> Candidate | J30: =IF($M30=0,"",INDEX(Data!$A$2051:$A$2550,$M30)) -> 6310 | K30: =IF($M30=0,"",IF(INDEX(Data!$I$2051:$I$2550,$M30)=0,"Add ID","Row "&(INDEX(Data!$I$2051:$I$2550,$M30)+7))) -> Row 145 | M30: =IF(COUNTIFS(Data!$Z$2051:$Z$2550,($J$5-1)*20+20)=1,MATCH(($J$5-1)*20+20,Data!$Z$2051:$Z$2550,0),0) -> 237

Sheet School Profile
A2: School profile
A3: Choose a school to see its need, evidence and next action. | K3: =IF(COUNTIFS(Data!$B$2051:$B$2550,B5)=1,MATCH(B5,Data!$B$2051:$B$2550,0),0) -> 1
A4: School | K4: =IF($K$3=0,"",INDEX(Data!$AF$2051:$AF$2550,$K$3)) -> 39.921497
B5: John Bartram High School | K5: =IF($K$3=0,"",INDEX(Data!$AG$2051:$AG$2550,$K$3)) -> -75.234056
K7: =IF($K$3=0,0,INDEX(Data!$AN$2051:$AN$2550,$K$3)) -> 1
A8: School ID | B8: =IF($K$3=0,"",INDEX(Data!$A$2051:$A$2550,$K$3)) -> 1010 | D8: Rubric component | E8: Points
A9: School type | B9: =IF($K$3=0,"",INDEX(Data!$C$2051:$C$2550,$K$3)) -> District | D9: Economic need | E9: =IF($K$3=0,"",IF(ISNUMBER(INDEX(Data!$O$2051:$O$2550,$K$3)),INDEX(Data!$O$2051:$O$2550,$K$3),"")) -> 25
A10: School address | B10: =IF($K$3=0,"",INDEX(Data!$AE$2051:$AE$2550,$K$3)) -> 2401 S 67TH ST | D10: Fresh access | E10: =IF($K$3=0,"",IF(ISNUMBER(INDEX(Data!$P$2051:$P$2550,$K$3)),INDEX(Data!$P$2051:$P$2550,$K$3),"")) -> 10
A11: Economic disadvantage | B11: =IF($K$3=0,"",IF(ISNUMBER(INDEX(Data!$G$2051:$G$2550,$K$3)),INDEX(Data!$G$2051:$G$2550,$K$3),"")) -> 0.8053 | D11: Resource gap | E11: =IF($K$3=0,"",IF(ISNUMBER(INDEX(Data!$Q$2051:$Q$2550,$K$3)),INDEX(Data!$Q$2051:$Q$2550,$K$3),"")) -> 5
A12: Enrollment | B12: =IF($K$3=0,"",IF(ISNUMBER(INDEX(Data!$F$2051:$F$2550,$K$3)),INDEX(Data!$F$2051:$F$2550,$K$3),"")) -> 594 | D12: Reach | E12: =IF($K$3=0,"",IF(ISNUMBER(INDEX(Data!$R$2051:$R$2550,$K$3)),INDEX(Data!$R$2051:$R$2550,$K$3),"")) -> 4
A13: Active priority score /85 | B13: =IF($K$3=0,"",IF(ISNUMBER(INDEX(Data!$T$2051:$T$2550,$K$3)),INDEX(Data!$T$2051:$T$2550,$K$3),"")) -> 44
A14: Baseline score /85 | B14: =IF($K$3=0,"",IF(ISNUMBER(INDEX(Data!$S$2051:$S$2550,$K$3)),INDEX(Data!$S$2051:$S$2550,$K$3),"")) -> 44
A15: Food evidence | B15: =IF($K$3=0,"",INDEX(Data!$U$2051:$U$2550,$K$3)) -> Listed | D15: =IF($K$3=0,"",IF(INDEX(Data!$I$2051:$I$2550,$K$3)=0,"Add the school ID to Staff Review","Update Staff Review row "&(INDEX(Data!$I$2051:$I$2550,$K$3)+7))) -> Update Staff Review row 143
A16: Already served (staff flag) | B16: =IF($K$3=0,"",INDEX(Data!$J$2051:$J$2550,$K$3)) -> No
A17: Outreach status | B17: =IF($K$3=0,"",INDEX(Data!$AH$2051:$AH$2550,$K$3)) -> Not contacted | D17: =IF($K$3=0,"",IF(INDEX(Data!$C$2051:$C$2550,$K$3)="Charter","Confirm current Title I eligibility. Published status used: 2025–26.","District-operated public school.")) -> District-operated public school.
A18: Scope / target status | B18: =IF($K$3=0,"",INDEX(Data!$V$2051:$V$2550,$K$3)) -> Candidate
A20: Fresh access miles | B20: =IF($K$3=0,"",IF(ISNUMBER(INDEX(Data!$K$2051:$K$2550,$K$3)),INDEX(Data!$K$2051:$K$2550,$K$3),"")) -> 0.33978194 | D20: Listed miles do not establish produce quality, affordability or walking access.
A21: Fresh access basis | B21: =IF($K$3=0,"",INDEX(Data!$M$2051:$M$2550,$K$3)) -> Listed
A22: Nearby resources ≤1mi | B22: =IF($K$3=0,"",IF(ISNUMBER(INDEX(Data!$L$2051:$L$2550,$K$3)),INDEX(Data!$L$2051:$L$2550,$K$3),"")) -> 4 | D22: Verified inputs require a date and evidence in Staff Review.
A23: Resource basis | B23: =IF($K$3=0,"",INDEX(Data!$N$2051:$N$2550,$K$3)) -> Listed
A26: Nearest listed supermarket | B26: =IF($K$3=0,"",INDEX(Data!$AC$2051:$AC$2550,$K$3)) -> Cousin's Fresh Market Inc
A27: Retailer address | B27: =IF($K$3=0,"",INDEX(Data!$AD$2051:$AD$2550,$K$3)) -> 6411 Woodland Ave, Philadelphia, PA, 19142
A30: Nearby listed food sites
A31: Active City Food Site candidates within one mile. Check hours, recurrence and eligibility before counting as verified access.
A33: Miles | B33: Food site | C33: Address | E33: Website
A34: =IF($K34=0,"",INDEX(Data!$M$511:$M$1010,$K34)) -> 0.19201505 | B34: =IF($K$3=0,"",IF($K34=0,"No listed candidate within 1 mile",INDEX(Data!$B$511:$B$1010,$K34))) -> Revelation Philadelphia Ministry Inc | C34: =IF($K34=0,"",INDEX(Data!$C$511:$C$1010,$K34)) -> 2561 South 67th St | E34: =IF($K34=0,"",INDEX(Data!$L$511:$L$1010,$K34)) -> https://www.sharefoodprogram.org/ | K34: =IF(COUNTIFS(Data!$N$511:$N$1010,1)=1,MATCH(1,Data!$N$511:$N$1010,0),0) -> 190
A35: =IF($K35=0,"",INDEX(Data!$M$511:$M$1010,$K35)) -> 0.4216979 | B35: =IF($K35=0,"",INDEX(Data!$B$511:$B$1010,$K35)) -> Catholic Social Services Southwest Family Service Center | C35: =IF($K35=0,"",INDEX(Data!$C$511:$C$1010,$K35)) -> 6214 Grays Ave | E35: =IF($K35=0,"",INDEX(Data!$L$511:$L$1010,$K35)) -> https://nutritionaldevelopmentservices.org/ | K35: =IF(COUNTIFS(Data!$N$511:$N$1010,2)=1,MATCH(2,Data!$N$511:$N$1010,0),0) -> 245
A36: =IF($K36=0,"",INDEX(Data!$M$511:$M$1010,$K36)) -> 0.5395979 | B36: =IF($K36=0,"",INDEX(Data!$B$511:$B$1010,$K36)) -> Resurrection Community Church | C36: =IF($K36=0,"",INDEX(Data!$C$511:$C$1010,$K36)) -> 6200 Dicks Ave | E36: =IF($K36=0,"",INDEX(Data!$L$511:$L$1010,$K36)) -> https://www.sharefoodprogram.org/ | K36: =IF(COUNTIFS(Data!$N$511:$N$1010,3)=1,MATCH(3,Data!$N$511:$N$1010,0),0) -> 244
A37: =IF($K37=0,"",INDEX(Data!$M$511:$M$1010,$K37)) -> 0.92788676 | B37: =IF($K37=0,"",INDEX(Data!$B$511:$B$1010,$K37)) -> Ezekiel Baptist Church | C37: =IF($K37=0,"",INDEX(Data!$C$511:$C$1010,$K37)) -> 5701 Grays Ave | E37: =IF($K37=0,"",INDEX(Data!$L$511:$L$1010,$K37)) -> https://www.philabundance.org/ | K37: =IF(COUNTIFS(Data!$N$511:$N$1010,4)=1,MATCH(4,Data!$N$511:$N$1010,0),0) -> 217
A38: =IF($K38=0,"",INDEX(Data!$M$511:$M$1010,$K38)) | B38: =IF($K38=0,"",INDEX(Data!$B$511:$B$1010,$K38)) | C38: =IF($K38=0,"",INDEX(Data!$C$511:$C$1010,$K38)) | E38: =IF($K38=0,"",INDEX(Data!$L$511:$L$1010,$K38)) | K38: =IF(COUNTIFS(Data!$N$511:$N$1010,5)=1,MATCH(5,Data!$N$511:$N$1010,0),0) -> 0
A40: School phone | B40: =IF($K$7=0,"",IF(LEN(INDEX(Data!$U$41:$U$540,$K$7))=0,"Not published",INDEX(Data!$U$41:$U$540,$K$7))) -> 215-400-8100
A41: School website | B41: =IF($K$7=0,"",INDEX(Data!$V$41:$V$540,$K$7)) -> https://bartram.philasd.org/

Sheet Staff Review
A2: Staff review and service list
A3: Filter School name. Set Already served to Yes to remove a school from targets; No means unchecked. Amber cells are editable.
A5: Food evidence is optional for initial targeting. Enter a verified value, date and evidence to replace a listed estimate.
A7: School ID | B7: School name | C7: Already served | D7: Verified fresh miles | E7: Fresh checked | F7: Verified resources ≤1mi | G7: Resources checked | H7: Evidence / notes | I7: Owner | J7: Contact stage | K7: Readiness | L7: Record status
A8: 6090 | B8: =IF(A8="","",IF(COUNTIFS(Data!$A$2:$A$501,A8)=1,INDEX(Data!$B$2:$B$501,MATCH(A8,Data!$A$2:$A$501,0)),"Not in current directory")) -> A. Philip Randolph Career and Technical High School | C8: No | J8: Not contacted | K8: Unknown | L8: =IF(A8="","",IF(COUNTIFS($A$8:$A$507,A8)<>1,"Duplicate ID",IF(COUNTIFS(Data!$A$2:$A$501,A8)<>1,"Not current","Current"))) -> Current
A9: 8010 | B9: =IF(A9="","",IF(COUNTIFS(Data!$A$2:$A$501,A9)=1,INDEX(Data!$B$2:$B$501,MATCH(A9,Data!$A$2:$A$501,0)),"Not in current directory")) -> Abraham Lincoln High School | C9: No | J9: Not contacted | K9: Unknown | L9: =IF(A9="","",IF(COUNTIFS($A$8:$A$507,A9)<>1,"Duplicate ID",IF(COUNTIFS(Data!$A$2:$A$501,A9)<>1,"Not current","Current"))) -> Current
A10: 2520 | B10: =IF(A10="","",IF(COUNTIFS(Data!$A$2:$A$501,A10)=1,INDEX(Data!$B$2:$B$501,MATCH(A10,Data!$A$2:$A$501,0)),"Not in current directory")) -> Abram S. Jenks School | C10: No | J10: Not contacted | K10: Unknown | L10: =IF(A10="","",IF(COUNTIFS($A$8:$A$507,A10)<>1,"Duplicate ID",IF(COUNTIFS(Data!$A$2:$A$501,A10)<>1,"Not current","Current"))) -> Current
A11: 2620 | B11: =IF(A11="","",IF(COUNTIFS(Data!$A$2:$A$501,A11)=1,INDEX(Data!$B$2:$B$501,MATCH(A11,Data!$A$2:$A$501,0)),"Not in current directory")) -> Academy at Palumbo | C11: No | J11: Not contacted | K11: Unknown | L11: =IF(A11="","",IF(COUNTIFS($A$8:$A$507,A11)<>1,"Duplicate ID",IF(COUNTIFS(Data!$A$2:$A$501,A11)<>1,"Not current","Current"))) -> Current
A12: 6480 | B12: =IF(A12="","",IF(COUNTIFS(Data!$A$2:$A$501,A12)=1,INDEX(Data!$B$2:$B$501,MATCH(A12,Data!$A$2:$A$501,0)),"Not in current directory")) -> Academy for the Middle Years at Northwest | C12: No | J12: Not contacted | K12: Unknown | L12: =IF(A12="","",IF(COUNTIFS($A$8:$A$507,A12)<>1,"Duplicate ID",IF(COUNTIFS(Data!$A$2:$A$501,A12)<>1,"Not current","Current"))) -> Current
A13: 2310 | B13: =IF(A13="","",IF(COUNTIFS(Data!$A$2:$A$501,A13)=1,INDEX(Data!$B$2:$B$501,MATCH(A13,Data!$A$2:$A$501,0)),"Not in current directory")) -> Achieve Academy of Philadelphia | C13: No | J13: Not contacted | K13: Unknown | L13: =IF(A13="","",IF(COUNTIFS($A$8:$A$507,A13)<>1,"Duplicate ID",IF(COUNTIFS(Data!$A$2:$A$501,A13)<>1,"Not current","Current"))) -> Current
A14: 3820 | B14: =IF(A14="","",IF(COUNTIFS(Data!$A$2:$A$501,A14)=1,INDEX(Data!$B$2:$B$501,MATCH(A14,Data!$A$2:$A$501,0)),"Not in current directory")) -> Achieve Academy of Philadelphia - East Campus | C14: No | J14: Not contacted | K14: Unknown | L14: =IF(A14="","",IF(COUNTIFS($A$8:$A$507,A14)<>1,"Duplicate ID",IF(COUNTIFS(Data!$A$2:$A$501,A14)<>1,"Not current","Current"))) -> Current
A15: 3379 | B15: =IF(A15="","",IF(COUNTIFS(Data!$A$2:$A$501,A15)=1,INDEX(Data!$B$2:$B$501,MATCH(A15,Data!$A$2:$A$501,0)),"Not in current directory")) -> Ad Prima Charter School | C15: No | J15: Not contacted | K15: Unknown | L15: =IF(A15="","",IF(COUNTIFS($A$8:$A$507,A15)<>1,"Duplicate ID",IF(COUNTIFS(Data!$A$2:$A$501,A15)<>1,"Not current","Current"))) -> Current
A16: 1460 | B16: =IF(A16="","",IF(COUNTIFS(Data!$A$2:$A$501,A16)=1,INDEX(Data!$B$2:$B$501,MATCH(A16,Data!$A$2:$A$501,0)),"Not in current directory")) -> Add B. Anderson School | C16: No | J16: Not contacted | K16: Unknown | L16: =IF(A16="","",IF(COUNTIFS($A$8:$A$507,A16)<>1,"Duplicate ID",IF(COUNTIFS(Data!$A$2:$A$501,A16)<>1,"Not current","Current"))) -> Current
A17: 1470 | B17: =IF(A17="","",IF(COUNTIFS(Data!$A$2:$A$501,A17)=1,INDEX(Data!$B$2:$B$501,MATCH(A17,Data!$A$2:$A$501,0)),"Not in current directory")) -> Alain Locke School | C17: No | J17: Not contacted | K17: Unknown | L17: =IF(A17="","",IF(COUNTIFS($A$8:$A$507,A17)<>1,"Duplicate ID",IF(COUNTIFS(Data!$A$2:$A$501,A17)<>1,"Not current","Current"))) -> Current
A18: 2470 | B18: =IF(A18="","",IF(COUNTIFS(Data!$A$2:$A$501,A18)=1,INDEX(Data!$B$2:$B$501,MATCH(A18,Data!$A$2:$A$501,0)),"Not in current directory")) -> Albert M. Greenfield School | C18: No | J18: Not contacted | K18: Unknown | L18: =IF(A18="","",IF(COUNTIFS($A$8:$A$507,A18)<>1,"Duplicate ID",IF(COUNTIFS(Data!$A$2:$A$501,A18)<>1,"Not current","Current"))) -> Current
A19: 5200 | B19: =IF(A19="","",IF(COUNTIFS(Data!$A$2:$A$501,A19)=1,INDEX(Data!$B$2:$B$501,MATCH(A19,Data!$A$2:$A$501,0)),"Not in current directory")) -> Alexander Adaire School | C19: No | J19: Not contacted | K19: Unknown | L19: =IF(A19="","",IF(COUNTIFS($A$8:$A$507,A19)<>1,"Duplicate ID",IF(COUNTIFS(Data!$A$2:$A$501,A19)<>1,"Not current","Current"))) -> Current
... A336: 3304 | B336: =IF(A336="","",IF(COUNTIFS(Data!$A$2:$A$501,A336)=1,INDEX(Data!$B$2:$B$501,MATCH(A336,Data!$A$2:$A$501,0)),"Not in current directory")) -> YouthBuild Philadelphia Charter School | C336: No | J336: Not contacted | K336: Unknown | L336: =IF(A336="","",IF(COUNTIFS($A$8:$A$507,A336)<>1,"Duplicate ID",IF(COUNTIFS(Data!$A$2:$A$501,A336)<>1,"Not current","Current"))) -> Current
B337: =IF(A337="","",IF(COUNTIFS(Data!$A$2:$A$501,A337)=1,INDEX(Data!$B$2:$B$501,MATCH(A337,Data!$A$2:$A$501,0)),"Not in current directory")) | L337: =IF(A337="","",IF(COUNTIFS($A$8:$A$507,A337)<>1,"Duplicate ID",IF(COUNTIFS(Data!$A$2:$A$501,A337)<>1,"Not current","Current")))
B338: =IF(A338="","",IF(COUNTIFS(Data!$A$2:$A$501,A338)=1,INDEX(Data!$B$2:$B$501,MATCH(A338,Data!$A$2:$A$501,0)),"Not in current directory")) | L338: =IF(A338="","",IF(COUNTIFS($A$8:$A$507,A338)<>1,"Duplicate ID",IF(COUNTIFS(Data!$A$2:$A$501,A338)<>1,"Not current","Current")))
B339: =IF(A339="","",IF(COUNTIFS(Data!$A$2:$A$501,A339)=1,INDEX(Data!$B$2:$B$501,MATCH(A339,Data!$A$2:$A$501,0)),"Not in current directory")) | L339: =IF(A339="","",IF(COUNTIFS($A$8:$A$507,A339)<>1,"Duplicate ID",IF(COUNTIFS(Data!$A$2:$A$501,A339)<>1,"Not current","Current")))
B340: =IF(A340="","",IF(COUNTIFS(Data!$A$2:$A$501,A340)=1,INDEX(Data!$B$2:$B$501,MATCH(A340,Data!$A$2:$A$501,0)),"Not in current directory")) | L340: =IF(A340="","",IF(COUNTIFS($A$8:$A$507,A340)<>1,"Duplicate ID",IF(COUNTIFS(Data!$A$2:$A$501,A340)<>1,"Not current","Current")))
B341: =IF(A341="","",IF(COUNTIFS(Data!$A$2:$A$501,A341)=1,INDEX(Data!$B$2:$B$501,MATCH(A341,Data!$A$2:$A$501,0)),"Not in current directory")) | L341: =IF(A341="","",IF(COUNTIFS($A$8:$A$507,A341)<>1,"Duplicate ID",IF(COUNTIFS(Data!$A$2:$A$501,A341)<>1,"Not current","Current")))
B342: =IF(A342="","",IF(COUNTIFS(Data!$A$2:$A$501,A342)=1,INDEX(Data!$B$2:$B$501,MATCH(A342,Data!$A$2:$A$501,0)),"Not in current directory")) | L342: =IF(A342="","",IF(COUNTIFS($A$8:$A$507,A342)<>1,"Duplicate ID",IF(COUNTIFS(Data!$A$2:$A$501,A342)<>1,"Not current","Current")))
B343: =IF(A343="","",IF(COUNTIFS(Data!$A$2:$A$501,A343)=1,INDEX(Data!$B$2:$B$501,MATCH(A343,Data!$A$2:$A$501,0)),"Not in current directory")) | L343: =IF(A343="","",IF(COUNTIFS($A$8:$A$507,A343)<>1,"Duplicate ID",IF(COUNTIFS(Data!$A$2:$A$501,A343)<>1,"Not current","Current")))
B344: =IF(A344="","",IF(COUNTIFS(Data!$A$2:$A$501,A344)=1,INDEX(Data!$B$2:$B$501,MATCH(A344,Data!$A$2:$A$501,0)),"Not in current directory")) | L344: =IF(A344="","",IF(COUNTIFS($A$8:$A$507,A344)<>1,"Duplicate ID",IF(COUNTIFS(Data!$A$2:$A$501,A344)<>1,"Not current","Current")))
B345: =IF(A345="","",IF(COUNTIFS(Data!$A$2:$A$501,A345)=1,INDEX(Data!$B$2:$B$501,MATCH(A345,Data!$A$2:$A$501,0)),"Not in current directory")) | L345: =IF(A345="","",IF(COUNTIFS($A$8:$A$507,A345)<>1,"Duplicate ID",IF(COUNTIFS(Data!$A$2:$A$501,A345)<>1,"Not current","Current")))
B346: =IF(A346="","",IF(COUNTIFS(Data!$A$2:$A$501,A346)=1,INDEX(Data!$B$2:$B$501,MATCH(A346,Data!$A$2:$A$501,0)),"Not in current directory")) | L346: =IF(A346="","",IF(COUNTIFS($A$8:$A$507,A346)<>1,"Duplicate ID",IF(COUNTIFS(Data!$A$2:$A$501,A346)<>1,"Not current","Current")))
B347: =IF(A347="","",IF(COUNTIFS(Data!$A$2:$A$501,A347)=1,INDEX(Data!$B$2:$B$501,MATCH(A347,Data!$A$2:$A$501,0)),"Not in current directory")) | L347: =IF(A347="","",IF(COUNTIFS($A$8:$A$507,A347)<>1,"Duplicate ID",IF(COUNTIFS(Data!$A$2:$A$501,A347)<>1,"Not current","Current")))
B348: =IF(A348="","",IF(COUNTIFS(Data!$A$2:$A$501,A348)=1,INDEX(Data!$B$2:$B$501,MATCH(A348,Data!$A$2:$A$501,0)),"Not in current directory")) | L348: =IF(A348="","",IF(COUNTIFS($A$8:$A$507,A348)<>1,"Duplicate ID",IF(COUNTIFS(Data!$A$2:$A$501,A348)<>1,"Not current","Current")))
... B507: =IF(A507="","",IF(COUNTIFS(Data!$A$2:$A$501,A507)=1,INDEX(Data!$B$2:$B$501,MATCH(A507,Data!$A$2:$A$501,0)),"Not in current directory")) | L507: =IF(A507="","",IF(COUNTIFS($A$8:$A$507,A507)<>1,"Duplicate ID",IF(COUNTIFS(Data!$A$2:$A$501,A507)<>1,"Not current","Current")))

Sheet Master_rankableSchools
A2: All rankable schools
A3: Use the controls below to filter all rankable schools and choose the sort order.
A9: School type | D9: School level | G9: Sort by | J9: Direction | M9: Contacts: blanks = not provided in source
A10: All | D10: All | G10: Priority score | J10: Descending
A11: =IF(SUM(Data!$AT$2051:$AT$2550)=0,"No matching schools. Change the filters above.",SUM(Data!$AT$2051:$AT$2550)&" matching rankable schools. Select All to reset each filter.") -> 293 matching rankable schools. Select All to reset each filter.
A12: Order | B12: School | C12: Type | D12: School level | E12: Economic % | F12: Enrollment | G12: Fresh miles | H12: Resources ≤1mi | I12: Score /85 | J12: Food evidence | K12: Why it needs attention | L12: Contact no. | M12: Source row | N12: Review row2
A13: =IF($M13=0,"",INDEX(Data!$W$2051:$W$2550,$M13)) -> 1 | B13: =IF($M13=0,"",INDEX(Data!$B$2051:$B$2550,$M13)) -> Tacony Academy Charter School | C13: =IF($M13=0,"",INDEX(Data!$C$2051:$C$2550,$M13)) -> Charter | D13: =IF($M13=0,"",INDEX(Data!$D$2051:$D$2550,$M13)) -> Elementary-Middle-High | E13: =IF($M13=0,"",INDEX(Data!$G$2051:$G$2550,$M13)) -> 0.7204 | F13: =IF($M13=0,"",INDEX(Data!$F$2051:$F$2550,$M13)) -> 1090 | G13: =IF($M13=0,"",INDEX(Data!$K$2051:$K$2550,$M13)) -> 0.77847906 | H13: =IF($M13=0,"",INDEX(Data!$L$2051:$L$2550,$M13)) -> 0 | I13: =IF($M13=0,"",INDEX(Data!$T$2051:$T$2550,$M13)) -> 70 | J13: =IF($M13=0,"",INDEX(Data!$U$2051:$U$2550,$M13)) -> Listed | K13: =IF($M13=0,"",INDEX(Data!$AA$2051:$AA$2550,$M13)) -> 72% economic need; 0.78 mi fresh access; 0 nearby resources | L13: =IF($M13=0,"",IF(INDEX(Data!$AN$2051:$AN$2550,$M13)=0,"",IF(INDEX(Data!$U$41:$U$540,INDEX(Data!$AN$2051:$AN$2550,$M13))="","",INDEX(Data!$U$41:$U$540,INDEX(Data!$AN$2051:$AN$2550,$M13))))) | M13: =IF(COUNTIFS(Data!$AV$2051:$AV$2550,1)=1,MATCH(1,Data!$AV$2051:$AV$2550,0),0) -> 126 | N13: =IF($M13=0,"",IF(INDEX(Data!$I$2051:$I$2550,$M13)=0,"Add ID","Row "&(INDEX(Data!$I$2051:$I$2550,$M13)+7))) -> Row 287
A14: =IF($M14=0,"",INDEX(Data!$W$2051:$W$2550,$M14)) -> 2 | B14: =IF($M14=0,"",INDEX(Data!$B$2051:$B$2550,$M14)) -> Joseph H. Brown School | C14: =IF($M14=0,"",INDEX(Data!$C$2051:$C$2550,$M14)) -> District | D14: =IF($M14=0,"",INDEX(Data!$D$2051:$D$2550,$M14)) -> Elementary-Middle | E14: =IF($M14=0,"",INDEX(Data!$G$2051:$G$2550,$M14)) -> 0.8056 | F14: =IF($M14=0,"",INDEX(Data!$F$2051:$F$2550,$M14)) -> 427 | G14: =IF($M14=0,"",INDEX(Data!$K$2051:$K$2550,$M14)) -> 0.9942284 | H14: =IF($M14=0,"",INDEX(Data!$L$2051:$L$2550,$M14)) -> 1 | I14: =IF($M14=0,"",INDEX(Data!$T$2051:$T$2550,$M14)) -> 68 | J14: =IF($M14=0,"",INDEX(Data!$U$2051:$U$2550,$M14)) -> Listed | K14: =IF($M14=0,"",INDEX(Data!$AA$2051:$AA$2550,$M14)) -> 81% economic need; 0.99 mi fresh access; 1 nearby resources | L14: =IF($M14=0,"",IF(INDEX(Data!$AN$2051:$AN$2550,$M14)=0,"",IF(INDEX(Data!$U$41:$U$540,INDEX(Data!$AN$2051:$AN$2550,$M14))="","",INDEX(Data!$U$41:$U$540,INDEX(Data!$AN$2051:$AN$2550,$M14))))) -> 215-400-3320 | M14: =IF(COUNTIFS(Data!$AV$2051:$AV$2550,2)=1,MATCH(2,Data!$AV$2051:$AV$2550,0),0) -> 299 | N14: =IF($M14=0,"",IF(INDEX(Data!$I$2051:$I$2550,$M14)=0,"Add ID","Row "&(INDEX(Data!$I$2051:$I$2550,$M14)+7))) -> Row 154
A15: =IF($M15=0,"",INDEX(Data!$W$2051:$W$2550,$M15)) -> 3 | B15: =IF($M15=0,"",INDEX(Data!$B$2051:$B$2550,$M15)) -> New Foundations Charter School | C15: =IF($M15=0,"",INDEX(Data!$C$2051:$C$2550,$M15)) -> Charter | D15: =IF($M15=0,"",INDEX(Data!$D$2051:$D$2550,$M15)) -> Elementary-Middle-High | E15: =IF($M15=0,"",INDEX(Data!$G$2051:$G$2550,$M15)) -> 0.7084 | F15: =IF($M15=0,"",INDEX(Data!$F$2051:$F$2550,$M15)) -> 1538 | G15: =IF($M15=0,"",INDEX(Data!$K$2051:$K$2550,$M15)) -> 1.3873237 | H15: =IF($M15=0,"",INDEX(Data!$L$2051:$L$2550,$M15)) -> 2 | I15: =IF($M15=0,"",INDEX(Data!$T$2051:$T$2550,$M15)) -> 65 | J15: =IF($M15=0,"",INDEX(Data!$U$2051:$U$2550,$M15)) -> Listed | K15: =IF($M15=0,"",INDEX(Data!$AA$2051:$AA$2550,$M15)) -> 71% economic need; 1.39 mi fresh access; 2 nearby resources | L15: =IF($M15=0,"",IF(INDEX(Data!$AN$2051:$AN$2550,$M15)=0,"",IF(INDEX(Data!$U$41:$U$540,INDEX(Data!$AN$2051:$AN$2550,$M15))="","",INDEX(Data!$U$41:$U$540,INDEX(Data!$AN$2051:$AN$2550,$M15))))) -> 215-624-8100 | M15: =IF(COUNTIFS(Data!$AV$2051:$AV$2550,3)=1,MATCH(3,Data!$AV$2051:$AV$2550,0),0) -> 94 | N15: =IF($M15=0,"",IF(INDEX(Data!$I$2051:$I$2550,$M15)=0,"Add ID","Row "&(INDEX(Data!$I$2051:$I$2550,$M15)+7))) -> Row 211
A16: =IF($M16=0,"",INDEX(Data!$W$2051:$W$2550,$M16)) -> 4 | B16: =IF($M16=0,"",INDEX(Data!$B$2051:$B$2550,$M16)) -> Southwest Leadership Academy Charter School | C16: =IF($M16=0,"",INDEX(Data!$C$2051:$C$2550,$M16)) -> Charter | D16: =IF($M16=0,"",INDEX(Data!$D$2051:$D$2550,$M16)) -> Elementary-Middle | E16: =IF($M16=0,"",INDEX(Data!$G$2051:$G$2550,$M16)) -> 1 | F16: =IF($M16=0,"",INDEX(Data!$F$2051:$F$2550,$M16)) -> 690 | G16: =IF($M16=0,"",INDEX(Data!$K$2051:$K$2550,$M16)) -> 0.74331399 | H16: =IF($M16=0,"",INDEX(Data!$L$2051:$L$2550,$M16)) -> 2 | I16: =IF($M16=0,"",INDEX(Data!$T$2051:$T$2550,$M16)) -> 64 | J16: =IF($M16=0,"",INDEX(Data!$U$2051:$U$2550,$M16)) -> Listed | K16: =IF($M16=0,"",INDEX(Data!$AA$2051:$AA$2550,$M16)) -> 100% economic need; 0.74 mi fresh access; 2 nearby resources | L16: =IF($M16=0,"",IF(INDEX(Data!$AN$2051:$AN$2550,$M16)=0,"",IF(INDEX(Data!$U$41:$U$540,INDEX(Data!$AN$2051:$AN$2550,$M16))="","",INDEX(Data!$U$41:$U$540,INDEX(Data!$AN$2051:$AN$2550,$M16))))) -> 215-729-1939 | M16: =IF(COUNTIFS(Data!$AV$2051:$AV$2550,4)=1,MATCH(4,Data!$AV$2051:$AV$2550,0),0) -> 120 | N16: =IF($M16=0,"",IF(INDEX(Data!$I$2051:$I$2550,$M16)=0,"Add ID","Row "&(INDEX(Data!$I$2051:$I$2550,$M16)+7))) -> Row 280
A17: =IF($M17=0,"",INDEX(Data!$W$2051:$W$2550,$M17)) -> 5 | B17: =IF($M17=0,"",INDEX(Data!$B$2051:$B$2550,$M17)) -> Ad Prima Charter School | C17: =IF($M17=0,"",INDEX(Data!$C$2051:$C$2550,$M17)) -> Charter | D17: =IF($M17=0,"",INDEX(Data!$D$2051:$D$2550,$M17)) -> Elementary-Middle | E17: =IF($M17=0,"",INDEX(Data!$G$2051:$G$2550,$M17)) -> 0.9274 | F17: =IF($M17=0,"",INDEX(Data!$F$2051:$F$2550,$M17)) -> 617 | G17: =IF($M17=0,"",INDEX(Data!$K$2051:$K$2550,$M17)) -> 1.2644636 | H17: =IF($M17=0,"",INDEX(Data!$L$2051:$L$2550,$M17)) -> 4 | I17: =IF($M17=0,"",INDEX(Data!$T$2051:$T$2550,$M17)) -> 64 | J17: =IF($M17=0,"",INDEX(Data!$U$2051:$U$2550,$M17)) -> Listed | K17: =IF($M17=0,"",INDEX(Data!$AA$2051:$AA$2550,$M17)) -> 93% economic need; 1.26 mi fresh access; 4 nearby resources | L17: =IF($M17=0,"",IF(INDEX(Data!$AN$2051:$AN$2550,$M17)=0,"",IF(INDEX(Data!$U$41:$U$540,INDEX(Data!$AN$2051:$AN$2550,$M17))="","",INDEX(Data!$U$41:$U$540,INDEX(Data!$AN$2051:$AN$2550,$M17))))) -> 267-403-2672 | M17: =IF(COUNTIFS(Data!$AV$2051:$AV$2550,5)=1,MATCH(5,Data!$AV$2051:$AV$2550,0),0) -> 113 | N17: =IF($M17=0,"",IF(INDEX(Data!$I$2051:$I$2550,$M17)=0,"Add ID","Row "&(INDEX(Data!$I$2051:$I$2550,$M17)+7))) -> Row 15
A18: =IF($M18=0,"",INDEX(Data!$W$2051:$W$2550,$M18)) -> 6 | B18: =IF($M18=0,"",INDEX(Data!$B$2051:$B$2550,$M18)) -> Rhawnhurst School | C18: =IF($M18=0,"",INDEX(Data!$C$2051:$C$2550,$M18)) -> District | D18: =IF($M18=0,"",INDEX(Data!$D$2051:$D$2550,$M18)) -> Elementary | E18: =IF($M18=0,"",INDEX(Data!$G$2051:$G$2550,$M18)) -> 0.7637 | F18: =IF($M18=0,"",INDEX(Data!$F$2051:$F$2550,$M18)) -> 584 | G18: =IF($M18=0,"",INDEX(Data!$K$2051:$K$2550,$M18)) -> 0.51437216 | H18: =IF($M18=0,"",INDEX(Data!$L$2051:$L$2550,$M18)) -> 0 | I18: =IF($M18=0,"",INDEX(Data!$T$2051:$T$2550,$M18)) -> 64 | J18: =IF($M18=0,"",INDEX(Data!$U$2051:$U$2550,$M18)) -> Listed | K18: =IF($M18=0,"",INDEX(Data!$AA$2051:$AA$2550,$M18)) -> 76% economic need; 0.51 mi fresh access; 0 nearby resources | L18: =IF($M18=0,"",IF(INDEX(Data!$AN$2051:$AN$2550,$M18)=0,"",IF(INDEX(Data!$U$41:$U$540,INDEX(Data!$AN$2051:$AN$2550,$M18))="","",INDEX(Data!$U$41:$U$540,INDEX(Data!$AN$2051:$AN$2550,$M18))))) -> 215-400-3220 | M18: =IF(COUNTIFS(Data!$AV$2051:$AV$2550,6)=1,MATCH(6,Data!$AV$2051:$AV$2550,0),0) -> 309 | N18: =IF($M18=0,"",IF(INDEX(Data!$I$2051:$I$2550,$M18)=0,"Add ID","Row "&(INDEX(Data!$I$2051:$I$2550,$M18)+7))) -> Row 254
A19: =IF($M19=0,"",INDEX(Data!$W$2051:$W$2550,$M19)) -> 7 | B19: =IF($M19=0,"",INDEX(Data!$B$2051:$B$2550,$M19)) -> Penrose School | C19: =IF($M19=0,"",INDEX(Data!$C$2051:$C$2550,$M19)) -> District | D19: =IF($M19=0,"",INDEX(Data!$D$2051:$D$2550,$M19)) -> Elementary-Middle | E19: =IF($M19=0,"",INDEX(Data!$G$2051:$G$2550,$M19)) -> 0.8372 | F19: =IF($M19=0,"",INDEX(Data!$F$2051:$F$2550,$M19)) -> 429 | G19: =IF($M19=0,"",INDEX(Data!$K$2051:$K$2550,$M19)) -> 0.50154309 | H19: =IF($M19=0,"",INDEX(Data!$L$2051:$L$2550,$M19)) -> 1 | I19: =IF($M19=0,"",INDEX(Data!$T$2051:$T$2550,$M19)) -> 63 | J19: =IF($M19=0,"",INDEX(Data!$U$2051:$U$2550,$M19)) -> Listed | K19: =IF($M19=0,"",INDEX(Data!$AA$2051:$AA$2550,$M19)) -> 84% economic need; 0.50 mi fresh access; 1 nearby resources | L19: =IF($M19=0,"",IF(INDEX(Data!$AN$2051:$AN$2550,$M19)=0,"",IF(INDEX(Data!$U$41:$U$540,INDEX(Data!$AN$2051:$AN$2550,$M19))="","",INDEX(Data!$U$41:$U$540,INDEX(Data!$AN$2051:$AN$2550,$M19))))) -> 215-400-8310 | M19: =IF(COUNTIFS(Data!$AV$2051:$AV$2550,7)=1,MATCH(7,Data!$AV$2051:$AV$2550,0),0) -> 24 | N19: =IF($M19=0,"",IF(INDEX(Data!$I$2051:$I$2550,$M19)=0,"Add ID","Row "&(INDEX(Data!$I$2051:$I$2550,$M19)+7))) -> Row 236
A20: =IF($M20=0,"",INDEX(Data!$W$2051:$W$2550,$M20)) -> 8 | B20: =IF($M20=0,"",INDEX(Data!$B$2051:$B$2550,$M20)) -> Robert E. Lamberton School | C20: =IF($M20=0,"",INDEX(Data!$C$2051:$C$2550,$M20)) -> District | D20: =IF($M20=0,"",INDEX(Data!$D$2051:$D$2550,$M20)) -> Elementary-Middle | E20: =IF($M20=0,"",INDEX(Data!$G$2051:$G$2550,$M20)) -> 0.8355 | F20: =IF($M20=0,"",INDEX(Data!$F$2051:$F$2550,$M20)) -> 362 | G20: =IF($M20=0,"",INDEX(Data!$K$2051:$K$2550,$M20)) -> 0.31893514 | H20: =IF($M20=0,"",INDEX(Data!$L$2051:$L$2550,$M20)) -> 0 | I20: =IF($M20=0,"",INDEX(Data!$T$2051:$T$2550,$M20)) -> 63 | J20: =IF($M20=0,"",INDEX(Data!$U$2051:$U$2550,$M20)) -> Listed | K20: =IF($M20=0,"",INDEX(Data!$AA$2051:$AA$2550,$M20)) -> 84% economic need; 0.32 mi fresh access; 0 nearby resources | L20: =IF($M20=0,"",IF(INDEX(Data!$AN$2051:$AN$2550,$M20)=0,"",IF(INDEX(Data!$U$41:$U$540,INDEX(Data!$AN$2051:$AN$2550,$M20))="","",INDEX(Data!$U$41:$U$540,INDEX(Data!$AN$2051:$AN$2550,$M20))))) -> 215-400-7530 | M20: =IF(COUNTIFS(Data!$AV$2051:$AV$2550,8)=1,MATCH(8,Data!$AV$2051:$AV$2550,0),0) -> 166 | N20: =IF($M20=0,"",IF(INDEX(Data!$I$2051:$I$2550,$M20)=0,"Add ID","Row "&(INDEX(Data!$I$2051:$I$2550,$M20)+7))) -> Row 259
A21: =IF($M21=0,"",INDEX(Data!$W$2051:$W$2550,$M21)) -> 9 | B21: =IF($M21=0,"",INDEX(Data!$B$2051:$B$2550,$M21)) -> Lankenau High School | C21: =IF($M21=0,"",INDEX(Data!$C$2051:$C$2550,$M21)) -> District | D21: =IF($M21=0,"",INDEX(Data!$D$2051:$D$2550,$M21)) -> High | E21: =IF($M21=0,"",INDEX(Data!$G$2051:$G$2550,$M21)) -> 0.64 | F21: =IF($M21=0,"",INDEX(Data!$F$2051:$F$2550,$M21)) -> 225 | G21: =IF($M21=0,"",INDEX(Data!$K$2051:$K$2550,$M21)) -> 0.86714508 | H21: =IF($M21=0,"",INDEX(Data!$L$2051:$L$2550,$M21)) -> 0 | I21: =IF($M21=0,"",INDEX(Data!$T$2051:$T$2550,$M21)) -> 62 | J21: =IF($M21=0,"",INDEX(Data!$U$2051:$U$2550,$M21)) -> Listed | K21: =IF($M21=0,"",INDEX(Data!$AA$2051:$AA$2550,$M21)) -> 64% economic need; 0.87 mi fresh access; 0 nearby resources | L21: =IF($M21=0,"",IF(INDEX(Data!$AN$2051:$AN$2550,$M21)=0,"",IF(INDEX(Data!$U$41:$U$540,INDEX(Data!$AN$2051:$AN$2550,$M21))="","",INDEX(Data!$U$41:$U$540,INDEX(Data!$AN$2051:$AN$2550,$M21))))) -> 215-400-3420 | M21: =IF(COUNTIFS(Data!$AV$2051:$AV$2550,9)=1,MATCH(9,Data!$AV$2051:$AV$2550,0),0) -> 251 | N21: =IF($M21=0,"",IF(INDEX(Data!$I$2051:$I$2550,$M21)=0,"Add ID","Row "&(INDEX(Data!$I$2051:$I$2550,$M21)+7))) -> Row 174
A22: =IF($M22=0,"",INDEX(Data!$W$2051:$W$2550,$M22)) -> 10 | B22: =IF($M22=0,"",INDEX(Data!$B$2051:$B$2550,$M22)) -> Robert B. Pollock School | C22: =IF($M22=0,"",INDEX(Data!$C$2051:$C$2550,$M22)) -> District | D22: =IF($M22=0,"",INDEX(Data!$D$2051:$D$2550,$M22)) -> Elementary-Middle | E22: =IF($M22=0,"",INDEX(Data!$G$2051:$G$2550,$M22)) -> 0.7341 | F22: =IF($M22=0,"",INDEX(Data!$F$2051:$F$2550,$M22)) -> 900 | G22: =IF($M22=0,"",INDEX(Data!$K$2051:$K$2550,$M22)) -> 0.80763086 | H22: =IF($M22=0,"",INDEX(Data!$L$2051:$L$2550,$M22)) -> 2 | I22: =IF($M22=0,"",INDEX(Data!$T$2051:$T$2550,$M22)) -> 60 | J22: =IF($M22=0,"",INDEX(Data!$U$2051:$U$2550,$M22)) -> Listed | K22: =IF($M22=0,"",INDEX(Data!$AA$2051:$AA$2550,$M22)) -> 73% economic need; 0.81 mi fresh access; 2 nearby resources | L22: =IF($M22=0,"",IF(INDEX(Data!$AN$2051:$AN$2550,$M22)=0,"",IF(INDEX(Data!$U$41:$U$540,INDEX(Data!$AN$2051:$AN$2550,$M22))="","",INDEX(Data!$U$41:$U$540,INDEX(Data!$AN$2051:$AN$2550,$M22))))) -> 215-400-3210 | M22: =IF(COUNTIFS(Data!$AV$2051:$AV$2550,10)=1,MATCH(10,Data!$AV$2051:$AV$2550,0),0) -> 314 | N22: =IF($M22=0,"",IF(INDEX(Data!$I$2051:$I$2550,$M22)=0,"Add ID","Row "&(INDEX(Data!$I$2051:$I$2550,$M22)+7))) -> Row 258
A23: =IF($M23=0,"",INDEX(Data!$W$2051:$W$2550,$M23)) -> 11 | B23: =IF($M23=0,"",INDEX(Data!$B$2051:$B$2550,$M23)) -> Northeast High School | C23: =IF($M23=0,"",INDEX(Data!$C$2051:$C$2550,$M23)) -> District | D23: =IF($M23=0,"",INDEX(Data!$D$2051:$D$2550,$M23)) -> High | E23: =IF($M23=0,"",INDEX(Data!$G$2051:$G$2550,$M23)) -> 0.7192 | F23: =IF($M23=0,"",INDEX(Data!$F$2051:$F$2550,$M23)) -> 3541 | G23: =IF($M23=0,"",INDEX(Data!$K$2051:$K$2550,$M23)) -> 0.37970186 | H23: =IF($M23=0,"",INDEX(Data!$L$2051:$L$2550,$M23)) -> 0 | I23: =IF($M23=0,"",INDEX(Data!$T$2051:$T$2550,$M23)) -> 60 | J23: =IF($M23=0,"",INDEX(Data!$U$2051:$U$2550,$M23)) -> Listed | K23: =IF($M23=0,"",INDEX(Data!$AA$2051:$AA$2550,$M23)) -> 72% economic need; 0.38 mi fresh access; 0 nearby resources | L23: =IF($M23=0,"",IF(INDEX(Data!$AN$2051:$AN$2550,$M23)=0,"",IF(INDEX(Data!$U$41:$U$540,INDEX(Data!$AN$2051:$AN$2550,$M23))="","",INDEX(Data!$U$41:$U$540,INDEX(Data!$AN$2051:$AN$2550,$M23))))) -> 215-400-3200 | M23: =IF(COUNTIFS(Data!$AV$2051:$AV$2550,11)=1,MATCH(11,Data!$AV$2051:$AV$2550,0),0) -> 287 | N23: =IF($M23=0,"",IF(INDEX(Data!$I$2051:$I$2550,$M23)=0,"Add ID","Row "&(INDEX(Data!$I$2051:$I$2550,$M23)+7))) -> Row 213
A24: =IF($M24=0,"",INDEX(Data!$W$2051:$W$2550,$M24)) -> 12 | B24: =IF($M24=0,"",INDEX(Data!$B$2051:$B$2550,$M24)) -> Aloysius L. Fitzpatrick School | C24: =IF($M24=0,"",INDEX(Data!$C$2051:$C$2550,$M24)) -> District | D24: =IF($M24=0,"",INDEX(Data!$D$2051:$D$2550,$M24)) -> Elementary-Middle | E24: =IF($M24=0,"",INDEX(Data!$G$2051:$G$2550,$M24)) -> 0.7176 | F24: =IF($M24=0,"",INDEX(Data!$F$2051:$F$2550,$M24)) -> 868 | G24: =IF($M24=0,"",INDEX(Data!$K$2051:$K$2550,$M24)) -> 0.48645902 | H24: =IF($M24=0,"",INDEX(Data!$L$2051:$L$2550,$M24)) -> 0 | I24: =IF($M24=0,"",INDEX(Data!$T$2051:$T$2550,$M24)) -> 60 | J24: =IF($M24=0,"",INDEX(Data!$U$2051:$U$2550,$M24)) -> Listed | K24: =IF($M24=0,"",INDEX(Data!$AA$2051:$AA$2550,$M24)) -> 72% economic need; 0.49 mi fresh access; 0 nearby resources | L24: =IF($M24=0,"",IF(INDEX(Data!$AN$2051:$AN$2550,$M24)=0,"",IF(INDEX(Data!$U$41:$U$540,INDEX(Data!$AN$2051:$AN$2550,$M24))="","",INDEX(Data!$U$41:$U$540,INDEX(Data!$AN$2051:$AN$2550,$M24))))) -> 215-400-3060 | M24: =IF(COUNTIFS(Data!$AV$2051:$AV$2550,12)=1,MATCH(12,Data!$AV$2051:$AV$2550,0),0) -> 312 | N24: =IF($M24=0,"",IF(INDEX(Data!$I$2051:$I$2550,$M24)=0,"Add ID","Row "&(INDEX(Data!$I$2051:$I$2550,$M24)+7))) -> Row 23
A25: =IF($M25=0,"",INDEX(Data!$W$2051:$W$2550,$M25)) -> 13 | B25: =IF($M25=0,"",INDEX(Data!$B$2051:$B$2550,$M25)) -> Franklin Towne Charter Elementary School | C25: =IF($M25=0,"",INDEX(Data!$C$2051:$C$2550,$M25)) -> Charter | D25: =IF($M25=0,"",INDEX(Data!$D$2051:$D$2550,$M25)) -> Elementary-Middle | E25: =IF($M25=0,"",INDEX(Data!$G$2051:$G$2550,$M25)) -> 0.6767 | F25: =IF($M25=0,"",INDEX(Data!$F$2051:$F$2550,$M25)) -> 958 | G25: =IF($M25=0,"",INDEX(Data!$K$2051:$K$2550,$M25)) -> 0.80801878 | H25: =IF($M25=0,"",INDEX(Data!$L$2051:$L$2550,$M25)) -> 1 | I25: =IF($M25=0,"",INDEX(Data!$T$2051:$T$2550,$M25)) -> 60 | J25: =IF($M25=0,"",INDEX(Data!$U$2051:$U$2550,$M25)) -> Listed | K25: =IF($M25=0,"",INDEX(Data!$AA$2051:$AA$2550,$M25)) -> 68% economic need; 0.81 mi fresh access; 1 nearby resources | L25: =IF($M25=0,"",IF(INDEX(Data!$AN$2051:$AN$2550,$M25)=0,"",IF(INDEX(Data!$U$41:$U$540,INDEX(Data!$AN$2051:$AN$2550,$M25))="","",INDEX(Data!$U$41:$U$540,INDEX(Data!$AN$2051:$AN$2550,$M25))))) | M25: =IF(COUNTIFS(Data!$AV$2051:$AV$2550,13)=1,MATCH(13,Data!$AV$2051:$AV$2550,0),0) -> 125 | N25: =IF($M25=0,"",IF(INDEX(Data!$I$2051:$I$2550,$M25)=0,"Add ID","Row "&(INDEX(Data!$I$2051:$I$2550,$M25)+7))) -> Row 92
A26: =IF($M26=0,"",INDEX(Data!$W$2051:$W$2550,$M26)) -> 14 | B26: =IF($M26=0,"",INDEX(Data!$B$2051:$B$2550,$M26)) -> Charles C.A. Baldi Middle School | C26: =IF($M26=0,"",INDEX(Data!$C$2051:$C$2550,$M26)) -> District | D26: =IF($M26=0,"",INDEX(Data!$D$2051:$D$2550,$M26)) -> Middle | E26: =IF($M26=0,"",INDEX(Data!$G$2051:$G$2550,$M26)) -> 0.6683 | F26: =IF($M26=0,"",INDEX(Data!$F$2051:$F$2550,$M26)) -> 1424 | G26: =IF($M26=0,"",INDEX(Data!$K$2051:$K$2550,$M26)) -> 0.56351641 | H26: =IF($M26=0,"",INDEX(Data!$L$2051:$L$2550,$M26)) -> 0 | I26: =IF($M26=0,"",INDEX(Data!$T$2051:$T$2550,$M26)) -> 60 | J26: =IF($M26=0,"",INDEX(Data!$U$2051:$U$2550,$M26)) -> Listed | K26: =IF($M26=0,"",INDEX(Data!$AA$2051:$AA$2550,$M26)) -> 67% economic need; 0.56 mi fresh access; 0 nearby resources | L26: =IF($M26=0,"",IF(INDEX(Data!$AN$2051:$AN$2550,$M26)=0,"",IF(INDEX(Data!$U$41:$U$540,INDEX(Data!$AN$2051:$AN$2550,$M26))="","",INDEX(Data!$U$41:$U$540,INDEX(Data!$AN$2051:$AN$2550,$M26))))) -> 215-400-3090 | M26: =IF(COUNTIFS(Data!$AV$2051:$AV$2550,14)=1,MATCH(14,Data!$AV$2051:$AV$2550,0),0) -> 296 | N26: =IF($M26=0,"",IF(INDEX(Data!$I$2051:$I$2550,$M26)=0,"Add ID","Row "&(INDEX(Data!$I$2051:$I$2550,$M26)+7))) -> Row 47
A27: =IF($M27=0,"",INDEX(Data!$W$2051:$W$2550,$M27)) -> 15 | B27: =IF($M27=0,"",INDEX(Data!$B$2051:$B$2550,$M27)) -> Joseph Greenberg School | C27: =IF($M27=0,"",INDEX(Data!$C$2051:$C$2550,$M27)) -> District | D27: =IF($M27=0,"",INDEX(Data!$D$2051:$D$2550,$M27)) -> Elementary-Middle | E27: =IF($M27=0,"",INDEX(Data!$G$2051:$G$2550,$M27)) -> 0.5234 | F27: =IF($M27=0,"",INDEX(Data!$F$2051:$F$2550,$M27)) -> 1048 | G27: =IF($M27=0,"",INDEX(Data!$K$2051:$K$2550,$M27)) -> 0.90583823 | H27: =IF($M27=0,"",INDEX(Data!$L$2051:$L$2550,$M27)) -> 0 | I27: =IF($M27=0,"",INDEX(Data!$T$2051:$T$2550,$M27)) -> 60 | J27: =IF($M27=0,"",INDEX(Data!$U$2051:$U$2550,$M27)) -> Listed | K27: =IF($M27=0,"",INDEX(Data!$AA$2051:$AA$2550,$M27)) -> 52% economic need; 0.91 mi fresh access; 0 nearby resources | L27: =IF($M27=0,"",IF(INDEX(Data!$AN$2051:$AN$2550,$M27)=0,"",IF(INDEX(Data!$U$41:$U$540,INDEX(Data!$AN$2051:$AN$2550,$M27))="","",INDEX(Data!$U$41:$U$540,INDEX(Data!$AN$2051:$AN$2550,$M27))))) -> 215-400-3080 | M27: =IF(COUNTIFS(Data!$AV$2051:$AV$2550,15)=1,MATCH(15,Data!$AV$2051:$AV$2550,0),0) -> 316 | N27: =IF($M27=0,"",IF(INDEX(Data!$I$2051:$I$2550,$M27)=0,"Add ID","Row "&(INDEX(Data!$I$2051:$I$2550,$M27)+7))) -> Row 153
A28: =IF($M28=0,"",INDEX(Data!$W$2051:$W$2550,$M28)) -> 16 | B28: =IF($M28=0,"",INDEX(Data!$B$2051:$B$2550,$M28)) -> Bridesburg School | C28: =IF($M28=0,"",INDEX(Data!$C$2051:$C$2550,$M28)) -> District | D28: =IF($M28=0,"",INDEX(Data!$D$2051:$D$2550,$M28)) -> Elementary-Middle | E28: =IF($M28=0,"",INDEX(Data!$G$2051:$G$2550,$M28)) -> 0.6934 | F28: =IF($M28=0,"",INDEX(Data!$F$2051:$F$2550,$M28)) -> 522 | G28: =IF($M28=0,"",INDEX(Data!$K$2051:$K$2550,$M28)) -> 0.7903588 | H28: =IF($M28=0,"",INDEX(Data!$L$2051:$L$2550,$M28)) -> 1 | I28: =IF($M28=0,"",INDEX(Data!$T$2051:$T$2550,$M28)) -> 59 | J28: =IF($M28=0,"",INDEX(Data!$U$2051:$U$2550,$M28)) -> Listed | K28: =IF($M28=0,"",INDEX(Data!$AA$2051:$AA$2550,$M28)) -> 69% economic need; 0.79 mi fresh access; 1 nearby resources | L28: =IF($M28=0,"",IF(INDEX(Data!$AN$2051:$AN$2550,$M28)=0,"",IF(INDEX(Data!$U$41:$U$540,INDEX(Data!$AN$2051:$AN$2550,$M28))="","",INDEX(Data!$U$41:$U$540,INDEX(Data!$AN$2051:$AN$2550,$M28))))) -> 215-400-7240 | M28: =IF(COUNTIFS(Data!$AV$2051:$AV$2550,16)=1,MATCH(16,Data!$AV$2051:$AV$2550,0),0) -> 280 | N28: =IF($M28=0,"",IF(INDEX(Data!$I$2051:$I$2550,$M28)=0,"Add ID","Row "&(INDEX(Data!$I$2051:$I$2550,$M28)+7))) -> Row 41
A29: =IF($M29=0,"",INDEX(Data!$W$2051:$W$2550,$M29)) -> 17 | B29: =IF($M29=0,"",INDEX(Data!$B$2051:$B$2550,$M29)) -> Kensington High School | C29: =IF($M29=0,"",INDEX(Data!$C$2051:$C$2550,$M29)) -> District | D29: =IF($M29=0,"",INDEX(Data!$D$2051:$D$2550,$M29)) -> High | E29: =IF($M29=0,"",INDEX(Data!$G$2051:$G$2550,$M29)) -> 0.8519 | F29: =IF($M29=0,"",INDEX(Data!$F$2051:$F$2550,$M29)) -> 447 | G29: =IF($M29=0,"",INDEX(Data!$K$2051:$K$2550,$M29)) -> 0.61090703 | H29: =IF($M29=0,"",INDEX(Data!$L$2051:$L$2550,$M29)) -> 2 | I29: =IF($M29=0,"",INDEX(Data!$T$2051:$T$2550,$M29)) -> 58 | J29: =IF($M29=0,"",INDEX(Data!$U$2051:$U$2550,$M29)) -> Listed | K29: =IF($M29=0,"",INDEX(Data!$AA$2051:$AA$2550,$M29)) -> 85% economic need; 0.61 mi fresh access; 2 nearby resources | L29: =IF($M29=0,"",IF(INDEX(Data!$AN$2051:$AN$2550,$M29)=0,"",IF(INDEX(Data!$U$41:$U$540,INDEX(Data!$AN$2051:$AN$2550,$M29))="","",INDEX(Data!$U$41:$U$540,INDEX(Data!$AN$2051:$AN$2550,$M29))))) -> 215-400-7700 | M29: =IF(COUNTIFS(Data!$AV$2051:$AV$2550,17)=1,MATCH(17,Data!$AV$2051:$AV$2550,0),0) -> 221 | N29: =IF($M29=0,"",IF(INDEX(Data!$I$2051:$I$2550,$M29)=0,"Add ID","Row "&(INDEX(Data!$I$2051:$I$2550,$M29)+7))) -> Row 165
A30: =IF($M30=0,"",INDEX(Data!$W$2051:$W$2550,$M30)) -> 18 | B30: =IF($M30=0,"",INDEX(Data!$B$2051:$B$2550,$M30)) -> Walter B. Saul High School | C30: =IF($M30=0,"",INDEX(Data!$C$2051:$C$2550,$M30)) -> District | D30: =IF($M30=0,"",INDEX(Data!$D$2051:$D$2550,$M30)) -> High | E30: =IF($M30=0,"",INDEX(Data!$G$2051:$G$2550,$M30)) -> 0.674 | F30: =IF($M30=0,"",INDEX(Data!$F$2051:$F$2550,$M30)) -> 406 | G30: =IF($M30=0,"",INDEX(Data!$K$2051:$K$2550,$M30)) -> 0.56905154 | H30: =IF($M30=0,"",INDEX(Data!$L$2051:$L$2550,$M30)) -> 0 | I30: =IF($M30=0,"",INDEX(Data!$T$2051:$T$2550,$M30)) -> 58 | J30: =IF($M30=0,"",INDEX(Data!$U$2051:$U$2550,$M30)) -> Listed | K30: =IF($M30=0,"",INDEX(Data!$AA$2051:$AA$2550,$M30)) -> 67% economic need; 0.57 mi fresh access; 0 nearby resources | L30: =IF($M30=0,"",IF(INDEX(Data!$AN$2051:$AN$2550,$M30)=0,"",IF(INDEX(Data!$U$41:$U$540,INDEX(Data!$AN$2051:$AN$2550,$M30))="","",INDEX(Data!$U$41:$U$540,INDEX(Data!$AN$2051:$AN$2550,$M30))))) -> 215-400-3450 | M30: =IF(COUNTIFS(Data!$AV$2051:$AV$2550,18)=1,MATCH(18,Data!$AV$2051:$AV$2550,0),0) -> 225 | N30: =IF($M30=0,"",IF(INDEX(Data!$I$2051:$I$2550,$M30)=0,"Add ID","Row "&(INDEX(Data!$I$2051:$I$2550,$M30)+7))) -> Row 312
A31: =IF($M31=0,"",INDEX(Data!$W$2051:$W$2550,$M31)) -> 19 | B31: =IF($M31=0,"",INDEX(Data!$B$2051:$B$2550,$M31)) -> Shawmont School | C31: =IF($M31=0,"",INDEX(Data!$C$2051:$C$2550,$M31)) -> District | D31: =IF($M31=0,"",INDEX(Data!$D$2051:$D$2550,$M31)) -> Elementary-Middle | E31: =IF($M31=0,"",INDEX(Data!$G$2051:$G$2550,$M31)) -> 0.6284 | F31: =IF($M31=0,"",INDEX(Data!$F$2051:$F$2550,$M31)) -> 457 | G31: =IF($M31=0,"",INDEX(Data!$K$2051:$K$2550,$M31)) -> 0.57084826 | H31: =IF($M31=0,"",INDEX(Data!$L$2051:$L$2550,$M31)) -> 0 | I31: =IF($M31=0,"",INDEX(Data!$T$2051:$T$2550,$M31)) -> 58 | J31: =IF($M31=0,"",INDEX(Data!$U$2051:$U$2550,$M31)) -> Listed | K31: =IF($M31=0,"",INDEX(Data!$AA$2051:$AA$2550,$M31)) -> 63% economic need; 0.57 mi fresh access; 0 nearby resources | L31: =IF($M31=0,"",IF(INDEX(Data!$AN$2051:$AN$2550,$M31)=0,"",IF(INDEX(Data!$U$41:$U$540,INDEX(Data!$AN$2051:$AN$2550,$M31))="","",INDEX(Data!$U$41:$U$540,INDEX(Data!$AN$2051:$AN$2550,$M31))))) -> 215-400-3440 | M31: =IF(COUNTIFS(Data!$AV$2051:$AV$2550,19)=1,MATCH(19,Data!$AV$2051:$AV$2550,0),0) -> 242 | N31: =IF($M31=0,"",IF(INDEX(Data!$I$2051:$I$2550,$M31)=0,"Add ID","Row "&(INDEX(Data!$I$2051:$I$2550,$M31)+7))) -> Row 275
A32: =IF($M32=0,"",INDEX(Data!$W$2051:$W$2550,$M32)) -> 20 | B32: =IF($M32=0,"",INDEX(Data!$B$2051:$B$2550,$M32)) -> John F. McCloskey School | C32: =IF($M32=0,"",INDEX(Data!$C$2051:$C$2550,$M32)) -> District | D32: =IF($M32=0,"",INDEX(Data!$D$2051:$D$2550,$M32)) -> Elementary-Middle | E32: =IF($M32=0,"",INDEX(Data!$G$2051:$G$2550,$M32)) -> 0.7557 | F32: =IF($M32=0,"",INDEX(Data!$F$2051:$F$2550,$M32)) -> 217 | G32: =IF($M32=0,"",INDEX(Data!$K$2051:$K$2550,$M32)) -> 0.25948804 | H32: =IF($M32=0,"",INDEX(Data!$L$2051:$L$2550,$M32)) -> 0 | I32: =IF($M32=0,"",INDEX(Data!$T$2051:$T$2550,$M32)) -> 57 | J32: =IF($M32=0,"",INDEX(Data!$U$2051:$U$2550,$M32)) -> Listed | K32: =IF($M32=0,"",INDEX(Data!$AA$2051:$AA$2550,$M32)) -> 76% economic need; 0.26 mi fresh access; 0 nearby resources | L32: =IF($M32=0,"",IF(INDEX(Data!$AN$2051:$AN$2550,$M32)=0,"",IF(INDEX(Data!$U$41:$U$540,INDEX(Data!$AN$2051:$AN$2550,$M32))="","",INDEX(Data!$U$41:$U$540,INDEX(Data!$AN$2051:$AN$2550,$M32))))) -> 215-400-3380 | M32: =IF(COUNTIFS(Data!$AV$2051:$AV$2550,20)=1,MATCH(20,Data!$AV$2051:$AV$2550,0),0) -> 237 | N32: =IF($M32=0,"",IF(INDEX(Data!$I$2051:$I$2550,$M32)=0,"Add ID","Row "&(INDEX(Data!$I$2051:$I$2550,$M32)+7))) -> Row 145
A33: =IF($M33=0,"",INDEX(Data!$W$2051:$W$2550,$M33)) -> 21 | B33: =IF($M33=0,"",INDEX(Data!$B$2051:$B$2550,$M33)) -> Kennedy C. Crossan School | C33: =IF($M33=0,"",INDEX(Data!$C$2051:$C$2550,$M33)) -> District | D33: =IF($M33=0,"",INDEX(Data!$D$2051:$D$2550,$M33)) -> Elementary | E33: =IF($M33=0,"",INDEX(Data!$G$2051:$G$2550,$M33)) -> 0.7358 | F33: =IF($M33=0,"",INDEX(Data!$F$2051:$F$2550,$M33)) -> 318 | G33: =IF($M33=0,"",INDEX(Data!$K$2051:$K$2550,$M33)) -> 0.82466884 | H33: =IF($M33=0,"",INDEX(Data!$L$2051:$L$2550,$M33)) -> 2 | I33: =IF($M33=0,"",INDEX(Data!$T$2051:$T$2550,$M33)) -> 57 | J33: =IF($M33=0,"",INDEX(Data!$U$2051:$U$2550,$M33)) -> Listed | K33: =IF($M33=0,"",INDEX(Data!$AA$2051:$AA$2550,$M33)) -> 74% economic need; 0.82 mi fresh access; 2 nearby resources | L33: =IF($M33=0,"",IF(INDEX(Data!$AN$2051:$AN$2550,$M33)=0,"",IF(INDEX(Data!$U$41:$U$540,INDEX(Data!$AN$2051:$AN$2550,$M33))="","",INDEX(Data!$U$41:$U$540,INDEX(Data!$AN$2051:$AN$2550,$M33))))) -> 215-400-3160 | M33: =IF(COUNTIFS(Data!$AV$2051:$AV$2550,21)=1,MATCH(21,Data!$AV$2051:$AV$2550,0),0) -> 300 | N33: =IF($M33=0,"",IF(INDEX(Data!$I$2051:$I$2550,$M33)=0,"Add ID","Row "&(INDEX(Data!$I$2051:$I$2550,$M33)+7))) -> Row 163
A34: =IF($M34=0,"",INDEX(Data!$W$2051:$W$2550,$M34)) -> 22 | B34: =IF($M34=0,"",INDEX(Data!$B$2051:$B$2550,$M34)) -> Samuel Gompers School | C34: =IF($M34=0,"",INDEX(Data!$C$2051:$C$2550,$M34)) -> District | D34: =IF($M34=0,"",INDEX(Data!$D$2051:$D$2550,$M34)) -> Elementary-Middle | E34: =IF($M34=0,"",INDEX(Data!$G$2051:$G$2550,$M34)) -> 0.7203 | F34: =IF($M34=0,"",INDEX(Data!$F$2051:$F$2550,$M34)) -> 236 | G34: =IF($M34=0,"",INDEX(Data!$K$2051:$K$2550,$M34)) -> 1.0969193 | H34: =IF($M34=0,"",INDEX(Data!$L$2051:$L$2550,$M34)) -> 3 | I34: =IF($M34=0,"",INDEX(Data!$T$2051:$T$2550,$M34)) -> 57 | J34: =IF($M34=0,"",INDEX(Data!$U$2051:$U$2550,$M34)) -> Listed | K34: =IF($M34=0,"",INDEX(Data!$AA$2051:$AA$2550,$M34)) -> 72% economic need; 1.10 mi fresh access; 3 nearby resources | L34: =IF($M34=0,"",IF(INDEX(Data!$AN$2051:$AN$2550,$M34)=0,"",IF(INDEX(Data!$U$41:$U$540,INDEX(Data!$AN$2051:$AN$2550,$M34))="","",INDEX(Data!$U$41:$U$540,INDEX(Data!$AN$2051:$AN$2550,$M34))))) -> 215-400-7250 | M34: =IF(COUNTIFS(Data!$AV$2051:$AV$2550,22)=1,MATCH(22,Data!$AV$2051:$AV$2550,0),0) -> 164 | N34: =IF($M34=0,"",IF(INDEX(Data!$I$2051:$I$2550,$M34)=0,"Add ID","Row "&(INDEX(Data!$I$2051:$I$2550,$M34)+7))) -> Row 269
A35: =IF($M35=0,"",INDEX(Data!$W$2051:$W$2550,$M35)) -> 23 | B35: =IF($M35=0,"",INDEX(Data!$B$2051:$B$2550,$M35)) -> Philadelphia Montessori Charter School | C35: =IF($M35=0,"",INDEX(Data!$C$2051:$C$2550,$M35)) -> Charter | D35: =IF($M35=0,"",INDEX(Data!$D$2051:$D$2550,$M35)) -> Elementary | E35: =IF($M35=0,"",INDEX(Data!$G$2051:$G$2550,$M35)) -> 0.6706 | F35: =IF($M35=0,"",INDEX(Data!$F$2051:$F$2550,$M35)) -> 249 | G35: =IF($M35=0,"",INDEX(Data!$K$2051:$K$2550,$M35)) -> 0.91191316 | H35: =IF($M35=0,"",INDEX(Data!$L$2051:$L$2550,$M35)) -> 1 | I35: =IF($M35=0,"",INDEX(Data!$T$2051:$T$2550,$M35)) -> 57 | J35: =IF($M35=0,"",INDEX(Data!$U$2051:$U$2550,$M35)) -> Listed | K35: =IF($M35=0,"",INDEX(Data!$AA$2051:$AA$2550,$M35)) -> 67% economic need; 0.91 mi fresh access; 1 nearby resources | L35: =IF($M35=0,"",IF(INDEX(Data!$AN$2051:$AN$2550,$M35)=0,"",IF(INDEX(Data!$U$41:$U$540,INDEX(Data!$AN$2051:$AN$2550,$M35))="","",INDEX(Data!$U$41:$U$540,INDEX(Data!$AN$2051:$AN$2550,$M35))))) -> 215-365-4011 | M35: =IF(COUNTIFS(Data!$AV$2051:$AV$2550,23)=1,MATCH(23,Data!$AV$2051:$AV$2550,0),0) -> 112 | N35: =IF($M35=0,"",IF(INDEX(Data!$I$2051:$I$2550,$M35)=0,"Add ID","Row "&(INDEX(Data!$I$2051:$I$2550,$M35)+7))) -> Row 247
A36: =IF($M36=0,"",INDEX(Data!$W$2051:$W$2550,$M36)) -> 24 | B36: =IF($M36=0,"",INDEX(Data!$B$2051:$B$2550,$M36)) -> West Oak Lane Charter School | C36: =IF($M36=0,"",INDEX(Data!$C$2051:$C$2550,$M36)) -> Charter | D36: =IF($M36=0,"",INDEX(Data!$D$2051:$D$2550,$M36)) -> Elementary-Middle | E36: =IF($M36=0,"",INDEX(Data!$G$2051:$G$2550,$M36)) -> 0.9637 | F36: =IF($M36=0,"",INDEX(Data!$F$2051:$F$2550,$M36)) -> 1007 | G36: =IF($M36=0,"",INDEX(Data!$K$2051:$K$2550,$M36)) -> 0.78787323 | H36: =IF($M36=0,"",INDEX(Data!$L$2051:$L$2550,$M36)) -> 8 | I36: =IF($M36=0,"",INDEX(Data!$T$2051:$T$2550,$M36)) -> 55 | J36: =IF($M36=0,"",INDEX(Data!$U$2051:$U$2550,$M36)) -> Listed | K36: =IF($M36=0,"",INDEX(Data!$AA$2051:$AA$2550,$M36)) -> 96% economic need; 0.79 mi fresh access; 8 nearby resources | L36: =IF($M36=0,"",IF(INDEX(Data!$AN$2051:$AN$2550,$M36)=0,"",IF(INDEX(Data!$U$41:$U$540,INDEX(Data!$AN$2051:$AN$2550,$M36))="","",INDEX(Data!$U$41:$U$540,INDEX(Data!$AN$2051:$AN$2550,$M36))))) -> 215-927-7995 | M36: =IF(COUNTIFS(Data!$AV$2051:$AV$2550,24)=1,MATCH(24,Data!$AV$2051:$AV$2550,0),0) -> 83 | N36: =IF($M36=0,"",IF(INDEX(Data!$I$2051:$I$2550,$M36)=0,"Add ID","Row "&(INDEX(Data!$I$2051:$I$2550,$M36)+7))) -> Row 315
A37: =IF($M37=0,"",INDEX(Data!$W$2051:$W$2550,$M37)) -> 25 | B37: =IF($M37=0,"",INDEX(Data!$B$2051:$B$2550,$M37)) -> Edwin Forrest School | C37: =IF($M37=0,"",INDEX(Data!$C$2051:$C$2550,$M37)) -> District | D37: =IF($M37=0,"",INDEX(Data!$D$2051:$D$2550,$M37)) -> Elementary | E37: =IF($M37=0,"",INDEX(Data!$G$2051:$G$2550,$M37)) -> 0.776 | F37: =IF($M37=0,"",INDEX(Data!$F$2051:$F$2550,$M37)) -> 798 | G37: =IF($M37=0,"",INDEX(Data!$K$2051:$K$2550,$M37)) -> 0.77034598 | H37: =IF($M37=0,"",INDEX(Data!$L$2051:$L$2550,$M37)) -> 3 | I37: =IF($M37=0,"",INDEX(Data!$T$2051:$T$2550,$M37)) -> 55 | J37: =IF($M37=0,"",INDEX(Data!$U$2051:$U$2550,$M37)) -> Listed | K37: =IF($M37=0,"",INDEX(Data!$AA$2051:$AA$2550,$M37)) -> 78% economic need; 0.77 mi fresh access; 3 nearby resources | L37: =IF($M37=0,"",IF(INDEX(Data!$AN$2051:$AN$2550,$M37)=0,"",IF(INDEX(Data!$U$41:$U$540,INDEX(Data!$AN$2051:$AN$2550,$M37))="","",INDEX(Data!$U$41:$U$540,INDEX(Data!$AN$2051:$AN$2550,$M37))))) -> 215-400-3330 | M37: =IF(COUNTIFS(Data!$AV$2051:$AV$2550,25)=1,MATCH(25,Data!$AV$2051:$AV$2550,0),0) -> 302 | N37: =IF($M37=0,"",IF(INDEX(Data!$I$2051:$I$2550,$M37)=0,"Add ID","Row "&(INDEX(Data!$I$2051:$I$2550,$M37)+7))) -> Row 65
A38: =IF($M38=0,"",INDEX(Data!$W$2051:$W$2550,$M38)) -> 26 | B38: =IF($M38=0,"",INDEX(Data!$B$2051:$B$2550,$M38)) -> Northeast Community Propel Academy | C38: =IF($M38=0,"",INDEX(Data!$C$2051:$C$2550,$M38)) -> District | D38: =IF($M38=0,"",INDEX(Data!$D$2051:$D$2550,$M38)) -> Elementary-Middle | E38: =IF($M38=0,"",INDEX(Data!$G$2051:$G$2550,$M38)) -> 0.7507 | F38: =IF($M38=0,"",INDEX(Data!$F$2051:$F$2550,$M38)) -> 1715 | G38: =IF($M38=0,"",INDEX(Data!$K$2051:$K$2550,$M38)) -> 0.61933032 | H38: =IF($M38=0,"",INDEX(Data!$L$2051:$L$2550,$M38)) -> 2 | I38: =IF($M38=0,"",INDEX(Data!$T$2051:$T$2550,$M38)) -> 55 | J38: =IF($M38=0,"",INDEX(Data!$U$2051:$U$2550,$M38)) -> Listed | K38: =IF($M38=0,"",INDEX(Data!$AA$2051:$AA$2550,$M38)) -> 75% economic need; 0.62 mi fresh access; 2 nearby resources | L38: =IF($M38=0,"",IF(INDEX(Data!$AN$2051:$AN$2550,$M38)=0,"",IF(INDEX(Data!$U$41:$U$540,INDEX(Data!$AN$2051:$AN$2550,$M38))="","",INDEX(Data!$U$41:$U$540,INDEX(Data!$AN$2051:$AN$2550,$M38))))) -> 215-400-8350 | M38: =IF(COUNTIFS(Data!$AV$2051:$AV$2550,26)=1,MATCH(26,Data!$AV$2051:$AV$2550,0),0) -> 295 | N38: =IF($M38=0,"",IF(INDEX(Data!$I$2051:$I$2550,$M38)=0,"Add ID","Row "&(INDEX(Data!$I$2051:$I$2550,$M38)+7))) -> Row 212
A39: =IF($M39=0,"",INDEX(Data!$W$2051:$W$2550,$M39)) -> 27 | B39: =IF($M39=0,"",INDEX(Data!$B$2051:$B$2550,$M39)) -> Abraham Lincoln High School | C39: =IF($M39=0,"",INDEX(Data!$C$2051:$C$2550,$M39)) -> District | D39: =IF($M39=0,"",INDEX(Data!$D$2051:$D$2550,$M39)) -> High | E39: =IF($M39=0,"",INDEX(Data!$G$2051:$G$2550,$M39)) -> 0.7382 | F39: =IF($M39=0,"",INDEX(Data!$F$2051:$F$2550,$M39)) -> 2332 | G39: =IF($M39=0,"",INDEX(Data!$K$2051:$K$2550,$M39)) -> 0.53087782 | H39: =IF($M39=0,"",INDEX(Data!$L$2051:$L$2550,$M39)) -> 2 | I39: =IF($M39=0,"",INDEX(Data!$T$2051:$T$2550,$M39)) -> 55 | J39: =IF($M39=0,"",INDEX(Data!$U$2051:$U$2550,$M39)) -> Listed | K39: =IF($M39=0,"",INDEX(Data!$AA$2051:$AA$2550,$M39)) -> 74% economic need; 0.53 mi fresh access; 2 nearby resources | L39: =IF($M39=0,"",IF(INDEX(Data!$AN$2051:$AN$2550,$M39)=0,"",IF(INDEX(Data!$U$41:$U$540,INDEX(Data!$AN$2051:$AN$2550,$M39))="","",INDEX(Data!$U$41:$U$540,INDEX(Data!$AN$2051:$AN$2550,$M39))))) -> 215-400-3300 | M39: =IF(COUNTIFS(Data!$AV$2051:$AV$2550,27)=1,MATCH(27,Data!$AV$2051:$AV$2550,0),0) -> 286 | N39: =IF($M39=0,"",IF(INDEX(Data!$I$2051:$I$2550,$M39)=0,"Add ID","Row "&(INDEX(Data!$I$2051:$I$2550,$M39)+7))) -> Row 9
A40: =IF($M40=0,"",INDEX(Data!$W$2051:$W$2550,$M40)) -> 28 | B40: =IF($M40=0,"",INDEX(Data!$B$2051:$B$2550,$M40)) -> Swenson Arts and Technology High School | C40: =IF($M40=0,"",INDEX(Data!$C$2051:$C$2550,$M40)) -> District | D40: =IF($M40=0,"",INDEX(Data!$D$2051:$D$2550,$M40)) -> High | E40: =IF($M40=0,"",INDEX(Data!$G$2051:$G$2550,$M40)) -> 0.7313 | F40: =IF($M40=0,"",INDEX(Data!$F$2051:$F$2550,$M40)) -> 780 | G40: =IF($M40=0,"",INDEX(Data!$K$2051:$K$2550,$M40)) -> 0.74643934 | H40: =IF($M40=0,"",INDEX(Data!$L$2051:$L$2550,$M40)) -> 2 | I40: =IF($M40=0,"",INDEX(Data!$T$2051:$T$2550,$M40)) -> 55 | J40: =IF($M40=0,"",INDEX(Data!$U$2051:$U$2550,$M40)) -> Listed | K40: =IF($M40=0,"",INDEX(Data!$AA$2051:$AA$2550,$M40)) -> 73% economic need; 0.75 mi fresh access; 2 nearby resources | L40: =IF($M40=0,"",IF(INDEX(Data!$AN$2051:$AN$2550,$M40)=0,"",IF(INDEX(Data!$U$41:$U$540,INDEX(Data!$AN$2051:$AN$2550,$M40))="","",INDEX(Data!$U$41:$U$540,INDEX(Data!$AN$2051:$AN$2550,$M40))))) -> 215-400-3140 | M40: =IF(COUNTIFS(Data!$AV$2051:$AV$2550,28)=1,MATCH(28,Data!$AV$2051:$AV$2550,0),0) -> 292 | N40: =IF($M40=0,"",IF(INDEX(Data!$I$2051:$I$2550,$M40)=0,"Add ID","Row "&(INDEX(Data!$I$2051:$I$2550,$M40)+7))) -> Row 286
A41: =IF($M41=0,"",INDEX(Data!$W$2051:$W$2550,$M41)) -> 29 | B41: =IF($M41=0,"",INDEX(Data!$B$2051:$B$2550,$M41)) -> Louis H. Farrell School | C41: =IF($M41=0,"",INDEX(Data!$C$2051:$C$2550,$M41)) -> District | D41: =IF($M41=0,"",INDEX(Data!$D$2051:$D$2550,$M41)) -> Elementary-Middle | E41: =IF($M41=0,"",INDEX(Data!$G$2051:$G$2550,$M41)) -> 0.7148 | F41: =IF($M41=0,"",INDEX(Data!$F$2051:$F$2550,$M41)) -> 1255 | G41: =IF($M41=0,"",INDEX(Data!$K$2051:$K$2550,$M41)) -> 0.08152945 | H41: =IF($M41=0,"",INDEX(Data!$L$2051:$L$2550,$M41)) -> 0 | I41: =IF($M41=0,"",INDEX(Data!$T$2051:$T$2550,$M41)) -> 55 | J41: =IF($M41=0,"",INDEX(Data!$U$2051:$U$2550,$M41)) -> Listed | K41: =IF($M41=0,"",INDEX(Data!$AA$2051:$AA$2550,$M41)) -> 71% economic need; 0.08 mi fresh access; 0 nearby resources | L41: =IF($M41=0,"",IF(INDEX(Data!$AN$2051:$AN$2550,$M41)=0,"",IF(INDEX(Data!$U$41:$U$540,INDEX(Data!$AN$2051:$AN$2550,$M41))="","",INDEX(Data!$U$41:$U$540,INDEX(Data!$AN$2051:$AN$2550,$M41))))) -> 215-400-3230 | M41: =IF(COUNTIFS(Data!$AV$2051:$AV$2550,29)=1,MATCH(29,Data!$AV$2051:$AV$2550,0),0) -> 311 | N41: =IF($M41=0,"",IF(INDEX(Data!$I$2051:$I$2550,$M41)=0,"Add ID","Row "&(INDEX(Data!$I$2051:$I$2550,$M41)+7))) -> Row 179
A42: =IF($M42=0,"",INDEX(Data!$W$2051:$W$2550,$M42)) -> 30 | B42: =IF($M42=0,"",INDEX(Data!$B$2051:$B$2550,$M42)) -> MAST Community Charter School III | C42: =IF($M42=0,"",INDEX(Data!$C$2051:$C$2550,$M42)) -> Charter | D42: =IF($M42=0,"",INDEX(Data!$D$2051:$D$2550,$M42)) -> Elementary | E42: =IF($M42=0,"",INDEX(Data!$G$2051:$G$2550,$M42)) -> 0.6847 | F42: =IF($M42=0,"",INDEX(Data!$F$2051:$F$2550,$M42)) -> 1328 | G42: =IF($M42=0,"",INDEX(Data!$K$2051:$K$2550,$M42)) -> 0.56566903 | H42: =IF($M42=0,"",INDEX(Data!$L$2051:$L$2550,$M42)) -> 1 | I42: =IF($M42=0,"",INDEX(Data!$T$2051:$T$2550,$M42)) -> 55 | J42: =IF($M42=0,"",INDEX(Data!$U$2051:$U$2550,$M42)) -> Listed | K42: =IF($M42=0,"",INDEX(Data!$AA$2051:$AA$2550,$M42)) -> 68% economic need; 0.57 mi fresh access; 1 nearby resources | L42: =IF($M42=0,"",IF(INDEX(Data!$AN$2051:$AN$2550,$M42)=0,"",IF(INDEX(Data!$U$41:$U$540,INDEX(Data!$AN$2051:$AN$2550,$M42))="","",INDEX(Data!$U$41:$U$540,INDEX(Data!$AN$2051:$AN$2550,$M42))))) | M42: =IF(COUNTIFS(Data!$AV$2051:$AV$2550,30)=1,MATCH(30,Data!$AV$2051:$AV$2550,0),0) -> 150 | N42: =IF($M42=0,"",IF(INDEX(Data!$I$2051:$I$2550,$M42)=0,"Add ID","Row "&(INDEX(Data!$I$2051:$I$2550,$M42)+7))) -> Row 187
A43: =IF($M43=0,"",INDEX(Data!$W$2051:$W$2550,$M43)) -> 31 | B43: =IF($M43=0,"",INDEX(Data!$B$2051:$B$2550,$M43)) -> Hancock, John Demonstration School | C43: =IF($M43=0,"",INDEX(Data!$C$2051:$C$2550,$M43)) -> District | D43: =IF($M43=0,"",INDEX(Data!$D$2051:$D$2550,$M43)) -> Elementary-Middle | E43: =IF($M43=0,"",INDEX(Data!$G$2051:$G$2550,$M43)) -> 0.6716 | F43: =IF($M43=0,"",INDEX(Data!$F$2051:$F$2550,$M43)) -> 869 | G43: =IF($M43=0,"",INDEX(Data!$K$2051:$K$2550,$M43)) -> 0.33709717 | H43: =IF($M43=0,"",INDEX(Data!$L$2051:$L$2550,$M43)) -> 0 | I43: =IF($M43=0,"",INDEX(Data!$T$2051:$T$2550,$M43)) -> 55 | J43: =IF($M43=0,"",INDEX(Data!$U$2051:$U$2550,$M43)) -> Listed | K43: =IF($M43=0,"",INDEX(Data!$AA$2051:$AA$2550,$M43)) -> 67% economic need; 0.34 mi fresh access; 0 nearby resources | L43: =IF($M43=0,"",IF(INDEX(Data!$AN$2051:$AN$2550,$M43)=0,"",IF(INDEX(Data!$U$41:$U$540,INDEX(Data!$AN$2051:$AN$2550,$M43))="","",INDEX(Data!$U$41:$U$540,INDEX(Data!$AN$2051:$AN$2550,$M43))))) -> 215-400-3120 | M43: =IF(COUNTIFS(Data!$AV$2051:$AV$2550,31)=1,MATCH(31,Data!$AV$2051:$AV$2550,0),0) -> 324 | N43: =IF($M43=0,"",IF(INDEX(Data!$I$2051:$I$2550,$M43)=0,"Add ID","Row "&(INDEX(Data!$I$2051:$I$2550,$M43)+7))) -> Row 114
A44: =IF($M44=0,"",INDEX(Data!$W$2051:$W$2550,$M44)) -> 32 | B44: =IF($M44=0,"",INDEX(Data!$B$2051:$B$2550,$M44)) -> Stephen Decatur School | C44: =IF($M44=0,"",INDEX(Data!$C$2051:$C$2550,$M44)) -> District | D44: =IF($M44=0,"",INDEX(Data!$D$2051:$D$2550,$M44)) -> Elementary-Middle | E44: =IF($M44=0,"",INDEX(Data!$G$2051:$G$2550,$M44)) -> 0.6692 | F44: =IF($M44=0,"",INDEX(Data!$F$2051:$F$2550,$M44)) -> 1041 | G44: =IF($M44=0,"",INDEX(Data!$K$2051:$K$2550,$M44)) -> 0.66024261 | H44: =IF($M44=0,"",INDEX(Data!$L$2051:$L$2550,$M44)) -> 1 | I44: =IF($M44=0,"",INDEX(Data!$T$2051:$T$2550,$M44)) -> 55 | J44: =IF($M44=0,"",INDEX(Data!$U$2051:$U$2550,$M44)) -> Listed | K44: =IF($M44=0,"",INDEX(Data!$AA$2051:$AA$2550,$M44)) -> 67% economic need; 0.66 mi fresh access; 1 nearby resources | L44: =IF($M44=0,"",IF(INDEX(Data!$AN$2051:$AN$2550,$M44)=0,"",IF(INDEX(Data!$U$41:$U$540,INDEX(Data!$AN$2051:$AN$2550,$M44))="","",INDEX(Data!$U$41:$U$540,INDEX(Data!$AN$2051:$AN$2550,$M44))))) -> 215-400-3050 | M44: =IF(COUNTIFS(Data!$AV$2051:$AV$2550,32)=1,MATCH(32,Data!$AV$2051:$AV$2550,0),0) -> 315 | N44: =IF($M44=0,"",IF(INDEX(Data!$I$2051:$I$2550,$M44)=0,"Add ID","Row "&(INDEX(Data!$I$2051:$I$2550,$M44)+7))) -> Row 282
A45: =IF($M45=0,"",INDEX(Data!$W$2051:$W$2550,$M45)) -> 33 | B45: =IF($M45=0,"",INDEX(Data!$B$2051:$B$2550,$M45)) -> Roxborough High School | C45: =IF($M45=0,"",INDEX(Data!$C$2051:$C$2550,$M45)) -> District | D45: =IF($M45=0,"",INDEX(Data!$D$2051:$D$2550,$M45)) -> High | E45: =IF($M45=0,"",INDEX(Data!$G$2051:$G$2550,$M45)) -> 0.7794 | F45: =IF($M45=0,"",INDEX(Data!$F$2051:$F$2550,$M45)) -> 529 | G45: =IF($M45=0,"",INDEX(Data!$K$2051:$K$2550,$M45)) -> 0.44340962 | H45: =IF($M45=0,"",INDEX(Data!$L$2051:$L$2550,$M45)) -> 1 | I45: =IF($M45=0,"",INDEX(Data!$T$2051:$T$2550,$M45)) -> 54 | J45: =IF($M45=0,"",INDEX(Data!$U$2051:$U$2550,$M45)) -> Listed | K45: =IF($M45=0,"",INDEX(Data!$AA$2051:$AA$2550,$M45)) -> 78% economic need; 0.44 mi fresh access; 1 nearby resources | L45: =IF($M45=0,"",IF(INDEX(Data!$AN$2051:$AN$2550,$M45)=0,"",IF(INDEX(Data!$U$41:$U$540,INDEX(Data!$AN$2051:$AN$2550,$M45))="","",INDEX(Data!$U$41:$U$540,INDEX(Data!$AN$2051:$AN$2550,$M45))))) -> 215-400-3400 | M45: =IF(COUNTIFS(Data!$AV$2051:$AV$2550,33)=1,MATCH(33,Data!$AV$2051:$AV$2550,0),0) -> 224 | N45: =IF($M45=0,"",IF(INDEX(Data!$I$2051:$I$2550,$M45)=0,"Add ID","Row "&(INDEX(Data!$I$2051:$I$2550,$M45)+7))) -> Row 262
A46: =IF($M46=0,"",INDEX(Data!$W$2051:$W$2550,$M46)) -> 34 | B46: =IF($M46=0,"",INDEX(Data!$B$2051:$B$2550,$M46)) -> Fox Chase School | C46: =IF($M46=0,"",INDEX(Data!$C$2051:$C$2550,$M46)) -> District | D46: =IF($M46=0,"",INDEX(Data!$D$2051:$D$2550,$M46)) -> Elementary | E46: =IF($M46=0,"",INDEX(Data!$G$2051:$G$2550,$M46)) -> 0.6847 | F46: =IF($M46=0,"",INDEX(Data!$F$2051:$F$2550,$M46)) -> 500 | G46: =IF($M46=0,"",INDEX(Data!$K$2051:$K$2550,$M46)) -> 0.86765672 | H46: =IF($M46=0,"",INDEX(Data!$L$2051:$L$2550,$M46)) -> 2 | I46: =IF($M46=0,"",INDEX(Data!$T$2051:$T$2550,$M46)) -> 54 | J46: =IF($M46=0,"",INDEX(Data!$U$2051:$U$2550,$M46)) -> Listed | K46: =IF($M46=0,"",INDEX(Data!$AA$2051:$AA$2550,$M46)) -> 68% economic need; 0.87 mi fresh access; 2 nearby resources | L46: =IF($M46=0,"",IF(INDEX(Data!$AN$2051:$AN$2550,$M46)=0,"",IF(INDEX(Data!$U$41:$U$540,INDEX(Data!$AN$2051:$AN$2550,$M46))="","",INDEX(Data!$U$41:$U$540,INDEX(Data!$AN$2051:$AN$2550,$M46))))) -> 215-400-3170 | M46: =IF(COUNTIFS(Data!$AV$2051:$AV$2550,34)=1,MATCH(34,Data!$AV$2051:$AV$2550,0),0) -> 303 | N46: =IF($M46=0,"",IF(INDEX(Data!$I$2051:$I$2550,$M46)=0,"Add ID","Row "&(INDEX(Data!$I$2051:$I$2550,$M46)+7))) -> Row 85
A47: =IF($M47=0,"",INDEX(Data!$W$2051:$W$2550,$M47)) -> 35 | B47: =IF($M47=0,"",INDEX(Data!$B$2051:$B$2550,$M47)) -> John M. Patterson School | C47: =IF($M47=0,"",INDEX(Data!$C$2051:$C$2550,$M47)) -> District | D47: =IF($M47=0,"",INDEX(Data!$D$2051:$D$2550,$M47)) -> Elementary | E47: =IF($M47=0,"",INDEX(Data!$G$2051:$G$2550,$M47)) -> 0.8425 | F47: =IF($M47=0,"",INDEX(Data!$F$2051:$F$2550,$M47)) -> 353 | G47: =IF($M47=0,"",INDEX(Data!$K$2051:$K$2550,$M47)) -> 0.73087419 | H47: =IF($M47=0,"",INDEX(Data!$L$2051:$L$2550,$M47)) -> 3 | I47: =IF($M47=0,"",INDEX(Data!$T$2051:$T$2550,$M47)) -> 53 | J47: =IF($M47=0,"",INDEX(Data!$U$2051:$U$2550,$M47)) -> Listed | K47: =IF($M47=0,"",INDEX(Data!$AA$2051:$AA$2550,$M47)) -> 84% economic need; 0.73 mi fresh access; 3 nearby resources | L47: =IF($M47=0,"",IF(INDEX(Data!$AN$2051:$AN$2550,$M47)=0,"",IF(INDEX(Data!$U$41:$U$540,INDEX(Data!$AN$2051:$AN$2550,$M47))="","",INDEX(Data!$U$41:$U$540,INDEX(Data!$AN$2051:$AN$2550,$M47))))) -> 215-400-8190 | M47: =IF(COUNTIFS(Data!$AV$2051:$AV$2550,35)=1,MATCH(35,Data!$AV$2051:$AV$2550,0),0) -> 21 | N47: =IF($M47=0,"",IF(INDEX(Data!$I$2051:$I$2550,$M47)=0,"Add ID","Row "&(INDEX(Data!$I$2051:$I$2550,$M47)+7))) -> Row 148
A48: =IF($M48=0,"",INDEX(Data!$W$2051:$W$2550,$M48)) -> 36 | B48: =IF($M48=0,"",INDEX(Data!$B$2051:$B$2550,$M48)) -> Kenderton School | C48: =IF($M48=0,"",INDEX(Data!$C$2051:$C$2550,$M48)) -> District | D48: =IF($M48=0,"",INDEX(Data!$D$2051:$D$2550,$M48)) -> Elementary-Middle | E48: =IF($M48=0,"",INDEX(Data!$G$2051:$G$2550,$M48)) -> 0.9125 | F48: =IF($M48=0,"",INDEX(Data!$F$2051:$F$2550,$M48)) -> 271 | G48: =IF($M48=0,"",INDEX(Data!$K$2051:$K$2550,$M48)) -> 0.90176728 | H48: =IF($M48=0,"",INDEX(Data!$L$2051:$L$2550,$M48)) -> 10 | I48: =IF($M48=0,"",INDEX(Data!$T$2051:$T$2550,$M48)) -> 52 | J48: =IF($M48=0,"",INDEX(Data!$U$2051:$U$2550,$M48)) -> Listed | K48: =IF($M48=0,"",INDEX(Data!$AA$2051:$AA$2550,$M48)) -> 91% economic need; 0.90 mi fresh access; 10 nearby resources | L48: =IF($M48=0,"",IF(INDEX(Data!$AN$2051:$AN$2550,$M48)=0,"",IF(INDEX(Data!$U$41:$U$540,INDEX(Data!$AN$2051:$AN$2550,$M48))="","",INDEX(Data!$U$41:$U$540,INDEX(Data!$AN$2051:$AN$2550,$M48))))) -> 215-400-8340 | M48: =IF(COUNTIFS(Data!$AV$2051:$AV$2550,36)=1,MATCH(36,Data!$AV$2051:$AV$2550,0),0) -> 168 | N48: =IF($M48=0,"",IF(INDEX(Data!$I$2051:$I$2550,$M48)=0,"Add ID","Row "&(INDEX(Data!$I$2051:$I$2550,$M48)+7))) -> Row 162
A49: =IF($M49=0,"",INDEX(Data!$W$2051:$W$2550,$M49)) -> 37 | B49: =IF($M49=0,"",INDEX(Data!$B$2051:$B$2550,$M49)) -> Overbrook Elementary School | C49: =IF($M49=0,"",INDEX(Data!$C$2051:$C$2550,$M49)) -> District | D49: =IF($M49=0,"",INDEX(Data!$D$2051:$D$2550,$M49)) -> Elementary-Middle | E49: =IF($M49=0,"",INDEX(Data!$G$2051:$G$2550,$M49)) -> 0.8558 | F49: =IF($M49=0,"",INDEX(Data!$F$2051:$F$2550,$M49)) -> 215 | G49: =IF($M49=0,"",INDEX(Data!$K$2051:$K$2550,$M49)) -> 1.1247383 | H49: =IF($M49=0,"",INDEX(Data!$L$2051:$L$2550,$M49)) -> 6 | I49: =IF($M49=0,"",INDEX(Data!$T$2051:$T$2550,$M49)) -> 52 | J49: =IF($M49=0,"",INDEX(Data!$U$2051:$U$2550,$M49)) -> Listed | K49: =IF($M49=0,"",INDEX(Data!$AA$2051:$AA$2550,$M49)) -> 86% economic need; 1.12 mi fresh access; 6 nearby resources | L49: =IF($M49=0,"",IF(INDEX(Data!$AN$2051:$AN$2550,$M49)=0,"",IF(INDEX(Data!$U$41:$U$540,INDEX(Data!$AN$2051:$AN$2550,$M49))="","",INDEX(Data!$U$41:$U$540,INDEX(Data!$AN$2051:$AN$2550,$M49))))) -> 215-400-7520 | M49: =IF(COUNTIFS(Data!$AV$2051:$AV$2550,37)=1,MATCH(37,Data!$AV$2051:$AV$2550,0),0) -> 169 | N49: =IF($M49=0,"",IF(INDEX(Data!$I$2051:$I$2550,$M49)=0,"Add ID","Row "&(INDEX(Data!$I$2051:$I$2550,$M49)+7))) -> Row 226
A50: =IF($M50=0,"",INDEX(Data!$W$2051:$W$2550,$M50)) -> 38 | B50: =IF($M50=0,"",INDEX(Data!$B$2051:$B$2550,$M50)) -> F. Amedee Bregy School | C50: =IF($M50=0,"",INDEX(Data!$C$2051:$C$2550,$M50)) -> District | D50: =IF($M50=0,"",INDEX(Data!$D$2051:$D$2550,$M50)) -> Elementary-Middle | E50: =IF($M50=0,"",INDEX(Data!$G$2051:$G$2550,$M50)) -> 0.8191 | F50: =IF($M50=0,"",INDEX(Data!$F$2051:$F$2550,$M50)) -> 244 | G50: =IF($M50=0,"",INDEX(Data!$K$2051:$K$2550,$M50)) -> 0.24888586 | H50: =IF($M50=0,"",INDEX(Data!$L$2051:$L$2550,$M50)) -> 1 | I50: =IF($M50=0,"",INDEX(Data!$T$2051:$T$2550,$M50)) -> 52 | J50: =IF($M50=0,"",INDEX(Data!$U$2051:$U$2550,$M50)) -> Listed | K50: =IF($M50=0,"",INDEX(Data!$AA$2051:$AA$2550,$M50)) -> 82% economic need; 0.25 mi fresh access; 1 nearby resources | L50: =IF($M50=0,"",IF(INDEX(Data!$AN$2051:$AN$2550,$M50)=0,"",IF(INDEX(Data!$U$41:$U$540,INDEX(Data!$AN$2051:$AN$2550,$M50))="","",INDEX(Data!$U$41:$U$540,INDEX(Data!$AN$2051:$AN$2550,$M50))))) -> 215-400-8210 | M50: =IF(COUNTIFS(Data!$AV$2051:$AV$2550,38)=1,MATCH(38,Data!$AV$2051:$AV$2550,0),0) -> 37 | N50: =IF($M50=0,"",IF(INDEX(Data!$I$2051:$I$2550,$M50)=0,"Add ID","Row "&(INDEX(Data!$I$2051:$I$2550,$M50)+7))) -> Row 78
A51: =IF($M51=0,"",INDEX(Data!$W$2051:$W$2550,$M51)) -> 39 | B51: =IF($M51=0,"",INDEX(Data!$B$2051:$B$2550,$M51)) -> General David B. Birney Charter School | C51: =IF($M51=0,"",INDEX(Data!$C$2051:$C$2550,$M51)) -> Charter | D51: =IF($M51=0,"",INDEX(Data!$D$2051:$D$2550,$M51)) -> Elementary-Middle | E51: =IF($M51=0,"",INDEX(Data!$G$2051:$G$2550,$M51)) -> 0.9188 | F51: =IF($M51=0,"",INDEX(Data!$F$2051:$F$2550,$M51)) -> 721 | G51: =IF($M51=0,"",INDEX(Data!$K$2051:$K$2550,$M51)) -> 0.6974453 | H51: =IF($M51=0,"",INDEX(Data!$L$2051:$L$2550,$M51)) -> 11 | I51: =IF($M51=0,"",INDEX(Data!$T$2051:$T$2550,$M51)) -> 50 | J51: =IF($M51=0,"",INDEX(Data!$U$2051:$U$2550,$M51)) -> Listed | K51: =IF($M51=0,"",INDEX(Data!$AA$2051:$AA$2550,$M51)) -> 92% economic need; 0.70 mi fresh access; 11 nearby resources | L51: =IF($M51=0,"",IF(INDEX(Data!$AN$2051:$AN$2550,$M51)=0,"",IF(INDEX(Data!$U$41:$U$540,INDEX(Data!$AN$2051:$AN$2550,$M51))="","",INDEX(Data!$U$41:$U$540,INDEX(Data!$AN$2051:$AN$2550,$M51))))) | M51: =IF(COUNTIFS(Data!$AV$2051:$AV$2550,39)=1,MATCH(39,Data!$AV$2051:$AV$2550,0),0) -> 134 | N51: =IF($M51=0,"",IF(INDEX(Data!$I$2051:$I$2550,$M51)=0,"Add ID","Row "&(INDEX(Data!$I$2051:$I$2550,$M51)+7))) -> Row 96
A52: =IF($M52=0,"",INDEX(Data!$W$2051:$W$2550,$M52)) -> 40 | B52: =IF($M52=0,"",INDEX(Data!$B$2051:$B$2550,$M52)) -> Mastery Charter School at Thomas Campus | C52: =IF($M52=0,"",INDEX(Data!$C$2051:$C$2550,$M52)) -> Charter | D52: =IF($M52=0,"",INDEX(Data!$D$2051:$D$2550,$M52)) -> Elementary-Middle-High | E52: =IF($M52=0,"",INDEX(Data!$G$2051:$G$2550,$M52)) -> 0.9098 | F52: =IF($M52=0,"",INDEX(Data!$F$2051:$F$2550,$M52)) -> 1269 | G52: =IF($M52=0,"",INDEX(Data!$K$2051:$K$2550,$M52)) -> 0.43348122 | H52: =IF($M52=0,"",INDEX(Data!$L$2051:$L$2550,$M52)) -> 4 | I52: =IF($M52=0,"",INDEX(Data!$T$2051:$T$2550,$M52)) -> 50 | J52: =IF($M52=0,"",INDEX(Data!$U$2051:$U$2550,$M52)) -> Listed | K52: =IF($M52=0,"",INDEX(Data!$AA$2051:$AA$2550,$M52)) -> 91% economic need; 0.43 mi fresh access; 4 nearby resources | L52: =IF($M52=0,"",IF(INDEX(Data!$AN$2051:$AN$2550,$M52)=0,"",IF(INDEX(Data!$U$41:$U$540,INDEX(Data!$AN$2051:$AN$2550,$M52))="","",INDEX(Data!$U$41:$U$540,INDEX(Data!$AN$2051:$AN$2550,$M52))))) -> 267-236-0036 | M52: =IF(COUNTIFS(Data!$AV$2051:$AV$2550,40)=1,MATCH(40,Data!$AV$2051:$AV$2550,0),0) -> 116 | N52: =IF($M52=0,"",IF(INDEX(Data!$I$2051:$I$2550,$M52)=0,"Add ID","Row "&(INDEX(Data!$I$2051:$I$2550,$M52)+7))) -> Row 200
A53: =IF($M53=0,"",INDEX(Data!$W$2051:$W$2550,$M53)) -> 41 | B53: =IF($M53=0,"",INDEX(Data!$B$2051:$B$2550,$M53)) -> Mastery Charter School at Hardy Williams | C53: =IF($M53=0,"",INDEX(Data!$C$2051:$C$2550,$M53)) -> Charter | D53: =IF($M53=0,"",INDEX(Data!$D$2051:$D$2550,$M53)) -> Elementary-Middle-High | E53: =IF($M53=0,"",INDEX(Data!$G$2051:$G$2550,$M53)) -> 0.9076 | F53: =IF($M53=0,"",INDEX(Data!$F$2051:$F$2550,$M53)) -> 1211 | G53: =IF($M53=0,"",INDEX(Data!$K$2051:$K$2550,$M53)) -> 0.54181122 | H53: =IF($M53=0,"",INDEX(Data!$L$2051:$L$2550,$M53)) -> 10 | I53: =IF($M53=0,"",INDEX(Data!$T$2051:$T$2550,$M53)) -> 50 | J53: =IF($M53=0,"",INDEX(Data!$U$2051:$U$2550,$M53)) -> Listed | K53: =IF($M53=0,"",INDEX(Data!$AA$2051:$AA$2550,$M53)) -> 91% economic need; 0.54 mi fresh access; 10 nearby resources | L53: =IF($M53=0,"",IF(INDEX(Data!$AN$2051:$AN$2550,$M53)=0,"",IF(INDEX(Data!$U$41:$U$540,INDEX(Data!$AN$2051:$AN$2550,$M53))="","",INDEX(Data!$U$41:$U$540,INDEX(Data!$AN$2051:$AN$2550,$M53))))) -> 215-724-2343 | M53: =IF(COUNTIFS(Data!$AV$2051:$AV$2550,41)=1,MATCH(41,Data!$AV$2051:$AV$2550,0),0) -> 87 | N53: =IF($M53=0,"",IF(INDEX(Data!$I$2051:$I$2550,$M53)=0,"Add ID","Row "&(INDEX(Data!$I$2051:$I$2550,$M53)+7))) -> Row 193
A54: =IF($M54=0,"",INDEX(Data!$W$2051:$W$2550,$M54)) -> 42 | B54: =IF($M54=0,"",INDEX(Data!$B$2051:$B$2550,$M54)) -> Juniata Park Academy | C54: =IF($M54=0,"",INDEX(Data!$C$2051:$C$2550,$M54)) -> District | D54: =IF($M54=0,"",INDEX(Data!$D$2051:$D$2550,$M54)) -> Elementary-Middle | E54: =IF($M54=0,"",INDEX(Data!$G$2051:$G$2550,$M54)) -> 0.8799 | F54: =IF($M54=0,"",INDEX(Data!$F$2051:$F$2550,$M54)) -> 784 | G54: =IF($M54=0,"",INDEX(Data!$K$2051:$K$2550,$M54)) -> 0.26634925 | H54: =IF($M54=0,"",INDEX(Data!$L$2051:$L$2550,$M54)) -> 3 | I54: =IF($M54=0,"",INDEX(Data!$T$2051:$T$2550,$M54)) -> 50 | J54: =IF($M54=0,"",INDEX(Data!$U$2051:$U$2550,$M54)) -> Listed | K54: =IF($M54=0,"",INDEX(Data!$AA$2051:$AA$2550,$M54)) -> 88% economic need; 0.27 mi fresh access; 3 nearby resources | L54: =IF($M54=0,"",IF(INDEX(Data!$AN$2051:$AN$2550,$M54)=0,"",IF(INDEX(Data!$U$41:$U$540,INDEX(Data!$AN$2051:$AN$2550,$M54))="","",INDEX(Data!$U$41:$U$540,INDEX(Data!$AN$2051:$AN$2550,$M54))))) -> 215-400-7010 | M54: =IF(COUNTIFS(Data!$AV$2051:$AV$2550,42)=1,MATCH(42,Data!$AV$2051:$AV$2550,0),0) -> 260 | N54: =IF($M54=0,"",IF(INDEX(Data!$I$2051:$I$2550,$M54)=0,"Add ID","Row "&(INDEX(Data!$I$2051:$I$2550,$M54)+7))) -> Row 161
A55: =IF($M55=0,"",INDEX(Data!$W$2051:$W$2550,$M55)) -> 43 | B55: =IF($M55=0,"",INDEX(Data!$B$2051:$B$2550,$M55)) -> Thomas Holme School | C55: =IF($M55=0,"",INDEX(Data!$C$2051:$C$2550,$M55)) -> District | D55: =IF($M55=0,"",INDEX(Data!$D$2051:$D$2550,$M55)) -> Elementary-Middle | E55: =IF($M55=0,"",INDEX(Data!$G$2051:$G$2550,$M55)) -> 0.7798 | F55: =IF($M55=0,"",INDEX(Data!$F$2051:$F$2550,$M55)) -> 801 | G55: =IF($M55=0,"",INDEX(Data!$K$2051:$K$2550,$M55)) -> 0.2110836 | H55: =IF($M55=0,"",INDEX(Data!$L$2051:$L$2550,$M55)) -> 1 | I55: =IF($M55=0,"",INDEX(Data!$T$2051:$T$2550,$M55)) -> 50 | J55: =IF($M55=0,"",INDEX(Data!$U$2051:$U$2550,$M55)) -> Listed | K55: =IF($M55=0,"",INDEX(Data!$AA$2051:$AA$2550,$M55)) -> 78% economic need; 0.21 mi fresh access; 1 nearby resources | L55: =IF($M55=0,"",IF(INDEX(Data!$AN$2051:$AN$2550,$M55)=0,"",IF(INDEX(Data!$U$41:$U$540,INDEX(Data!$AN$2051:$AN$2550,$M55))="","",INDEX(Data!$U$41:$U$540,INDEX(Data!$AN$2051:$AN$2550,$M55))))) -> 215-400-3130 | M55: =IF(COUNTIFS(Data!$AV$2051:$AV$2550,43)=1,MATCH(43,Data!$AV$2051:$AV$2550,0),0) -> 304 | N55: =IF($M55=0,"",IF(INDEX(Data!$I$2051:$I$2550,$M55)=0,"Add ID","Row "&(INDEX(Data!$I$2051:$I$2550,$M55)+7))) -> Row 301
A56: =IF($M56=0,"",INDEX(Data!$W$2051:$W$2550,$M56)) -> 44 | B56: =IF($M56=0,"",INDEX(Data!$B$2051:$B$2550,$M56)) -> J. Hampton Moore School | C56: =IF($M56=0,"",INDEX(Data!$C$2051:$C$2550,$M56)) -> District | D56: =IF($M56=0,"",INDEX(Data!$D$2051:$D$2550,$M56)) -> Elementary | E56: =IF($M56=0,"",INDEX(Data!$G$2051:$G$2550,$M56)) -> 0.7795 | F56: =IF($M56=0,"",INDEX(Data!$F$2051:$F$2550,$M56)) -> 1162 | G56: =IF($M56=0,"",INDEX(Data!$K$2051:$K$2550,$M56)) -> 0.48677922 | H56: =IF($M56=0,"",INDEX(Data!$L$2051:$L$2550,$M56)) -> 2 | I56: =IF($M56=0,"",INDEX(Data!$T$2051:$T$2550,$M56)) -> 50 | J56: =IF($M56=0,"",INDEX(Data!$U$2051:$U$2550,$M56)) -> Listed | K56: =IF($M56=0,"",INDEX(Data!$AA$2051:$AA$2550,$M56)) -> 78% economic need; 0.49 mi fresh access; 2 nearby resources | L56: =IF($M56=0,"",IF(INDEX(Data!$AN$2051:$AN$2550,$M56)=0,"",IF(INDEX(Data!$U$41:$U$540,INDEX(Data!$AN$2051:$AN$2550,$M56))="","",INDEX(Data!$U$41:$U$540,INDEX(Data!$AN$2051:$AN$2550,$M56))))) -> 215-400-3180 | M56: =IF(COUNTIFS(Data!$AV$2051:$AV$2550,44)=1,MATCH(44,Data!$AV$2051:$AV$2550,0),0) -> 306 | N56: =IF($M56=0,"",IF(INDEX(Data!$I$2051:$I$2550,$M56)=0,"Add ID","Row "&(INDEX(Data!$I$2051:$I$2550,$M56)+7))) -> Row 131
A57: =IF($M57=0,"",INDEX(Data!$W$2051:$W$2550,$M57)) -> 45 | B57: =IF($M57=0,"",INDEX(Data!$B$2051:$B$2550,$M57)) -> Castor Gardens Middle School | C57: =IF($M57=0,"",INDEX(Data!$C$2051:$C$2550,$M57)) -> District | D57: =IF($M57=0,"",INDEX(Data!$D$2051:$D$2550,$M57)) -> Middle | E57: =IF($M57=0,"",INDEX(Data!$G$2051:$G$2550,$M57)) -> 0.7573 | F57: =IF($M57=0,"",INDEX(Data!$F$2051:$F$2550,$M57)) -> 1340 | G57: =IF($M57=0,"",INDEX(Data!$K$2051:$K$2550,$M57)) -> 0.21854623 | H57: =IF($M57=0,"",INDEX(Data!$L$2051:$L$2550,$M57)) -> 1 | I57: =IF($M57=0,"",INDEX(Data!$T$2051:$T$2550,$M57)) -> 50 | J57: =IF($M57=0,"",INDEX(Data!$U$2051:$U$2550,$M57)) -> Listed | K57: =IF($M57=0,"",INDEX(Data!$AA$2051:$AA$2550,$M57)) -> 76% economic need; 0.22 mi fresh access; 1 nearby resources | L57: =IF($M57=0,"",IF(INDEX(Data!$AN$2051:$AN$2550,$M57)=0,"",IF(INDEX(Data!$U$41:$U$540,INDEX(Data!$AN$2051:$AN$2550,$M57))="","",INDEX(Data!$U$41:$U$540,INDEX(Data!$AN$2051:$AN$2550,$M57))))) -> 215-400-3190 | M57: =IF(COUNTIFS(Data!$AV$2051:$AV$2550,45)=1,MATCH(45,Data!$AV$2051:$AV$2550,0),0) -> 294 | N57: =IF($M57=0,"",IF(INDEX(Data!$I$2051:$I$2550,$M57)=0,"Add ID","Row "&(INDEX(Data!$I$2051:$I$2550,$M57)+7))) -> Row 44
A58: =IF($M58=0,"",INDEX(Data!$W$2051:$W$2550,$M58)) -> 46 | B58: =IF($M58=0,"",INDEX(Data!$B$2051:$B$2550,$M58)) -> West Philadelphia Achievement Charter School | C58: =IF($M58=0,"",INDEX(Data!$C$2051:$C$2550,$M58)) -> Charter | D58: =IF($M58=0,"",INDEX(Data!$D$2051:$D$2550,$M58)) -> Elementary | E58: =IF($M58=0,"",INDEX(Data!$G$2051:$G$2550,$M58)) -> 1 | F58: =IF($M58=0,"",INDEX(Data!$F$2051:$F$2550,$M58)) -> 613 | G58: =IF($M58=0,"",INDEX(Data!$K$2051:$K$2550,$M58)) -> 0.52753064 | H58: =IF($M58=0,"",INDEX(Data!$L$2051:$L$2550,$M58)) -> 7 | I58: =IF($M58=0,"",INDEX(Data!$T$2051:$T$2550,$M58)) -> 49 | J58: =IF($M58=0,"",INDEX(Data!$U$2051:$U$2550,$M58)) -> Listed | K58: =IF($M58=0,"",INDEX(Data!$AA$2051:$AA$2550,$M58)) -> 100% economic need; 0.53 mi fresh access; 7 nearby resources | L58: =IF($M58=0,"",IF(INDEX(Data!$AN$2051:$AN$2550,$M58)=0,"",IF(INDEX(Data!$U$41:$U$540,INDEX(Data!$AN$2051:$AN$2550,$M58))="","",INDEX(Data!$U$41:$U$540,INDEX(Data!$AN$2051:$AN$2550,$M58))))) -> 215-476-6471 | M58: =IF(COUNTIFS(Data!$AV$2051:$AV$2550,46)=1,MATCH(46,Data!$AV$2051:$AV$2550,0),0) -> 100 | N58: =IF($M58=0,"",IF(INDEX(Data!$I$2051:$I$2550,$M58)=0,"Add ID","Row "&(INDEX(Data!$I$2051:$I$2550,$M58)+7))) -> Row 316
A59: =IF($M59=0,"",INDEX(Data!$W$2051:$W$2550,$M59)) -> 47 | B59: =IF($M59=0,"",INDEX(Data!$B$2051:$B$2550,$M59)) -> Mastery Charter School at Wister | C59: =IF($M59=0,"",INDEX(Data!$C$2051:$C$2550,$M59)) -> Charter | D59: =IF($M59=0,"",INDEX(Data!$D$2051:$D$2550,$M59)) -> Elementary | E59: =IF($M59=0,"",INDEX(Data!$G$2051:$G$2550,$M59)) -> 0.998 | F59: =IF($M59=0,"",INDEX(Data!$F$2051:$F$2550,$M59)) -> 505 | G59: =IF($M59=0,"",INDEX(Data!$K$2051:$K$2550,$M59)) -> 0.6254119 | H59: =IF($M59=0,"",INDEX(Data!$L$2051:$L$2550,$M59)) -> 19 | I59: =IF($M59=0,"",INDEX(Data!$T$2051:$T$2550,$M59)) -> 49 | J59: =IF($M59=0,"",INDEX(Data!$U$2051:$U$2550,$M59)) -> Listed | K59: =IF($M59=0,"",INDEX(Data!$AA$2051:$AA$2550,$M59)) -> 100% economic need; 0.63 mi fresh access; 19 nearby resources | L59: =IF($M59=0,"",IF(INDEX(Data!$AN$2051:$AN$2550,$M59)=0,"",IF(INDEX(Data!$U$41:$U$540,INDEX(Data!$AN$2051:$AN$2550,$M59))="","",INDEX(Data!$U$41:$U$540,INDEX(Data!$AN$2051:$AN$2550,$M59))))) | M59: =IF(COUNTIFS(Data!$AV$2051:$AV$2550,47)=1,MATCH(47,Data!$AV$2051:$AV$2550,0),0) -> 140 | N59: =IF($M59=0,"",IF(INDEX(Data!$I$2051:$I$2550,$M59)=0,"Add ID","Row "&(INDEX(Data!$I$2051:$I$2550,$M59)+7))) -> Row 201
A60: =IF($M60=0,"",INDEX(Data!$W$2051:$W$2550,$M60)) -> 48 | B60: =IF($M60=0,"",INDEX(Data!$B$2051:$B$2550,$M60)) -> Mastery Prep Elementary Charter School | C60: =IF($M60=0,"",INDEX(Data!$C$2051:$C$2550,$M60)) -> Charter | D60: =IF($M60=0,"",INDEX(Data!$D$2051:$D$2550,$M60)) -> Elementary | E60: =IF($M60=0,"",INDEX(Data!$G$2051:$G$2550,$M60)) -> 0.9152 | F60: =IF($M60=0,"",INDEX(Data!$F$2051:$F$2550,$M60)) -> 602 | G60: =IF($M60=0,"",INDEX(Data!$K$2051:$K$2550,$M60)) -> 0.65998674 | H60: =IF($M60=0,"",INDEX(Data!$L$2051:$L$2550,$M60)) -> 9 | I60: =IF($M60=0,"",INDEX(Data!$T$2051:$T$2550,$M60)) -> 49 | J60: =IF($M60=0,"",INDEX(Data!$U$2051:$U$2550,$M60)) -> Listed | K60: =IF($M60=0,"",INDEX(Data!$AA$2051:$AA$2550,$M60)) -> 92% economic need; 0.66 mi fresh access; 9 nearby resources | L60: =IF($M60=0,"",IF(INDEX(Data!$AN$2051:$AN$2550,$M60)=0,"",IF(INDEX(Data!$U$41:$U$540,INDEX(Data!$AN$2051:$AN$2550,$M60))="","",INDEX(Data!$U$41:$U$540,INDEX(Data!$AN$2051:$AN$2550,$M60))))) | M60: =IF(COUNTIFS(Data!$AV$2051:$AV$2550,48)=1,MATCH(48,Data!$AV$2051:$AV$2550,0),0) -> 145 | N60: =IF($M60=0,"",IF(INDEX(Data!$I$2051:$I$2550,$M60)=0,"Add ID","Row "&(INDEX(Data!$I$2051:$I$2550,$M60)+7))) -> Row 202
A61: =IF($M61=0,"",INDEX(Data!$W$2051:$W$2550,$M61)) -> 49 | B61: =IF($M61=0,"",INDEX(Data!$B$2051:$B$2550,$M61)) -> Mastery Charter High School | C61: =IF($M61=0,"",INDEX(Data!$C$2051:$C$2550,$M61)) -> Charter | D61: =IF($M61=0,"",INDEX(Data!$D$2051:$D$2550,$M61)) -> Middle-High | E61: =IF($M61=0,"",INDEX(Data!$G$2051:$G$2550,$M61)) -> 0.8921 | F61: =IF($M61=0,"",INDEX(Data!$F$2051:$F$2550,$M61)) -> 614 | G61: =IF($M61=0,"",INDEX(Data!$K$2051:$K$2550,$M61)) -> 0.32748913 | H61: =IF($M61=0,"",INDEX(Data!$L$2051:$L$2550,$M61)) -> 3 | I61: =IF($M61=0,"",INDEX(Data!$T$2051:$T$2550,$M61)) -> 49 | J61: =IF($M61=0,"",INDEX(Data!$U$2051:$U$2550,$M61)) -> Listed | K61: =IF($M61=0,"",INDEX(Data!$AA$2051:$AA$2550,$M61)) -> 89% economic need; 0.33 mi fresh access; 3 nearby resources | L61: =IF($M61=0,"",IF(INDEX(Data!$AN$2051:$AN$2550,$M61)=0,"",IF(INDEX(Data!$U$41:$U$540,INDEX(Data!$AN$2051:$AN$2550,$M61))="","",INDEX(Data!$U$41:$U$540,INDEX(Data!$AN$2051:$AN$2550,$M61))))) -> 215-922-1902 | M61: =IF(COUNTIFS(Data!$AV$2051:$AV$2550,49)=1,MATCH(49,Data!$AV$2051:$AV$2550,0),0) -> 104 | N61: =IF($M61=0,"",IF(INDEX(Data!$I$2051:$I$2550,$M61)=0,"Add ID","Row "&(INDEX(Data!$I$2051:$I$2550,$M61)+7))) -> Row 188
A62: =IF($M62=0,"",INDEX(Data!$W$2051:$W$2550,$M62)) -> 50 | B62: =IF($M62=0,"",INDEX(Data!$B$2051:$B$2550,$M62)) -> High School of the Future | C62: =IF($M62=0,"",INDEX(Data!$C$2051:$C$2550,$M62)) -> District | D62: =IF($M62=0,"",INDEX(Data!$D$2051:$D$2550,$M62)) -> High | E62: =IF($M62=0,"",INDEX(Data!$G$2051:$G$2550,$M62)) -> 0.8416 | F62: =IF($M62=0,"",INDEX(Data!$F$2051:$F$2550,$M62)) -> 648 | G62: =IF($M62=0,"",INDEX(Data!$K$2051:$K$2550,$M62)) -> 0.92711382 | H62: =IF($M62=0,"",INDEX(Data!$L$2051:$L$2550,$M62)) -> 9 | I62: =IF($M62=0,"",INDEX(Data!$T$2051:$T$2550,$M62)) -> 49 | J62: =IF($M62=0,"",INDEX(Data!$U$2051:$U$2550,$M62)) -> Listed | K62: =IF($M62=0,"",INDEX(Data!$AA$2051:$AA$2550,$M62)) -> 84% economic need; 0.93 mi fresh access; 9 nearby resources | L62: =IF($M62=0,"",IF(INDEX(Data!$AN$2051:$AN$2550,$M62)=0,"",IF(INDEX(Data!$U$41:$U$540,INDEX(Data!$AN$2051:$AN$2550,$M62))="","",INDEX(Data!$U$41:$U$540,INDEX(Data!$AN$2051:$AN$2550,$M62))))) -> 215-400-7790 | M62: =IF(COUNTIFS(Data!$AV$2051:$AV$2550,50)=1,MATCH(50,Data!$AV$2051:$AV$2550,0),0) -> 3 | N62: =IF($M62=0,"",IF(INDEX(Data!$I$2051:$I$2550,$M62)=0,"Add ID","Row "&(INDEX(Data!$I$2051:$I$2550,$M62)+7))) -> Row 121
A63: =IF($M63=0,"",INDEX(Data!$W$2051:$W$2550,$M63)) -> 51 | B63: =IF($M63=0,"",INDEX(Data!$B$2051:$B$2550,$M63)) -> Henry W. Lawton School | C63: =IF($M63=0,"",INDEX(Data!$C$2051:$C$2550,$M63)) -> District | D63: =IF($M63=0,"",INDEX(Data!$D$2051:$D$2550,$M63)) -> Elementary | E63: =IF($M63=0,"",INDEX(Data!$G$2051:$G$2550,$M63)) -> 0.8275 | F63: =IF($M63=0,"",INDEX(Data!$F$2051:$F$2550,$M63)) -> 513 | G63: =IF($M63=0,"",INDEX(Data!$K$2051:$K$2550,$M63)) -> 0.36615105 | H63: =IF($M63=0,"",INDEX(Data!$L$2051:$L$2550,$M63)) -> 3 | I63: =IF($M63=0,"",INDEX(Data!$T$2051:$T$2550,$M63)) -> 49 | J63: =IF($M63=0,"",INDEX(Data!$U$2051:$U$2550,$M63)) -> Listed | K63: =IF($M63=0,"",INDEX(Data!$AA$2051:$AA$2550,$M63)) -> 83% economic need; 0.37 mi fresh access; 3 nearby resources | L63: =IF($M63=0,"",IF(INDEX(Data!$AN$2051:$AN$2550,$M63)=0,"",IF(INDEX(Data!$U$41:$U$540,INDEX(Data!$AN$2051:$AN$2550,$M63))="","",INDEX(Data!$U$41:$U$540,INDEX(Data!$AN$2051:$AN$2550,$M63))))) -> 215-400-3340 | M63: =IF(COUNTIFS(Data!$AV$2051:$AV$2550,51)=1,MATCH(51,Data!$AV$2051:$AV$2550,0),0) -> 270 | N63: =IF($M63=0,"",IF(INDEX(Data!$I$2051:$I$2550,$M63)=0,"Add ID","Row "&(INDEX(Data!$I$2051:$I$2550,$M63)+7))) -> Row 119
A64: =IF($M64=0,"",INDEX(Data!$W$2051:$W$2550,$M64)) -> 52 | B64: =IF($M64=0,"",INDEX(Data!$B$2051:$B$2550,$M64)) -> Martin Luther King High School | C64: =IF($M64=0,"",INDEX(Data!$C$2051:$C$2550,$M64)) -> District | D64: =IF($M64=0,"",INDEX(Data!$D$2051:$D$2550,$M64)) -> High | E64: =IF($M64=0,"",INDEX(Data!$G$2051:$G$2550,$M64)) -> 0.8066 | F64: =IF($M64=0,"",INDEX(Data!$F$2051:$F$2550,$M64)) -> 604 | G64: =IF($M64=0,"",INDEX(Data!$K$2051:$K$2550,$M64)) -> 0.75924371 | H64: =IF($M64=0,"",INDEX(Data!$L$2051:$L$2550,$M64)) -> 9 | I64: =IF($M64=0,"",INDEX(Data!$T$2051:$T$2550,$M64)) -> 49 | J64: =IF($M64=0,"",INDEX(Data!$U$2051:$U$2550,$M64)) -> Listed | K64: =IF($M64=0,"",INDEX(Data!$AA$2051:$AA$2550,$M64)) -> 81% economic need; 0.76 mi fresh access; 9 nearby resources | L64: =IF($M64=0,"",IF(INDEX(Data!$AN$2051:$AN$2550,$M64)=0,"",IF(INDEX(Data!$U$41:$U$540,INDEX(Data!$AN$2051:$AN$2550,$M64))="","",INDEX(Data!$U$41:$U$540,INDEX(Data!$AN$2051:$AN$2550,$M64))))) -> 215-400-3500 | M64: =IF(COUNTIFS(Data!$AV$2051:$AV$2550,52)=1,MATCH(52,Data!$AV$2051:$AV$2550,0),0) -> 227 | N64: =IF($M64=0,"",IF(INDEX(Data!$I$2051:$I$2550,$M64)=0,"Add ID","Row "&(INDEX(Data!$I$2051:$I$2550,$M64)+7))) -> Row 184
A65: =IF($M65=0,"",INDEX(Data!$W$2051:$W$2550,$M65)) -> 53 | B65: =IF($M65=0,"",INDEX(Data!$B$2051:$B$2550,$M65)) -> Hill-Freedman World Academy | C65: =IF($M65=0,"",INDEX(Data!$C$2051:$C$2550,$M65)) -> District | D65: =IF($M65=0,"",INDEX(Data!$D$2051:$D$2550,$M65)) -> Middle-High | E65: =IF($M65=0,"",INDEX(Data!$G$2051:$G$2550,$M65)) -> 0.6781 | F65: =IF($M65=0,"",INDEX(Data!$F$2051:$F$2550,$M65)) -> 650 | G65: =IF($M65=0,"",INDEX(Data!$K$2051:$K$2550,$M65)) -> 0.83599564 | H65: =IF($M65=0,"",INDEX(Data!$L$2051:$L$2550,$M65)) -> 3 | I65: =IF($M65=0,"",INDEX(Data!$T$2051:$T$2550,$M65)) -> 49 | J65: =IF($M65=0,"",INDEX(Data!$U$2051:$U$2550,$M65)) -> Listed | K65: =IF($M65=0,"",INDEX(Data!$AA$2051:$AA$2550,$M65)) -> 68% economic need; 0.84 mi fresh access; 3 nearby resources | L65: =IF($M65=0,"",IF(INDEX(Data!$AN$2051:$AN$2550,$M65)=0,"",IF(INDEX(Data!$U$41:$U$540,INDEX(Data!$AN$2051:$AN$2550,$M65))="","",INDEX(Data!$U$41:$U$540,INDEX(Data!$AN$2051:$AN$2550,$M65))))) -> 215-400-3530 | M65: =IF(COUNTIFS(Data!$AV$2051:$AV$2550,53)=1,MATCH(53,Data!$AV$2051:$AV$2550,0),0) -> 248 | N65: =IF($M65=0,"",IF(INDEX(Data!$I$2051:$I$2550,$M65)=0,"Add ID","Row "&(INDEX(Data!$I$2051:$I$2550,$M65)+7))) -> Row 122
A66: =IF($M66=0,"",INDEX(Data!$W$2051:$W$2550,$M66)) -> 54 | B66: =IF($M66=0,"",INDEX(Data!$B$2051:$B$2550,$M66)) -> Watson Comly School | C66: =IF($M66=0,"",INDEX(Data!$C$2051:$C$2550,$M66)) -> District | D66: =IF($M66=0,"",INDEX(Data!$D$2051:$D$2550,$M66)) -> Elementary | E66: =IF($M66=0,"",INDEX(Data!$G$2051:$G$2550,$M66)) -> 0.6656 | F66: =IF($M66=0,"",INDEX(Data!$F$2051:$F$2550,$M66)) -> 660 | G66: =IF($M66=0,"",INDEX(Data!$K$2051:$K$2550,$M66)) -> 0.42671827 | H66: =IF($M66=0,"",INDEX(Data!$L$2051:$L$2550,$M66)) -> 1 | I66: =IF($M66=0,"",INDEX(Data!$T$2051:$T$2550,$M66)) -> 49 | J66: =IF($M66=0,"",INDEX(Data!$U$2051:$U$2550,$M66)) -> Listed | K66: =IF($M66=0,"",INDEX(Data!$AA$2051:$AA$2550,$M66)) -> 67% economic need; 0.43 mi fresh access; 1 nearby resources | L66: =IF($M66=0,"",IF(INDEX(Data!$AN$2051:$AN$2550,$M66)=0,"",IF(INDEX(Data!$U$41:$U$540,INDEX(Data!$AN$2051:$AN$2550,$M66))="","",INDEX(Data!$U$41:$U$540,INDEX(Data!$AN$2051:$AN$2550,$M66))))) -> 215-400-3010 | M66: =IF(COUNTIFS(Data!$AV$2051:$AV$2550,54)=1,MATCH(54,Data!$AV$2051:$AV$2550,0),0) -> 310 | N66: =IF($M66=0,"",IF(INDEX(Data!$I$2051:$I$2550,$M66)=0,"Add ID","Row "&(INDEX(Data!$I$2051:$I$2550,$M66)+7))) -> Row 314
A67: =IF($M67=0,"",INDEX(Data!$W$2051:$W$2550,$M67)) -> 55 | B67: =IF($M67=0,"",INDEX(Data!$B$2051:$B$2550,$M67)) -> Arts Academy at Benjamin Rush | C67: =IF($M67=0,"",INDEX(Data!$C$2051:$C$2550,$M67)) -> District | D67: =IF($M67=0,"",INDEX(Data!$D$2051:$D$2550,$M67)) -> High | E67: =IF($M67=0,"",INDEX(Data!$G$2051:$G$2550,$M67)) -> 0.5581 | F67: =IF($M67=0,"",INDEX(Data!$F$2051:$F$2550,$M67)) -> 602 | G67: =IF($M67=0,"",INDEX(Data!$K$2051:$K$2550,$M67)) -> 0.32811668 | H67: =IF($M67=0,"",INDEX(Data!$L$2051:$L$2550,$M67)) -> 0 | I67: =IF($M67=0,"",INDEX(Data!$T$2051:$T$2550,$M67)) -> 49 | J67: =IF($M67=0,"",INDEX(Data!$U$2051:$U$2550,$M67)) -> Listed | K67: =IF($M67=0,"",INDEX(Data!$AA$2051:$AA$2550,$M67)) -> 56% economic need; 0.33 mi fresh access; 0 nearby resources | L67: =IF($M67=0,"",IF(INDEX(Data!$AN$2051:$AN$2550,$M67)=0,"",IF(INDEX(Data!$U$41:$U$540,INDEX(Data!$AN$2051:$AN$2550,$M67))="","",INDEX(Data!$U$41:$U$540,INDEX(Data!$AN$2051:$AN$2550,$M67))))) -> 215-400-3030 | M67: =IF(COUNTIFS(Data!$AV$2051:$AV$2550,55)=1,MATCH(55,Data!$AV$2051:$AV$2550,0),0) -> 289 | N67: =IF($M67=0,"",IF(INDEX(Data!$I$2051:$I$2550,$M67)=0,"Add ID","Row "&(INDEX(Data!$I$2051:$I$2550,$M67)+7))) -> Row 31
A68: =IF($M68=0,"",INDEX(Data!$W$2051:$W$2550,$M68)) -> 56 | B68: =IF($M68=0,"",INDEX(Data!$B$2051:$B$2550,$M68)) -> Frances E. Willard School | C68: =IF($M68=0,"",INDEX(Data!$C$2051:$C$2550,$M68)) -> District | D68: =IF($M68=0,"",INDEX(Data!$D$2051:$D$2550,$M68)) -> Elementary | E68: =IF($M68=0,"",INDEX(Data!$G$2051:$G$2550,$M68)) -> 0.9342 | F68: =IF($M68=0,"",INDEX(Data!$F$2051:$F$2550,$M68)) -> 352 | G68: =IF($M68=0,"",INDEX(Data!$K$2051:$K$2550,$M68)) -> 0.64030942 | H68: =IF($M68=0,"",INDEX(Data!$L$2051:$L$2550,$M68)) -> 12 | I68: =IF($M68=0,"",INDEX(Data!$T$2051:$T$2550,$M68)) -> 48 | J68: =IF($M68=0,"",INDEX(Data!$U$2051:$U$2550,$M68)) -> Listed | K68: =IF($M68=0,"",INDEX(Data!$AA$2051:$AA$2550,$M68)) -> 93% economic need; 0.64 mi fresh access; 12 nearby resources | L68: =IF($M68=0,"",IF(INDEX(Data!$AN$2051:$AN$2550,$M68)=0,"",IF(INDEX(Data!$U$41:$U$540,INDEX(Data!$AN$2051:$AN$2550,$M68))="","",INDEX(Data!$U$41:$U$540,INDEX(Data!$AN$2051:$AN$2550,$M68))))) -> 215-400-7180 | M68: =IF(COUNTIFS(Data!$AV$2051:$AV$2550,56)=1,MATCH(56,Data!$AV$2051:$AV$2550,0),0) -> 205 | N68: =IF($M68=0,"",IF(INDEX(Data!$I$2051:$I$2550,$M68)=0,"Add ID","Row "&(INDEX(Data!$I$2051:$I$2550,$M68)+7))) -> Row 86
A69: =IF($M69=0,"",INDEX(Data!$W$2051:$W$2550,$M69)) -> 57 | B69: =IF($M69=0,"",INDEX(Data!$B$2051:$B$2550,$M69)) -> E. Washington Rhodes School | C69: =IF($M69=0,"",INDEX(Data!$C$2051:$C$2550,$M69)) -> District | D69: =IF($M69=0,"",INDEX(Data!$D$2051:$D$2550,$M69)) -> Elementary-Middle | E69: =IF($M69=0,"",INDEX(Data!$G$2051:$G$2550,$M69)) -> 0.9248 | F69: =IF($M69=0,"",INDEX(Data!$F$2051:$F$2550,$M69)) -> 350 | G69: =IF($M69=0,"",INDEX(Data!$K$2051:$K$2550,$M69)) -> 0.52728564 | H69: =IF($M69=0,"",INDEX(Data!$L$2051:$L$2550,$M69)) -> 9 | I69: =IF($M69=0,"",INDEX(Data!$T$2051:$T$2550,$M69)) -> 48 | J69: =IF($M69=0,"",INDEX(Data!$U$2051:$U$2550,$M69)) -> Listed | K69: =IF($M69=0,"",INDEX(Data!$AA$2051:$AA$2550,$M69)) -> 92% economic need; 0.53 mi fresh access; 9 nearby resources | L69: =IF($M69=0,"",IF(INDEX(Data!$AN$2051:$AN$2550,$M69)=0,"",IF(INDEX(Data!$U$41:$U$540,INDEX(Data!$AN$2051:$AN$2550,$M69))="","",INDEX(Data!$U$41:$U$540,INDEX(Data!$AN$2051:$AN$2550,$M69))))) -> 215-400-7060 | M69: =IF(COUNTIFS(Data!$AV$2051:$AV$2550,57)=1,MATCH(57,Data!$AV$2051:$AV$2550,0),0) -> 167 | N69: =IF($M69=0,"",IF(INDEX(Data!$I$2051:$I$2550,$M69)=0,"Add ID","Row "&(INDEX(Data!$I$2051:$I$2550,$M69)+7))) -> Row 60
A70: =IF($M70=0,"",INDEX(Data!$W$2051:$W$2550,$M70)) -> 58 | B70: =IF($M70=0,"",INDEX(Data!$B$2051:$B$2550,$M70)) -> Mary M. Bethune School | C70: =IF($M70=0,"",INDEX(Data!$C$2051:$C$2550,$M70)) -> District | D70: =IF($M70=0,"",INDEX(Data!$D$2051:$D$2550,$M70)) -> Elementary-Middle | E70: =IF($M70=0,"",INDEX(Data!$G$2051:$G$2550,$M70)) -> 0.9214 | F70: =IF($M70=0,"",INDEX(Data!$F$2051:$F$2550,$M70)) -> 353 | G70: =IF($M70=0,"",INDEX(Data!$K$2051:$K$2550,$M70)) -> 0.67579568 | H70: =IF($M70=0,"",INDEX(Data!$L$2051:$L$2550,$M70)) -> 10 | I70: =IF($M70=0,"",INDEX(Data!$T$2051:$T$2550,$M70)) -> 48 | J70: =IF($M70=0,"",INDEX(Data!$U$2051:$U$2550,$M70)) -> Listed | K70: =IF($M70=0,"",INDEX(Data!$AA$2051:$AA$2550,$M70)) -> 92% economic need; 0.68 mi fresh access; 10 nearby resources | L70: =IF($M70=0,"",IF(INDEX(Data!$AN$2051:$AN$2550,$M70)=0,"",IF(INDEX(Data!$U$41:$U$540,INDEX(Data!$AN$2051:$AN$2550,$M70))="","",INDEX(Data!$U$41:$U$540,INDEX(Data!$AN$2051:$AN$2550,$M70))))) -> 215-400-3890 | M70: =IF(COUNTIFS(Data!$AV$2051:$AV$2550,58)=1,MATCH(58,Data!$AV$2051:$AV$2550,0),0) -> 283 | N70: =IF($M70=0,"",IF(INDEX(Data!$I$2051:$I$2550,$M70)=0,"Add ID","Row "&(INDEX(Data!$I$2051:$I$2550,$M70)+7))) -> Row 185
A71: =IF($M71=0,"",INDEX(Data!$W$2051:$W$2550,$M71)) -> 59 | B71: =IF($M71=0,"",INDEX(Data!$B$2051:$B$2550,$M71)) -> Tanner G. Duckrey School | C71: =IF($M71=0,"",INDEX(Data!$C$2051:$C$2550,$M71)) -> District | D71: =IF($M71=0,"",INDEX(Data!$D$2051:$D$2550,$M71)) -> Elementary-Middle | E71: =IF($M71=0,"",INDEX(Data!$G$2051:$G$2550,$M71)) -> 0.9047 | F71: =IF($M71=0,"",INDEX(Data!$F$2051:$F$2550,$M71)) -> 402 | G71: =IF($M71=0,"",INDEX(Data!$K$2051:$K$2550,$M71)) -> 0.59754365 | H71: =IF($M71=0,"",INDEX(Data!$L$2051:$L$2550,$M71)) -> 14 | I71: =IF($M71=0,"",INDEX(Data!$T$2051:$T$2550,$M71)) -> 48 | J71: =IF($M71=0,"",INDEX(Data!$U$2051:$U$2550,$M71)) -> Listed | K71: =IF($M71=0,"",INDEX(Data!$AA$2051:$AA$2550,$M71)) -> 90% economic need; 0.60 mi fresh access; 14 nearby resources | L71: =IF($M71=0,"",IF(INDEX(Data!$AN$2051:$AN$2550,$M71)=0,"",IF(INDEX(Data!$U$41:$U$540,INDEX(Data!$AN$2051:$AN$2550,$M71))="","",INDEX(Data!$U$41:$U$540,INDEX(Data!$AN$2051:$AN$2550,$M71))))) -> 215-400-7350 | M71: =IF(COUNTIFS(Data!$AV$2051:$AV$2550,59)=1,MATCH(59,Data!$AV$2051:$AV$2550,0),0) -> 172 | N71: =IF($M71=0,"",IF(INDEX(Data!$I$2051:$I$2550,$M71)=0,"Add ID","Row "&(INDEX(Data!$I$2051:$I$2550,$M71)+7))) -> Row 288
A72: =IF($M72=0,"",INDEX(Data!$W$2051:$W$2550,$M72)) -> 60 | B72: =IF($M72=0,"",INDEX(Data!$B$2051:$B$2550,$M72)) -> James R. Lowell School | C72: =IF($M72=0,"",INDEX(Data!$C$2051:$C$2550,$M72)) -> District | D72: =IF($M72=0,"",INDEX(Data!$D$2051:$D$2550,$M72)) -> Elementary | E72: =IF($M72=0,"",INDEX(Data!$G$2051:$G$2550,$M72)) -> 0.8768 | F72: =IF($M72=0,"",INDEX(Data!$F$2051:$F$2550,$M72)) -> 430 | G72: =IF($M72=0,"",INDEX(Data!$K$2051:$K$2550,$M72)) -> 0.54540436 | H72: =IF($M72=0,"",INDEX(Data!$L$2051:$L$2550,$M72)) -> 4 | I72: =IF($M72=0,"",INDEX(Data!$T$2051:$T$2550,$M72)) -> 48 | J72: =IF($M72=0,"",INDEX(Data!$U$2051:$U$2550,$M72)) -> Listed | K72: =IF($M72=0,"",INDEX(Data!$AA$2051:$AA$2550,$M72)) -> 88% economic need; 0.55 mi fresh access; 4 nearby resources | L72: =IF($M72=0,"",IF(INDEX(Data!$AN$2051:$AN$2550,$M72)=0,"",IF(INDEX(Data!$U$41:$U$540,INDEX(Data!$AN$2051:$AN$2550,$M72))="","",INDEX(Data!$U$41:$U$540,INDEX(Data!$AN$2051:$AN$2550,$M72))))) -> 215-400-3740 | M72: =IF(COUNTIFS(Data!$AV$2051:$AV$2550,60)=1,MATCH(60,Data!$AV$2051:$AV$2550,0),0) -> 271 | N72: =IF($M72=0,"",IF(INDEX(Data!$I$2051:$I$2550,$M72)=0,"Add ID","Row "&(INDEX(Data!$I$2051:$I$2550,$M72)+7))) -> Row 136
A73: =IF($M73=0,"",INDEX(Data!$W$2051:$W$2550,$M73)) -> 61 | B73: =IF($M73=0,"",INDEX(Data!$B$2051:$B$2550,$M73)) -> Allen M. Stearne School | C73: =IF($M73=0,"",INDEX(Data!$C$2051:$C$2550,$M73)) -> District | D73: =IF($M73=0,"",INDEX(Data!$D$2051:$D$2550,$M73)) -> Elementary-Middle | E73: =IF($M73=0,"",INDEX(Data!$G$2051:$G$2550,$M73)) -> 0.8664 | F73: =IF($M73=0,"",INDEX(Data!$F$2051:$F$2550,$M73)) -> 370 | G73: =IF($M73=0,"",INDEX(Data!$K$2051:$K$2550,$M73)) -> 0.78220236 | H73: =IF($M73=0,"",INDEX(Data!$L$2051:$L$2550,$M73)) -> 7 | I73: =IF($M73=0,"",INDEX(Data!$T$2051:$T$2550,$M73)) -> 48 | J73: =IF($M73=0,"",INDEX(Data!$U$2051:$U$2550,$M73)) -> Listed | K73: =IF($M73=0,"",INDEX(Data!$AA$2051:$AA$2550,$M73)) -> 87% economic need; 0.78 mi fresh access; 7 nearby resources | L73: =IF($M73=0,"",IF(INDEX(Data!$AN$2051:$AN$2550,$M73)=0,"",IF(INDEX(Data!$U$41:$U$540,INDEX(Data!$AN$2051:$AN$2550,$M73))="","",INDEX(Data!$U$41:$U$540,INDEX(Data!$AN$2051:$AN$2550,$M73))))) -> 215-400-3980 | M73: =IF(COUNTIFS(Data!$AV$2051:$AV$2550,61)=1,MATCH(61,Data!$AV$2051:$AV$2550,0),0) -> 266 | N73: =IF($M73=0,"",IF(INDEX(Data!$I$2051:$I$2550,$M73)=0,"Add ID","Row "&(INDEX(Data!$I$2051:$I$2550,$M73)+7))) -> Row 21
A74: =IF($M74=0,"",INDEX(Data!$W$2051:$W$2550,$M74)) -> 62 | B74: =IF($M74=0,"",INDEX(Data!$B$2051:$B$2550,$M74)) -> John S. Jenks Academy for the Arts and Sciences | C74: =IF($M74=0,"",INDEX(Data!$C$2051:$C$2550,$M74)) -> District | D74: =IF($M74=0,"",INDEX(Data!$D$2051:$D$2550,$M74)) -> Elementary-Middle | E74: =IF($M74=0,"",INDEX(Data!$G$2051:$G$2550,$M74)) -> 0.6078 | F74: =IF($M74=0,"",INDEX(Data!$F$2051:$F$2550,$M74)) -> 380 | G74: =IF($M74=0,"",INDEX(Data!$K$2051:$K$2550,$M74)) -> 0.072008836 | H74: =IF($M74=0,"",INDEX(Data!$L$2051:$L$2550,$M74)) -> 0 | I74: =IF($M74=0,"",INDEX(Data!$T$2051:$T$2550,$M74)) -> 48 | J74: =IF($M74=0,"",INDEX(Data!$U$2051:$U$2550,$M74)) -> Listed | K74: =IF($M74=0,"",INDEX(Data!$AA$2051:$AA$2550,$M74)) -> 61% economic need; 0.07 mi fresh access; 0 nearby resources | L74: =IF($M74=0,"",IF(INDEX(Data!$AN$2051:$AN$2550,$M74)=0,"",IF(INDEX(Data!$U$41:$U$540,INDEX(Data!$AN$2051:$AN$2550,$M74))="","",INDEX(Data!$U$41:$U$540,INDEX(Data!$AN$2051:$AN$2550,$M74))))) -> 215-400-3360 | M74: =IF(COUNTIFS(Data!$AV$2051:$AV$2550,62)=1,MATCH(62,Data!$AV$2051:$AV$2550,0),0) -> 235 | N74: =IF($M74=0,"",IF(INDEX(Data!$I$2051:$I$2550,$M74)=0,"Add ID","Row "&(INDEX(Data!$I$2051:$I$2550,$M74)+7))) -> Row 151
A75: =IF($M75=0,"",INDEX(Data!$W$2051:$W$2550,$M75)) -> 63 | B75: =IF($M75=0,"",INDEX(Data!$B$2051:$B$2550,$M75)) -> Thomas Mifflin School | C75: =IF($M75=0,"",INDEX(Data!$C$2051:$C$2550,$M75)) -> District | D75: =IF($M75=0,"",INDEX(Data!$D$2051:$D$2550,$M75)) -> Elementary-Middle | E75: =IF($M75=0,"",INDEX(Data!$G$2051:$G$2550,$M75)) -> 0.6037 | F75: =IF($M75=0,"",INDEX(Data!$F$2051:$F$2550,$M75)) -> 396 | G75: =IF($M75=0,"",INDEX(Data!$K$2051:$K$2550,$M75)) -> 0.87254924 | H75: =IF($M75=0,"",INDEX(Data!$L$2051:$L$2550,$M75)) -> 3 | I75: =IF($M75=0,"",INDEX(Data!$T$2051:$T$2550,$M75)) -> 48 | J75: =IF($M75=0,"",INDEX(Data!$U$2051:$U$2550,$M75)) -> Listed | K75: =IF($M75=0,"",INDEX(Data!$AA$2051:$AA$2550,$M75)) -> 60% economic need; 0.87 mi fresh access; 3 nearby resources | L75: =IF($M75=0,"",IF(INDEX(Data!$AN$2051:$AN$2550,$M75)=0,"",IF(INDEX(Data!$U$41:$U$540,INDEX(Data!$AN$2051:$AN$2550,$M75))="","",INDEX(Data!$U$41:$U$540,INDEX(Data!$AN$2051:$AN$2550,$M75))))) -> 215-400-3830 | M75: =IF(COUNTIFS(Data!$AV$2051:$AV$2550,63)=1,MATCH(63,Data!$AV$2051:$AV$2550,0),0) -> 238 | N75: =IF($M75=0,"",IF(INDEX(Data!$I$2051:$I$2550,$M75)=0,"Add ID","Row "&(INDEX(Data!$I$2051:$I$2550,$M75)+7))) -> Row 304
A76: =IF($M76=0,"",INDEX(Data!$W$2051:$W$2550,$M76)) -> 64 | B76: =IF($M76=0,"",INDEX(Data!$B$2051:$B$2550,$M76)) -> Morton McMichael School | C76: =IF($M76=0,"",INDEX(Data!$C$2051:$C$2550,$M76)) -> District | D76: =IF($M76=0,"",INDEX(Data!$D$2051:$D$2550,$M76)) -> Elementary-Middle | E76: =IF($M76=0,"",INDEX(Data!$G$2051:$G$2550,$M76)) -> 0.9264 | F76: =IF($M76=0,"",INDEX(Data!$F$2051:$F$2550,$M76)) -> 286 | G76: =IF($M76=0,"",INDEX(Data!$K$2051:$K$2550,$M76)) -> 0.71397994 | H76: =IF($M76=0,"",INDEX(Data!$L$2051:$L$2550,$M76)) -> 11 | I76: =IF($M76=0,"",INDEX(Data!$T$2051:$T$2550,$M76)) -> 47 | J76: =IF($M76=0,"",INDEX(Data!$U$2051:$U$2550,$M76)) -> Listed | K76: =IF($M76=0,"",INDEX(Data!$AA$2051:$AA$2550,$M76)) -> 93% economic need; 0.71 mi fresh access; 11 nearby resources | L76: =IF($M76=0,"",IF(INDEX(Data!$AN$2051:$AN$2550,$M76)=0,"",IF(INDEX(Data!$U$41:$U$540,INDEX(Data!$AN$2051:$AN$2550,$M76))="","",INDEX(Data!$U$41:$U$540,INDEX(Data!$AN$2051:$AN$2550,$M76))))) -> 215-400-7750 | M76: =IF(COUNTIFS(Data!$AV$2051:$AV$2550,64)=1,MATCH(64,Data!$AV$2051:$AV$2550,0),0) -> 17 | N76: =IF($M76=0,"",IF(INDEX(Data!$I$2051:$I$2550,$M76)=0,"Add ID","Row "&(INDEX(Data!$I$2051:$I$2550,$M76)+7))) -> Row 207
A77: =IF($M77=0,"",INDEX(Data!$W$2051:$W$2550,$M77)) -> 65 | B77: =IF($M77=0,"",INDEX(Data!$B$2051:$B$2550,$M77)) -> William D. Kelley School | C77: =IF($M77=0,"",INDEX(Data!$C$2051:$C$2550,$M77)) -> District | D77: =IF($M77=0,"",INDEX(Data!$D$2051:$D$2550,$M77)) -> Elementary-Middle | E77: =IF($M77=0,"",INDEX(Data!$G$2051:$G$2550,$M77)) -> 0.9115 | F77: =IF($M77=0,"",INDEX(Data!$F$2051:$F$2550,$M77)) -> 205 | G77: =IF($M77=0,"",INDEX(Data!$K$2051:$K$2550,$M77)) -> 0.5182432 | H77: =IF($M77=0,"",INDEX(Data!$L$2051:$L$2550,$M77)) -> 11 | I77: =IF($M77=0,"",INDEX(Data!$T$2051:$T$2550,$M77)) -> 47 | J77: =IF($M77=0,"",INDEX(Data!$U$2051:$U$2550,$M77)) -> Listed | K77: =IF($M77=0,"",INDEX(Data!$AA$2051:$AA$2550,$M77)) -> 91% economic need; 0.52 mi fresh access; 11 nearby resources | L77: =IF($M77=0,"",IF(INDEX(Data!$AN$2051:$AN$2550,$M77)=0,"",IF(INDEX(Data!$U$41:$U$540,INDEX(Data!$AN$2051:$AN$2550,$M77))="","",INDEX(Data!$U$41:$U$540,INDEX(Data!$AN$2051:$AN$2550,$M77))))) -> 215-400-7370 | M77: =IF(COUNTIFS(Data!$AV$2051:$AV$2550,65)=1,MATCH(65,Data!$AV$2051:$AV$2550,0),0) -> 177 | N77: =IF($M77=0,"",IF(INDEX(Data!$I$2051:$I$2550,$M77)=0,"Add ID","Row "&(INDEX(Data!$I$2051:$I$2550,$M77)+7))) -> Row 322
A78: =IF($M78=0,"",INDEX(Data!$W$2051:$W$2550,$M78)) -> 66 | B78: =IF($M78=0,"",INDEX(Data!$B$2051:$B$2550,$M78)) -> Dr. Ethel Allen School | C78: =IF($M78=0,"",INDEX(Data!$C$2051:$C$2550,$M78)) -> District | D78: =IF($M78=0,"",INDEX(Data!$D$2051:$D$2550,$M78)) -> Elementary-Middle | E78: =IF($M78=0,"",INDEX(Data!$G$2051:$G$2550,$M78)) -> 0.9062 | F78: =IF($M78=0,"",INDEX(Data!$F$2051:$F$2550,$M78)) -> 274 | G78: =IF($M78=0,"",INDEX(Data!$K$2051:$K$2550,$M78)) -> 0.55178442 | H78: =IF($M78=0,"",INDEX(Data!$L$2051:$L$2550,$M78)) -> 10 | I78: =IF($M78=0,"",INDEX(Data!$T$2051:$T$2550,$M78)) -> 47 | J78: =IF($M78=0,"",INDEX(Data!$U$2051:$U$2550,$M78)) -> Listed | K78: =IF($M78=0,"",INDEX(Data!$AA$2051:$AA$2550,$M78)) -> 91% economic need; 0.55 mi fresh access; 10 nearby resources | L78: =IF($M78=0,"",IF(INDEX(Data!$AN$2051:$AN$2550,$M78)=0,"",IF(INDEX(Data!$U$41:$U$540,INDEX(Data!$AN$2051:$AN$2550,$M78))="","",INDEX(Data!$U$41:$U$540,INDEX(Data!$AN$2051:$AN$2550,$M78))))) -> 215-400-7040 | M78: =IF(COUNTIFS(Data!$AV$2051:$AV$2550,66)=1,MATCH(66,Data!$AV$2051:$AV$2550,0),0) -> 171 | N78: =IF($M78=0,"",IF(INDEX(Data!$I$2051:$I$2550,$M78)=0,"Add ID","Row "&(INDEX(Data!$I$2051:$I$2550,$M78)+7))) -> Row 59
A79: =IF($M79=0,"",INDEX(Data!$W$2051:$W$2550,$M79)) -> 67 | B79: =IF($M79=0,"",INDEX(Data!$B$2051:$B$2550,$M79)) -> William C. Bryant School | C79: =IF($M79=0,"",INDEX(Data!$C$2051:$C$2550,$M79)) -> District | D79: =IF($M79=0,"",INDEX(Data!$D$2051:$D$2550,$M79)) -> Elementary-Middle | E79: =IF($M79=0,"",INDEX(Data!$G$2051:$G$2550,$M79)) -> 0.9023 | F79: =IF($M79=0,"",INDEX(Data!$F$2051:$F$2550,$M79)) -> 332 | G79: =IF($M79=0,"",INDEX(Data!$K$2051:$K$2550,$M79)) -> 0.55923747 | H79: =IF($M79=0,"",INDEX(Data!$L$2051:$L$2550,$M79)) -> 5 | I79: =IF($M79=0,"",INDEX(Data!$T$2051:$T$2550,$M79)) -> 47 | J79: =IF($M79=0,"",INDEX(Data!$U$2051:$U$2550,$M79)) -> Listed | K79: =IF($M79=0,"",INDEX(Data!$AA$2051:$AA$2550,$M79)) -> 90% economic need; 0.56 mi fresh access; 5 nearby resources | L79: =IF($M79=0,"",IF(INDEX(Data!$AN$2051:$AN$2550,$M79)=0,"",IF(INDEX(Data!$U$41:$U$540,INDEX(Data!$AN$2051:$AN$2550,$M79))="","",INDEX(Data!$U$41:$U$540,INDEX(Data!$AN$2051:$AN$2550,$M79))))) -> 215-400-7910 | M79: =IF(COUNTIFS(Data!$AV$2051:$AV$2550,67)=1,MATCH(67,Data!$AV$2051:$AV$2550,0),0) -> 9 | N79: =IF($M79=0,"",IF(INDEX(Data!$I$2051:$I$2550,$M79)=0,"Add ID","Row "&(INDEX(Data!$I$2051:$I$2550,$M79)+7))) -> Row 319
A80: =IF($M80=0,"",INDEX(Data!$W$2051:$W$2550,$M80)) -> 68 | B80: =IF($M80=0,"",INDEX(Data!$B$2051:$B$2550,$M80)) -> James Logan School | C80: =IF($M80=0,"",INDEX(Data!$C$2051:$C$2550,$M80)) -> District | D80: =IF($M80=0,"",INDEX(Data!$D$2051:$D$2550,$M80)) -> Elementary | E80: =IF($M80=0,"",INDEX(Data!$G$2051:$G$2550,$M80)) -> 0.9023 | F80: =IF($M80=0,"",INDEX(Data!$F$2051:$F$2550,$M80)) -> 223 | G80: =IF($M80=0,"",INDEX(Data!$K$2051:$K$2550,$M80)) -> 0.69701528 | H80: =IF($M80=0,"",INDEX(Data!$L$2051:$L$2550,$M80)) -> 8 | I80: =IF($M80=0,"",INDEX(Data!$T$2051:$T$2550,$M80)) -> 47 | J80: =IF($M80=0,"",INDEX(Data!$U$2051:$U$2550,$M80)) -> Listed | K80: =IF($M80=0,"",INDEX(Data!$AA$2051:$AA$2550,$M80)) -> 90% economic need; 0.70 mi fresh access; 8 nearby resources | L80: =IF($M80=0,"",IF(INDEX(Data!$AN$2051:$AN$2550,$M80)=0,"",IF(INDEX(Data!$U$41:$U$540,INDEX(Data!$AN$2051:$AN$2550,$M80))="","",INDEX(Data!$U$41:$U$540,INDEX(Data!$AN$2051:$AN$2550,$M80))))) -> 215-400-3670 | M80: =IF(COUNTIFS(Data!$AV$2051:$AV$2550,68)=1,MATCH(68,Data!$AV$2051:$AV$2550,0),0) -> 236 | N80: =IF($M80=0,"",IF(INDEX(Data!$I$2051:$I$2550,$M80)=0,"Add ID","Row "&(INDEX(Data!$I$2051:$I$2550,$M80)+7))) -> Row 135
A81: =IF($M81=0,"",INDEX(Data!$W$2051:$W$2550,$M81)) -> 69 | B81: =IF($M81=0,"",INDEX(Data!$B$2051:$B$2550,$M81)) -> Benjamin B. Comegys School | C81: =IF($M81=0,"",INDEX(Data!$C$2051:$C$2550,$M81)) -> District | D81: =IF($M81=0,"",INDEX(Data!$D$2051:$D$2550,$M81)) -> Elementary-Middle | E81: =IF($M81=0,"",INDEX(Data!$G$2051:$G$2550,$M81)) -> 0.9014 | F81: =IF($M81=0,"",INDEX(Data!$F$2051:$F$2550,$M81)) -> 213 | G81: =IF($M81=0,"",INDEX(Data!$K$2051:$K$2550,$M81)) -> 0.56455784 | H81: =IF($M81=0,"",INDEX(Data!$L$2051:$L$2550,$M81)) -> 7 | I81: =IF($M81=0,"",INDEX(Data!$T$2051:$T$2550,$M81)) -> 47 | J81: =IF($M81=0,"",INDEX(Data!$U$2051:$U$2550,$M81)) -> Listed | K81: =IF($M81=0,"",INDEX(Data!$AA$2051:$AA$2550,$M81)) -> 90% economic need; 0.56 mi fresh access; 7 nearby resources | L81: =IF($M81=0,"",IF(INDEX(Data!$AN$2051:$AN$2550,$M81)=0,"",IF(INDEX(Data!$U$41:$U$540,INDEX(Data!$AN$2051:$AN$2550,$M81))="","",INDEX(Data!$U$41:$U$540,INDEX(Data!$AN$2051:$AN$2550,$M81))))) -> 215-400-7860 | M81: =IF(COUNTIFS(Data!$AV$2051:$AV$2550,69)=1,MATCH(69,Data!$AV$2051:$AV$2550,0),0) -> 11 | N81: =IF($M81=0,"",IF(INDEX(Data!$I$2051:$I$2550,$M81)=0,"Add ID","Row "&(INDEX(Data!$I$2051:$I$2550,$M81)+7))) -> Row 37
A82: =IF($M82=0,"",INDEX(Data!$W$2051:$W$2550,$M82)) -> 70 | B82: =IF($M82=0,"",INDEX(Data!$B$2051:$B$2550,$M82)) -> James Dobson School | C82: =IF($M82=0,"",INDEX(Data!$C$2051:$C$2550,$M82)) -> District | D82: =IF($M82=0,"",INDEX(Data!$D$2051:$D$2550,$M82)) -> Elementary-Middle | E82: =IF($M82=0,"",INDEX(Data!$G$2051:$G$2550,$M82)) -> 0.4901 | F82: =IF($M82=0,"",INDEX(Data!$F$2051:$F$2550,$M82)) -> 253 | G82: =IF($M82=0,"",INDEX(Data!$K$2051:$K$2550,$M82)) -> 0.83432831 | H82: =IF($M82=0,"",INDEX(Data!$L$2051:$L$2550,$M82)) -> 1 | I82: =IF($M82=0,"",INDEX(Data!$T$2051:$T$2550,$M82)) -> 47 | J82: =IF($M82=0,"",INDEX(Data!$U$2051:$U$2550,$M82)) -> Listed | K82: =IF($M82=0,"",INDEX(Data!$AA$2051:$AA$2550,$M82)) -> 49% economic need; 0.83 mi fresh access; 1 nearby resources | L82: =IF($M82=0,"",IF(INDEX(Data!$AN$2051:$AN$2550,$M82)=0,"",IF(INDEX(Data!$U$41:$U$540,INDEX(Data!$AN$2051:$AN$2550,$M82))="","",INDEX(Data!$U$41:$U$540,INDEX(Data!$AN$2051:$AN$2550,$M82))))) -> 215-400-3570 | M82: =IF(COUNTIFS(Data!$AV$2051:$AV$2550,70)=1,MATCH(70,Data!$AV$2051:$AV$2550,0),0) -> 247 | N82: =IF($M82=0,"",IF(INDEX(Data!$I$2051:$I$2550,$M82)=0,"Add ID","Row "&(INDEX(Data!$I$2051:$I$2550,$M82)+7))) -> Row 132
A83: =IF($M83=0,"",INDEX(Data!$W$2051:$W$2550,$M83)) -> 71 | B83: =IF($M83=0,"",INDEX(Data!$B$2051:$B$2550,$M83)) -> Philadelphia Learning Academy North | C83: =IF($M83=0,"",INDEX(Data!$C$2051:$C$2550,$M83)) -> District | D83: =IF($M83=0,"",INDEX(Data!$D$2051:$D$2550,$M83)) -> Transition/Overage School | E83: =IF($M83=0,"",INDEX(Data!$G$2051:$G$2550,$M83)) -> 0.9016 | F83: =IF($M83=0,"",INDEX(Data!$F$2051:$F$2550,$M83)) -> 67 | G83: =IF($M83=0,"",INDEX(Data!$K$2051:$K$2550,$M83)) -> 0.51816367 | H83: =IF($M83=0,"",INDEX(Data!$L$2051:$L$2550,$M83)) -> 10 | I83: =IF($M83=0,"",INDEX(Data!$T$2051:$T$2550,$M83)) -> 46 | J83: =IF($M83=0,"",INDEX(Data!$U$2051:$U$2550,$M83)) -> Listed | K83: =IF($M83=0,"",INDEX(Data!$AA$2051:$AA$2550,$M83)) -> 90% economic need; 0.52 mi fresh access; 10 nearby resources | L83: =IF($M83=0,"",IF(INDEX(Data!$AN$2051:$AN$2550,$M83)=0,"",IF(INDEX(Data!$U$41:$U$540,INDEX(Data!$AN$2051:$AN$2550,$M83))="","",INDEX(Data!$U$41:$U$540,INDEX(Data!$AN$2051:$AN$2550,$M83))))) -> 215-400-9050 | M83: =IF(COUNTIFS(Data!$AV$2051:$AV$2550,71)=1,MATCH(71,Data!$AV$2051:$AV$2550,0),0) -> 320 | N83: =IF($M83=0,"",IF(INDEX(Data!$I$2051:$I$2550,$M83)=0,"Add ID","Row "&(INDEX(Data!$I$2051:$I$2550,$M83)+7))) -> Row 244
A84: =IF($M84=0,"",INDEX(Data!$W$2051:$W$2550,$M84)) -> 72 | B84: =IF($M84=0,"",INDEX(Data!$B$2051:$B$2550,$M84)) -> Fitler Academics Plus School | C84: =IF($M84=0,"",INDEX(Data!$C$2051:$C$2550,$M84)) -> District | D84: =IF($M84=0,"",INDEX(Data!$D$2051:$D$2550,$M84)) -> Elementary-Middle | E84: =IF($M84=0,"",INDEX(Data!$G$2051:$G$2550,$M84)) -> 0.8474 | F84: =IF($M84=0,"",INDEX(Data!$F$2051:$F$2550,$M84)) -> 177 | G84: =IF($M84=0,"",INDEX(Data!$K$2051:$K$2550,$M84)) -> 0.76489358 | H84: =IF($M84=0,"",INDEX(Data!$L$2051:$L$2550,$M84)) -> 14 | I84: =IF($M84=0,"",INDEX(Data!$T$2051:$T$2550,$M84)) -> 46 | J84: =IF($M84=0,"",INDEX(Data!$U$2051:$U$2550,$M84)) -> Listed | K84: =IF($M84=0,"",INDEX(Data!$AA$2051:$AA$2550,$M84)) -> 85% economic need; 0.76 mi fresh access; 14 nearby resources | L84: =IF($M84=0,"",IF(INDEX(Data!$AN$2051:$AN$2550,$M84)=0,"",IF(INDEX(Data!$U$41:$U$540,INDEX(Data!$AN$2051:$AN$2550,$M84))="","",INDEX(Data!$U$41:$U$540,INDEX(Data!$AN$2051:$AN$2550,$M84))))) -> 215-400-3610 | M84: =IF(COUNTIFS(Data!$AV$2051:$AV$2550,72)=1,MATCH(72,Data!$AV$2051:$AV$2550,0),0) -> 232 | N84: =IF($M84=0,"",IF(INDEX(Data!$I$2051:$I$2550,$M84)=0,"Add ID","Row "&(INDEX(Data!$I$2051:$I$2550,$M84)+7))) -> Row 83
A85: =IF($M85=0,"",INDEX(Data!$W$2051:$W$2550,$M85)) -> 73 | B85: =IF($M85=0,"",INDEX(Data!$B$2051:$B$2550,$M85)) -> Academy for the Middle Years at Northwest | C85: =IF($M85=0,"",INDEX(Data!$C$2051:$C$2550,$M85)) -> District | D85: =IF($M85=0,"",INDEX(Data!$D$2051:$D$2550,$M85)) -> Middle | E85: =IF($M85=0,"",INDEX(Data!$G$2051:$G$2550,$M85)) -> 0.772 | F85: =IF($M85=0,"",INDEX(Data!$F$2051:$F$2550,$M85)) -> 136 | G85: =IF($M85=0,"",INDEX(Data!$K$2051:$K$2550,$M85)) -> 0.07651678 | H85: =IF($M85=0,"",INDEX(Data!$L$2051:$L$2550,$M85)) -> 1 | I85: =IF($M85=0,"",INDEX(Data!$T$2051:$T$2550,$M85)) -> 46 | J85: =IF($M85=0,"",INDEX(Data!$U$2051:$U$2550,$M85)) -> Listed | K85: =IF($M85=0,"",INDEX(Data!$AA$2051:$AA$2550,$M85)) -> 77% economic need; 0.08 mi fresh access; 1 nearby resources | L85: =IF($M85=0,"",IF(INDEX(Data!$AN$2051:$AN$2550,$M85)=0,"",IF(INDEX(Data!$U$41:$U$540,INDEX(Data!$AN$2051:$AN$2550,$M85))="","",INDEX(Data!$U$41:$U$540,INDEX(Data!$AN$2051:$AN$2550,$M85))))) -> 215-400-3460 | M85: =IF(COUNTIFS(Data!$AV$2051:$AV$2550,73)=1,MATCH(73,Data!$AV$2051:$AV$2550,0),0) -> 250 | N85: =IF($M85=0,"",IF(INDEX(Data!$I$2051:$I$2550,$M85)=0,"Add ID","Row "&(INDEX(Data!$I$2051:$I$2550,$M85)+7))) -> Row 12
A86: =IF($M86=0,"",INDEX(Data!$W$2051:$W$2550,$M86)) -> 74 | B86: =IF($M86=0,"",INDEX(Data!$B$2051:$B$2550,$M86)) -> Mastery Charter School at Gratz | C86: =IF($M86=0,"",INDEX(Data!$C$2051:$C$2550,$M86)) -> Charter | D86: =IF($M86=0,"",INDEX(Data!$D$2051:$D$2550,$M86)) -> Middle-High | E86: =IF($M86=0,"",INDEX(Data!$G$2051:$G$2550,$M86)) -> 0.8847 | F86: =IF($M86=0,"",INDEX(Data!$F$2051:$F$2550,$M86)) -> 1097 | G86: =IF($M86=0,"",INDEX(Data!$K$2051:$K$2550,$M86)) -> 0.61868296 | H86: =IF($M86=0,"",INDEX(Data!$L$2051:$L$2550,$M86)) -> 8 | I86: =IF($M86=0,"",INDEX(Data!$T$2051:$T$2550,$M86)) -> 45 | J86: =IF($M86=0,"",INDEX(Data!$U$2051:$U$2550,$M86)) -> Listed | K86: =IF($M86=0,"",INDEX(Data!$AA$2051:$AA$2550,$M86)) -> 88% economic need; 0.62 mi fresh access; 8 nearby resources | L86: =IF($M86=0,"",IF(INDEX(Data!$AN$2051:$AN$2550,$M86)=0,"",IF(INDEX(Data!$U$41:$U$540,INDEX(Data!$AN$2051:$AN$2550,$M86))="","",INDEX(Data!$U$41:$U$540,INDEX(Data!$AN$2051:$AN$2550,$M86))))) | M86: =IF(COUNTIFS(Data!$AV$2051:$AV$2550,74)=1,MATCH(74,Data!$AV$2051:$AV$2550,0),0) -> 132 | N86: =IF($M86=0,"",IF(INDEX(Data!$I$2051:$I$2550,$M86)=0,"Add ID","Row "&(INDEX(Data!$I$2051:$I$2550,$M86)+7))) -> Row 192
A87: =IF($M87=0,"",INDEX(Data!$W$2051:$W$2550,$M87)) -> 75 | B87: =IF($M87=0,"",INDEX(Data!$B$2051:$B$2550,$M87)) -> The Philadelphia Charter School for Arts and Sciences | C87: =IF($M87=0,"",INDEX(Data!$C$2051:$C$2550,$M87)) -> Charter | D87: =IF($M87=0,"",INDEX(Data!$D$2051:$D$2550,$M87)) -> Elementary-Middle | E87: =IF($M87=0,"",INDEX(Data!$G$2051:$G$2550,$M87)) -> 0.8432 | F87: =IF($M87=0,"",INDEX(Data!$F$2051:$F$2550,$M87)) -> 837 | G87: =IF($M87=0,"",INDEX(Data!$K$2051:$K$2550,$M87)) -> 0.53094574 | H87: =IF($M87=0,"",INDEX(Data!$L$2051:$L$2550,$M87)) -> 7 | I87: =IF($M87=0,"",INDEX(Data!$T$2051:$T$2550,$M87)) -> 45 | J87: =IF($M87=0,"",INDEX(Data!$U$2051:$U$2550,$M87)) -> Listed | K87: =IF($M87=0,"",INDEX(Data!$AA$2051:$AA$2550,$M87)) -> 84% economic need; 0.53 mi fresh access; 7 nearby resources | L87: =IF($M87=0,"",IF(INDEX(Data!$AN$2051:$AN$2550,$M87)=0,"",IF(INDEX(Data!$U$41:$U$540,INDEX(Data!$AN$2051:$AN$2550,$M87))="","",INDEX(Data!$U$41:$U$540,INDEX(Data!$AN$2051:$AN$2550,$M87))))) -> 215-537-2520 | M87: =IF(COUNTIFS(Data!$AV$2051:$AV$2550,75)=1,MATCH(75,Data!$AV$2051:$AV$2550,0),0) -> 137 | N87: =IF($M87=0,"",IF(INDEX(Data!$I$2051:$I$2550,$M87)=0,"Add ID","Row "&(INDEX(Data!$I$2051:$I$2550,$M87)+7))) -> Row 294
A88: =IF($M88=0,"",INDEX(Data!$W$2051:$W$2550,$M88)) -> 76 | B88: =IF($M88=0,"",INDEX(Data!$B$2051:$B$2550,$M88)) -> First Philadelphia Preparatory Charter School | C88: =IF($M88=0,"",INDEX(Data!$C$2051:$C$2550,$M88)) -> Charter | D88: =IF($M88=0,"",INDEX(Data!$D$2051:$D$2550,$M88)) -> Elementary-Middle-High | E88: =IF($M88=0,"",INDEX(Data!$G$2051:$G$2550,$M88)) -> 0.7978 | F88: =IF($M88=0,"",INDEX(Data!$F$2051:$F$2550,$M88)) -> 1880 | G88: =IF($M88=0,"",INDEX(Data!$K$2051:$K$2550,$M88)) -> 0.75178174 | H88: =IF($M88=0,"",INDEX(Data!$L$2051:$L$2550,$M88)) -> 7 | I88: =IF($M88=0,"",INDEX(Data!$T$2051:$T$2550,$M88)) -> 45 | J88: =IF($M88=0,"",INDEX(Data!$U$2051:$U$2550,$M88)) -> Listed | K88: =IF($M88=0,"",INDEX(Data!$AA$2051:$AA$2550,$M88)) -> 80% economic need; 0.75 mi fresh access; 7 nearby resources | L88: =IF($M88=0,"",IF(INDEX(Data!$AN$2051:$AN$2550,$M88)=0,"",IF(INDEX(Data!$U$41:$U$540,INDEX(Data!$AN$2051:$AN$2550,$M88))="","",INDEX(Data!$U$41:$U$540,INDEX(Data!$AN$2051:$AN$2550,$M88))))) -> 215-743-3100 | M88: =IF(COUNTIFS(Data!$AV$2051:$AV$2550,76)=1,MATCH(76,Data!$AV$2051:$AV$2550,0),0) -> 106 | N88: =IF($M88=0,"",IF(INDEX(Data!$I$2051:$I$2550,$M88)=0,"Add ID","Row "&(INDEX(Data!$I$2051:$I$2550,$M88)+7))) -> Row 82
A89: =IF($M89=0,"",INDEX(Data!$W$2051:$W$2550,$M89)) -> 77 | B89: =IF($M89=0,"",INDEX(Data!$B$2051:$B$2550,$M89)) -> Solomon Solis-Cohen School | C89: =IF($M89=0,"",INDEX(Data!$C$2051:$C$2550,$M89)) -> District | D89: =IF($M89=0,"",INDEX(Data!$D$2051:$D$2550,$M89)) -> Elementary | E89: =IF($M89=0,"",INDEX(Data!$G$2051:$G$2550,$M89)) -> 0.7902 | F89: =IF($M89=0,"",INDEX(Data!$F$2051:$F$2550,$M89)) -> 1354 | G89: =IF($M89=0,"",INDEX(Data!$K$2051:$K$2550,$M89)) -> 0.36391859 | H89: =IF($M89=0,"",INDEX(Data!$L$2051:$L$2550,$M89)) -> 3 | I89: =IF($M89=0,"",INDEX(Data!$T$2051:$T$2550,$M89)) -> 45 | J89: =IF($M89=0,"",INDEX(Data!$U$2051:$U$2550,$M89)) -> Listed | K89: =IF($M89=0,"",INDEX(Data!$AA$2051:$AA$2550,$M89)) -> 79% economic need; 0.36 mi fresh access; 3 nearby resources | L89: =IF($M89=0,"",IF(INDEX(Data!$AN$2051:$AN$2550,$M89)=0,"",IF(INDEX(Data!$U$41:$U$540,INDEX(Data!$AN$2051:$AN$2550,$M89))="","",INDEX(Data!$U$41:$U$540,INDEX(Data!$AN$2051:$AN$2550,$M89))))) -> 215-400-3250 | M89: =IF(COUNTIFS(Data!$AV$2051:$AV$2550,77)=1,MATCH(77,Data!$AV$2051:$AV$2550,0),0) -> 307 | N89: =IF($M89=0,"",IF(INDEX(Data!$I$2051:$I$2550,$M89)=0,"Add ID","Row "&(INDEX(Data!$I$2051:$I$2550,$M89)+7))) -> Row 276
A90: =IF($M90=0,"",INDEX(Data!$W$2051:$W$2550,$M90)) -> 78 | B90: =IF($M90=0,"",INDEX(Data!$B$2051:$B$2550,$M90)) -> Mayfair School | C90: =IF($M90=0,"",INDEX(Data!$C$2051:$C$2550,$M90)) -> District | D90: =IF($M90=0,"",INDEX(Data!$D$2051:$D$2550,$M90)) -> Elementary-Middle | E90: =IF($M90=0,"",INDEX(Data!$G$2051:$G$2550,$M90)) -> 0.7385 | F90: =IF($M90=0,"",INDEX(Data!$F$2051:$F$2550,$M90)) -> 1746 | G90: =IF($M90=0,"",INDEX(Data!$K$2051:$K$2550,$M90)) -> 0.18475066 | H90: =IF($M90=0,"",INDEX(Data!$L$2051:$L$2550,$M90)) -> 2 | I90: =IF($M90=0,"",INDEX(Data!$T$2051:$T$2550,$M90)) -> 45 | J90: =IF($M90=0,"",INDEX(Data!$U$2051:$U$2550,$M90)) -> Listed | K90: =IF($M90=0,"",INDEX(Data!$AA$2051:$AA$2550,$M90)) -> 74% economic need; 0.18 mi fresh access; 2 nearby resources | L90: =IF($M90=0,"",IF(INDEX(Data!$AN$2051:$AN$2550,$M90)=0,"",IF(INDEX(Data!$U$41:$U$540,INDEX(Data!$AN$2051:$AN$2550,$M90))="","",INDEX(Data!$U$41:$U$540,INDEX(Data!$AN$2051:$AN$2550,$M90))))) -> 215-400-3280 | M90: =IF(COUNTIFS(Data!$AV$2051:$AV$2550,78)=1,MATCH(78,Data!$AV$2051:$AV$2550,0),0) -> 305 | N90: =IF($M90=0,"",IF(INDEX(Data!$I$2051:$I$2550,$M90)=0,"Add ID","Row "&(INDEX(Data!$I$2051:$I$2550,$M90)+7))) -> Row 204
A91: =IF($M91=0,"",INDEX(Data!$W$2051:$W$2550,$M91)) -> 79 | B91: =IF($M91=0,"",INDEX(Data!$B$2051:$B$2550,$M91)) -> Anne Frank School | C91: =IF($M91=0,"",INDEX(Data!$C$2051:$C$2550,$M91)) -> District | D91: =IF($M91=0,"",INDEX(Data!$D$2051:$D$2550,$M91)) -> Elementary | E91: =IF($M91=0,"",INDEX(Data!$G$2051:$G$2550,$M91)) -> 0.6848 | F91: =IF($M91=0,"",INDEX(Data!$F$2051:$F$2550,$M91)) -> 1687 | G91: =IF($M91=0,"",INDEX(Data!$K$2051:$K$2550,$M91)) -> 0.3258615 | H91: =IF($M91=0,"",INDEX(Data!$L$2051:$L$2550,$M91)) -> 2 | I91: =IF($M91=0,"",INDEX(Data!$T$2051:$T$2550,$M91)) -> 45 | J91: =IF($M91=0,"",INDEX(Data!$U$2051:$U$2550,$M91)) -> Listed | K91: =IF($M91=0,"",INDEX(Data!$AA$2051:$AA$2550,$M91)) -> 68% economic need; 0.33 mi fresh access; 2 nearby resources | L91: =IF($M91=0,"",IF(INDEX(Data!$AN$2051:$AN$2550,$M91)=0,"",IF(INDEX(Data!$U$41:$U$540,INDEX(Data!$AN$2051:$AN$2550,$M91))="","",INDEX(Data!$U$41:$U$540,INDEX(Data!$AN$2051:$AN$2550,$M91))))) -> 215-400-3070 | M91: =IF(COUNTIFS(Data!$AV$2051:$AV$2550,79)=1,MATCH(79,Data!$AV$2051:$AV$2550,0),0) -> 313 | N91: =IF($M91=0,"",IF(INDEX(Data!$I$2051:$I$2550,$M91)=0,"Add ID","Row "&(INDEX(Data!$I$2051:$I$2550,$M91)+7))) -> Row 29
A92: =IF($M92=0,"",INDEX(Data!$W$2051:$W$2550,$M92)) -> 80 | B92: =IF($M92=0,"",INDEX(Data!$B$2051:$B$2550,$M92)) -> Mathematics, Science, and Technology Community Charter School (MaST) | C92: =IF($M92=0,"",INDEX(Data!$C$2051:$C$2550,$M92)) -> Charter | D92: =IF($M92=0,"",INDEX(Data!$D$2051:$D$2550,$M92)) -> Elementary-Middle-High | E92: =IF($M92=0,"",INDEX(Data!$G$2051:$G$2550,$M92)) -> 0.4112 | F92: =IF($M92=0,"",INDEX(Data!$F$2051:$F$2550,$M92)) -> 1486 | G92: =IF($M92=0,"",INDEX(Data!$K$2051:$K$2550,$M92)) -> 0.51504148 | H92: =IF($M92=0,"",INDEX(Data!$L$2051:$L$2550,$M92)) -> 1 | I92: =IF($M92=0,"",INDEX(Data!$T$2051:$T$2550,$M92)) -> 45 | J92: =IF($M92=0,"",INDEX(Data!$U$2051:$U$2550,$M92)) -> Listed | K92: =IF($M92=0,"",INDEX(Data!$AA$2051:$AA$2550,$M92)) -> 41% economic need; 0.52 mi fresh access; 1 nearby resources | L92: =IF($M92=0,"",IF(INDEX(Data!$AN$2051:$AN$2550,$M92)=0,"",IF(INDEX(Data!$U$41:$U$540,INDEX(Data!$AN$2051:$AN$2550,$M92))="","",INDEX(Data!$U$41:$U$540,INDEX(Data!$AN$2051:$AN$2550,$M92))))) -> 267-348-1100 | M92: =IF(COUNTIFS(Data!$AV$2051:$AV$2550,80)=1,MATCH(80,Data!$AV$2051:$AV$2550,0),0) -> 89 | N92: =IF($M92=0,"",IF(INDEX(Data!$I$2051:$I$2550,$M92)=0,"Add ID","Row "&(INDEX(Data!$I$2051:$I$2550,$M92)+7))) -> Row 203
A93: =IF($M93=0,"",INDEX(Data!$W$2051:$W$2550,$M93)) -> 81 | B93: =IF($M93=0,"",INDEX(Data!$B$2051:$B$2550,$M93)) -> Mastery Charter School at Douglass | C93: =IF($M93=0,"",INDEX(Data!$C$2051:$C$2550,$M93)) -> Charter | D93: =IF($M93=0,"",INDEX(Data!$D$2051:$D$2550,$M93)) -> Elementary-Middle | E93: =IF($M93=0,"",INDEX(Data!$G$2051:$G$2550,$M93)) -> 0.9928 | F93: =IF($M93=0,"",INDEX(Data!$F$2051:$F$2550,$M93)) -> 559 | G93: =IF($M93=0,"",INDEX(Data!$K$2051:$K$2550,$M93)) -> 0.46190673 | H93: =IF($M93=0,"",INDEX(Data!$L$2051:$L$2550,$M93)) -> 19 | I93: =IF($M93=0,"",INDEX(Data!$T$2051:$T$2550,$M93)) -> 44 | J93: =IF($M93=0,"",INDEX(Data!$U$2051:$U$2550,$M93)) -> Listed | K93: =IF($M93=0,"",INDEX(Data!$AA$2051:$AA$2550,$M93)) -> 99% economic need; 0.46 mi fresh access; 19 nearby resources | L93: =IF($M93=0,"",IF(INDEX(Data!$AN$2051:$AN$2550,$M93)=0,"",IF(INDEX(Data!$U$41:$U$540,INDEX(Data!$AN$2051:$AN$2550,$M93))="","",INDEX(Data!$U$41:$U$540,INDEX(Data!$AN$2051:$AN$2550,$M93))))) -> 215-684-5063 | M93: =IF(COUNTIFS(Data!$AV$2051:$AV$2550,81)=1,MATCH(81,Data!$AV$2051:$AV$2550,0),0) -> 130 | N93: =IF($M93=0,"",IF(INDEX(Data!$I$2051:$I$2550,$M93)=0,"Add ID","Row "&(INDEX(Data!$I$2051:$I$2550,$M93)+7))) -> Row 191
A94: =IF($M94=0,"",INDEX(Data!$W$2051:$W$2550,$M94)) -> 82 | B94: =IF($M94=0,"",INDEX(Data!$B$2051:$B$2550,$M94)) -> Universal Charter School at Audenried | C94: =IF($M94=0,"",INDEX(Data!$C$2051:$C$2550,$M94)) -> Charter | D94: =IF($M94=0,"",INDEX(Data!$D$2051:$D$2550,$M94)) -> High | E94: =IF($M94=0,"",INDEX(Data!$G$2051:$G$2550,$M94)) -> 0.9783 | F94: =IF($M94=0,"",INDEX(Data!$F$2051:$F$2550,$M94)) -> 606 | G94: =IF($M94=0,"",INDEX(Data!$K$2051:$K$2550,$M94)) -> 0.45171755 | H94: =IF($M94=0,"",INDEX(Data!$L$2051:$L$2550,$M94)) -> 6 | I94: =IF($M94=0,"",INDEX(Data!$T$2051:$T$2550,$M94)) -> 44 | J94: =IF($M94=0,"",INDEX(Data!$U$2051:$U$2550,$M94)) -> Listed | K94: =IF($M94=0,"",INDEX(Data!$AA$2051:$AA$2550,$M94)) -> 98% economic need; 0.45 mi fresh access; 6 nearby resources | L94: =IF($M94=0,"",IF(INDEX(Data!$AN$2051:$AN$2550,$M94)=0,"",IF(INDEX(Data!$U$41:$U$540,INDEX(Data!$AN$2051:$AN$2550,$M94))="","",INDEX(Data!$U$41:$U$540,INDEX(Data!$AN$2051:$AN$2550,$M94))))) | M94: =IF(COUNTIFS(Data!$AV$2051:$AV$2550,82)=1,MATCH(82,Data!$AV$2051:$AV$2550,0),0) -> 133 | N94: =IF($M94=0,"",IF(INDEX(Data!$I$2051:$I$2550,$M94)=0,"Add ID","Row "&(INDEX(Data!$I$2051:$I$2550,$M94)+7))) -> Row 307
A95: =IF($M95=0,"",INDEX(Data!$W$2051:$W$2550,$M95)) -> 83 | B95: =IF($M95=0,"",INDEX(Data!$B$2051:$B$2550,$M95)) -> Russell Byers Charter School | C95: =IF($M95=0,"",INDEX(Data!$C$2051:$C$2550,$M95)) -> Charter | D95: =IF($M95=0,"",INDEX(Data!$D$2051:$D$2550,$M95)) -> Elementary-Middle | E95: =IF($M95=0,"",INDEX(Data!$G$2051:$G$2550,$M95)) -> 0.9747 | F95: =IF($M95=0,"",INDEX(Data!$F$2051:$F$2550,$M95)) -> 681 | G95: =IF($M95=0,"",INDEX(Data!$K$2051:$K$2550,$M95)) -> 0.2803498 | H95: =IF($M95=0,"",INDEX(Data!$L$2051:$L$2550,$M95)) -> 5 | I95: =IF($M95=0,"",INDEX(Data!$T$2051:$T$2550,$M95)) -> 44 | J95: =IF($M95=0,"",INDEX(Data!$U$2051:$U$2550,$M95)) -> Listed | K95: =IF($M95=0,"",INDEX(Data!$AA$2051:$AA$2550,$M95)) -> 97% economic need; 0.28 mi fresh access; 5 nearby resources | L95: =IF($M95=0,"",IF(INDEX(Data!$AN$2051:$AN$2550,$M95)=0,"",IF(INDEX(Data!$U$41:$U$540,INDEX(Data!$AN$2051:$AN$2550,$M95))="","",INDEX(Data!$U$41:$U$540,INDEX(Data!$AN$2051:$AN$2550,$M95))))) -> 215-972-1700 | M95: =IF(COUNTIFS(Data!$AV$2051:$AV$2550,83)=1,MATCH(83,Data!$AV$2051:$AV$2550,0),0) -> 103 | N95: =IF($M95=0,"",IF(INDEX(Data!$I$2051:$I$2550,$M95)=0,"Add ID","Row "&(INDEX(Data!$I$2051:$I$2550,$M95)+7))) -> Row 264
A96: =IF($M96=0,"",INDEX(Data!$W$2051:$W$2550,$M96)) -> 84 | B96: =IF($M96=0,"",INDEX(Data!$B$2051:$B$2550,$M96)) -> Julia de Burgos School | C96: =IF($M96=0,"",INDEX(Data!$C$2051:$C$2550,$M96)) -> District | D96: =IF($M96=0,"",INDEX(Data!$D$2051:$D$2550,$M96)) -> Elementary-Middle | E96: =IF($M96=0,"",INDEX(Data!$G$2051:$G$2550,$M96)) -> 0.9003 | F96: =IF($M96=0,"",INDEX(Data!$F$2051:$F$2550,$M96)) -> 512 | G96: =IF($M96=0,"",INDEX(Data!$K$2051:$K$2550,$M96)) -> 0.28858848 | H96: =IF($M96=0,"",INDEX(Data!$L$2051:$L$2550,$M96)) -> 14 | I96: =IF($M96=0,"",INDEX(Data!$T$2051:$T$2550,$M96)) -> 44 | J96: =IF($M96=0,"",INDEX(Data!$U$2051:$U$2550,$M96)) -> Listed | K96: =IF($M96=0,"",INDEX(Data!$AA$2051:$AA$2550,$M96)) -> 90% economic need; 0.29 mi fresh access; 14 nearby resources | L96: =IF($M96=0,"",IF(INDEX(Data!$AN$2051:$AN$2550,$M96)=0,"",IF(INDEX(Data!$U$41:$U$540,INDEX(Data!$AN$2051:$AN$2550,$M96))="","",INDEX(Data!$U$41:$U$540,INDEX(Data!$AN$2051:$AN$2550,$M96))))) -> 215-400-7080 | M96: =IF(COUNTIFS(Data!$AV$2051:$AV$2550,84)=1,MATCH(84,Data!$AV$2051:$AV$2550,0),0) -> 187 | N96: =IF($M96=0,"",IF(INDEX(Data!$I$2051:$I$2550,$M96)=0,"Add ID","Row "&(INDEX(Data!$I$2051:$I$2550,$M96)+7))) -> Row 158
A97: =IF($M97=0,"",INDEX(Data!$W$2051:$W$2550,$M97)) -> 85 | B97: =IF($M97=0,"",INDEX(Data!$B$2051:$B$2550,$M97)) -> Mastery Charter School at Mann | C97: =IF($M97=0,"",INDEX(Data!$C$2051:$C$2550,$M97)) -> Charter | D97: =IF($M97=0,"",INDEX(Data!$D$2051:$D$2550,$M97)) -> Elementary | E97: =IF($M97=0,"",INDEX(Data!$G$2051:$G$2550,$M97)) -> 0.8836 | F97: =IF($M97=0,"",INDEX(Data!$F$2051:$F$2550,$M97)) -> 549 | G97: =IF($M97=0,"",INDEX(Data!$K$2051:$K$2550,$M97)) -> 0.59459036 | H97: =IF($M97=0,"",INDEX(Data!$L$2051:$L$2550,$M97)) -> 5 | I97: =IF($M97=0,"",INDEX(Data!$T$2051:$T$2550,$M97)) -> 44 | J97: =IF($M97=0,"",INDEX(Data!$U$2051:$U$2550,$M97)) -> Listed | K97: =IF($M97=0,"",INDEX(Data!$AA$2051:$AA$2550,$M97)) -> 88% economic need; 0.59 mi fresh access; 5 nearby resources | L97: =IF($M97=0,"",IF(INDEX(Data!$AN$2051:$AN$2550,$M97)=0,"",IF(INDEX(Data!$U$41:$U$540,INDEX(Data!$AN$2051:$AN$2550,$M97))="","",INDEX(Data!$U$41:$U$540,INDEX(Data!$AN$2051:$AN$2550,$M97))))) -> 215-581-5516 | M97: =IF(COUNTIFS(Data!$AV$2051:$AV$2550,85)=1,MATCH(85,Data!$AV$2051:$AV$2550,0),0) -> 128 | N97: =IF($M97=0,"",IF(INDEX(Data!$I$2051:$I$2550,$M97)=0,"Add ID","Row "&(INDEX(Data!$I$2051:$I$2550,$M97)+7))) -> Row 195
A98: =IF($M98=0,"",INDEX(Data!$W$2051:$W$2550,$M98)) -> 86 | B98: =IF($M98=0,"",INDEX(Data!$B$2051:$B$2550,$M98)) -> Jules E. Mastbaum Area Vocational Technical High School | C98: =IF($M98=0,"",INDEX(Data!$C$2051:$C$2550,$M98)) -> District | D98: =IF($M98=0,"",INDEX(Data!$D$2051:$D$2550,$M98)) -> High | E98: =IF($M98=0,"",INDEX(Data!$G$2051:$G$2550,$M98)) -> 0.8795 | F98: =IF($M98=0,"",INDEX(Data!$F$2051:$F$2550,$M98)) -> 676 | G98: =IF($M98=0,"",INDEX(Data!$K$2051:$K$2550,$M98)) -> 0.701272 | H98: =IF($M98=0,"",INDEX(Data!$L$2051:$L$2550,$M98)) -> 9 | I98: =IF($M98=0,"",INDEX(Data!$T$2051:$T$2550,$M98)) -> 44 | J98: =IF($M98=0,"",INDEX(Data!$U$2051:$U$2550,$M98)) -> Listed | K98: =IF($M98=0,"",INDEX(Data!$AA$2051:$AA$2550,$M98)) -> 88% economic need; 0.70 mi fresh access; 9 nearby resources | L98: =IF($M98=0,"",IF(INDEX(Data!$AN$2051:$AN$2550,$M98)=0,"",IF(INDEX(Data!$U$41:$U$540,INDEX(Data!$AN$2051:$AN$2550,$M98))="","",INDEX(Data!$U$41:$U$540,INDEX(Data!$AN$2051:$AN$2550,$M98))))) -> 215-400-7220 | M98: =IF(COUNTIFS(Data!$AV$2051:$AV$2550,86)=1,MATCH(86,Data!$AV$2051:$AV$2550,0),0) -> 181 | N98: =IF($M98=0,"",IF(INDEX(Data!$I$2051:$I$2550,$M98)=0,"Add ID","Row "&(INDEX(Data!$I$2051:$I$2550,$M98)+7))) -> Row 157
A99: =IF($M99=0,"",INDEX(Data!$W$2051:$W$2550,$M99)) -> 87 | B99: =IF($M99=0,"",INDEX(Data!$B$2051:$B$2550,$M99)) -> John Bartram High School | C99: =IF($M99=0,"",INDEX(Data!$C$2051:$C$2550,$M99)) -> District | D99: =IF($M99=0,"",INDEX(Data!$D$2051:$D$2550,$M99)) -> High | E99: =IF($M99=0,"",INDEX(Data!$G$2051:$G$2550,$M99)) -> 0.8053 | F99: =IF($M99=0,"",INDEX(Data!$F$2051:$F$2550,$M99)) -> 594 | G99: =IF($M99=0,"",INDEX(Data!$K$2051:$K$2550,$M99)) -> 0.33978194 | H99: =IF($M99=0,"",INDEX(Data!$L$2051:$L$2550,$M99)) -> 4 | I99: =IF($M99=0,"",INDEX(Data!$T$2051:$T$2550,$M99)) -> 44 | J99: =IF($M99=0,"",INDEX(Data!$U$2051:$U$2550,$M99)) -> Listed | K99: =IF($M99=0,"",INDEX(Data!$AA$2051:$AA$2550,$M99)) -> 81% economic need; 0.34 mi fresh access; 4 nearby resources | L99: =IF($M99=0,"",IF(INDEX(Data!$AN$2051:$AN$2550,$M99)=0,"",IF(INDEX(Data!$U$41:$U$540,INDEX(Data!$AN$2051:$AN$2550,$M99))="","",INDEX(Data!$U$41:$U$540,INDEX(Data!$AN$2051:$AN$2550,$M99))))) -> 215-400-8100 | M99: =IF(COUNTIFS(Data!$AV$2051:$AV$2550,87)=1,MATCH(87,Data!$AV$2051:$AV$2550,0),0) -> 1 | N99: =IF($M99=0,"",IF(INDEX(Data!$I$2051:$I$2550,$M99)=0,"Add ID","Row "&(INDEX(Data!$I$2051:$I$2550,$M99)+7))) -> Row 143
A100: =IF($M100=0,"",INDEX(Data!$W$2051:$W$2550,$M100)) -> 88 | B100: =IF($M100=0,"",INDEX(Data!$B$2051:$B$2550,$M100)) -> Philadelphia Hebrew Public Charter School | C100: =IF($M100=0,"",INDEX(Data!$C$2051:$C$2550,$M100)) -> Charter | D100: =IF($M100=0,"",INDEX(Data!$D$2051:$D$2550,$M100)) -> Elementary | E100: =IF($M100=0,"",INDEX(Data!$G$2051:$G$2550,$M100)) -> 0.7869 | F100: =IF($M100=0,"",INDEX(Data!$F$2051:$F$2550,$M100)) -> 614 | G100: =IF($M100=0,"",INDEX(Data!$K$2051:$K$2550,$M100)) -> 0.49400209 | H100: =IF($M100=0,"",INDEX(Data!$L$2051:$L$2550,$M100)) -> 3 | I100: =IF($M100=0,"",INDEX(Data!$T$2051:$T$2550,$M100)) -> 44 | J100: =IF($M100=0,"",INDEX(Data!$U$2051:$U$2550,$M100)) -> Listed | K100: =IF($M100=0,"",INDEX(Data!$AA$2051:$AA$2550,$M100)) -> 79% economic need; 0.49 mi fresh access; 3 nearby resources | L100: =IF($M100=0,"",IF(INDEX(Data!$AN$2051:$AN$2550,$M100)=0,"",IF(INDEX(Data!$U$41:$U$540,INDEX(Data!$AN$2051:$AN$2550,$M100))="","",INDEX(Data!$U$41:$U$540,INDEX(Data!$AN$2051:$AN$2550,$M100))))) | M100: =IF(COUNTIFS(Data!$AV$2051:$AV$2550,88)=1,MATCH(88,Data!$AV$2051:$AV$2550,0),0) -> 151 | N100: =IF($M100=0,"",IF(INDEX(Data!$I$2051:$I$2550,$M100)=0,"Add ID","Row "&(INDEX(Data!$I$2051:$I$2550,$M100)+7))) -> Row 241
A101: =IF($M101=0,"",INDEX(Data!$W$2051:$W$2550,$M101)) -> 89 | B101: =IF($M101=0,"",INDEX(Data!$B$2051:$B$2550,$M101)) -> Eugenio Maria De Hostos Charter School | C101: =IF($M101=0,"",INDEX(Data!$C$2051:$C$2550,$M101)) -> Charter | D101: =IF($M101=0,"",INDEX(Data!$D$2051:$D$2550,$M101)) -> Elementary-Middle | E101: =IF($M101=0,"",INDEX(Data!$G$2051:$G$2550,$M101)) -> 0.7647 | F101: =IF($M101=0,"",INDEX(Data!$F$2051:$F$2550,$M101)) -> 697 | G101: =IF($M101=0,"",INDEX(Data!$K$2051:$K$2550,$M101)) -> 0.29237139 | H101: =IF($M101=0,"",INDEX(Data!$L$2051:$L$2550,$M101)) -> 3 | I101: =IF($M101=0,"",INDEX(Data!$T$2051:$T$2550,$M101)) -> 44 | J101: =IF($M101=0,"",INDEX(Data!$U$2051:$U$2550,$M101)) -> Listed | K101: =IF($M101=0,"",INDEX(Data!$AA$2051:$AA$2550,$M101)) -> 76% economic need; 0.29 mi fresh access; 3 nearby resources | L101: =IF($M101=0,"",IF(INDEX(Data!$AN$2051:$AN$2550,$M101)=0,"",IF(INDEX(Data!$U$41:$U$540,INDEX(Data!$AN$2051:$AN$2550,$M101))="","",INDEX(Data!$U$41:$U$540,INDEX(Data!$AN$2051:$AN$2550,$M101))))) -> 215-455-2300 | M101: =IF(COUNTIFS(Data!$AV$2051:$AV$2550,89)=1,MATCH(89,Data!$AV$2051:$AV$2550,0),0) -> 77 | N101: =IF($M101=0,"",IF(INDEX(Data!$I$2051:$I$2550,$M101)=0,"Add ID","Row "&(INDEX(Data!$I$2051:$I$2550,$M101)+7))) -> Row 73
A102: =IF($M102=0,"",INDEX(Data!$W$2051:$W$2550,$M102)) -> 90 | B102: =IF($M102=0,"",INDEX(Data!$B$2051:$B$2550,$M102)) -> Mastery Charter School at Clymer | C102: =IF($M102=0,"",INDEX(Data!$C$2051:$C$2550,$M102)) -> Charter | D102: =IF($M102=0,"",INDEX(Data!$D$2051:$D$2550,$M102)) -> Elementary | E102: =IF($M102=0,"",INDEX(Data!$G$2051:$G$2550,$M102)) -> 0.9808 | F102: =IF($M102=0,"",INDEX(Data!$F$2051:$F$2550,$M102)) -> 417 | G102: =IF($M102=0,"",INDEX(Data!$K$2051:$K$2550,$M102)) -> 0.36645928 | H102: =IF($M102=0,"",INDEX(Data!$L$2051:$L$2550,$M102)) -> 14 | I102: =IF($M102=0,"",INDEX(Data!$T$2051:$T$2550,$M102)) -> 43 | J102: =IF($M102=0,"",INDEX(Data!$U$2051:$U$2550,$M102)) -> Listed | K102: =IF($M102=0,"",INDEX(Data!$AA$2051:$AA$2550,$M102)) -> 98% economic need; 0.37 mi fresh access; 14 nearby resources | L102: =IF($M102=0,"",IF(INDEX(Data!$AN$2051:$AN$2550,$M102)=0,"",IF(INDEX(Data!$U$41:$U$540,INDEX(Data!$AN$2051:$AN$2550,$M102))="","",INDEX(Data!$U$41:$U$540,INDEX(Data!$AN$2051:$AN$2550,$M102))))) | M102: =IF(COUNTIFS(Data!$AV$2051:$AV$2550,90)=1,MATCH(90,Data!$AV$2051:$AV$2550,0),0) -> 131 | N102: =IF($M102=0,"",IF(INDEX(Data!$I$2051:$I$2550,$M102)=0,"Add ID","Row "&(INDEX(Data!$I$2051:$I$2550,$M102)+7))) -> Row 190
A103: =IF($M103=0,"",INDEX(Data!$W$2051:$W$2550,$M103)) -> 91 | B103: =IF($M103=0,"",INDEX(Data!$B$2051:$B$2550,$M103)) -> James Rhoads School | C103: =IF($M103=0,"",INDEX(Data!$C$2051:$C$2550,$M103)) -> District | D103: =IF($M103=0,"",INDEX(Data!$D$2051:$D$2550,$M103)) -> Elementary-Middle | E103: =IF($M103=0,"",INDEX(Data!$G$2051:$G$2550,$M103)) -> 0.927 | F103: =IF($M103=0,"",INDEX(Data!$F$2051:$F$2550,$M103)) -> 415 | G103: =IF($M103=0,"",INDEX(Data!$K$2051:$K$2550,$M103)) -> 0.35550347 | H103: =IF($M103=0,"",INDEX(Data!$L$2051:$L$2550,$M103)) -> 12 | I103: =IF($M103=0,"",INDEX(Data!$T$2051:$T$2550,$M103)) -> 43 | J103: =IF($M103=0,"",INDEX(Data!$U$2051:$U$2550,$M103)) -> Listed | K103: =IF($M103=0,"",INDEX(Data!$AA$2051:$AA$2550,$M103)) -> 93% economic need; 0.36 mi fresh access; 12 nearby resources | L103: =IF($M103=0,"",IF(INDEX(Data!$AN$2051:$AN$2550,$M103)=0,"",IF(INDEX(Data!$U$41:$U$540,INDEX(Data!$AN$2051:$AN$2550,$M103))="","",INDEX(Data!$U$41:$U$540,INDEX(Data!$AN$2051:$AN$2550,$M103))))) -> 215-400-7680 | M103: =IF(COUNTIFS(Data!$AV$2051:$AV$2550,91)=1,MATCH(91,Data!$AV$2051:$AV$2550,0),0) -> 22 | N103: =IF($M103=0,"",IF(INDEX(Data!$I$2051:$I$2550,$M103)=0,"Add ID","Row "&(INDEX(Data!$I$2051:$I$2550,$M103)+7))) -> Row 138
A104: =IF($M104=0,"",INDEX(Data!$W$2051:$W$2550,$M104)) -> 92 | B104: =IF($M104=0,"",INDEX(Data!$B$2051:$B$2550,$M104)) -> John Barry School | C104: =IF($M104=0,"",INDEX(Data!$C$2051:$C$2550,$M104)) -> District | D104: =IF($M104=0,"",INDEX(Data!$D$2051:$D$2550,$M104)) -> Elementary-Middle | E104: =IF($M104=0,"",INDEX(Data!$G$2051:$G$2550,$M104)) -> 0.9118 | F104: =IF($M104=0,"",INDEX(Data!$F$2051:$F$2550,$M104)) -> 442 | G104: =IF($M104=0,"",INDEX(Data!$K$2051:$K$2550,$M104)) -> 0.3547315 | H104: =IF($M104=0,"",INDEX(Data!$L$2051:$L$2550,$M104)) -> 11 | I104: =IF($M104=0,"",INDEX(Data!$T$2051:$T$2550,$M104)) -> 43 | J104: =IF($M104=0,"",INDEX(Data!$U$2051:$U$2550,$M104)) -> Listed | K104: =IF($M104=0,"",INDEX(Data!$AA$2051:$AA$2550,$M104)) -> 91% economic need; 0.35 mi fresh access; 11 nearby resources | L104: =IF($M104=0,"",IF(INDEX(Data!$AN$2051:$AN$2550,$M104)=0,"",IF(INDEX(Data!$U$41:$U$540,INDEX(Data!$AN$2051:$AN$2550,$M104))="","",INDEX(Data!$U$41:$U$540,INDEX(Data!$AN$2051:$AN$2550,$M104))))) -> 215-400-7640 | M104: =IF(COUNTIFS(Data!$AV$2051:$AV$2550,92)=1,MATCH(92,Data!$AV$2051:$AV$2550,0),0) -> 8 | N104: =IF($M104=0,"",IF(INDEX(Data!$I$2051:$I$2550,$M104)=0,"Add ID","Row "&(INDEX(Data!$I$2051:$I$2550,$M104)+7))) -> Row 142
A105: =IF($M105=0,"",INDEX(Data!$W$2051:$W$2550,$M105)) -> 93 | B105: =IF($M105=0,"",INDEX(Data!$B$2051:$B$2550,$M105)) -> Lewis Elkin School | C105: =IF($M105=0,"",INDEX(Data!$C$2051:$C$2550,$M105)) -> District | D105: =IF($M105=0,"",INDEX(Data!$D$2051:$D$2550,$M105)) -> Elementary | E105: =IF($M105=0,"",INDEX(Data!$G$2051:$G$2550,$M105)) -> 0.9069 | F105: =IF($M105=0,"",INDEX(Data!$F$2051:$F$2550,$M105)) -> 431 | G105: =IF($M105=0,"",INDEX(Data!$K$2051:$K$2550,$M105)) -> 0.32714422 | H105: =IF($M105=0,"",INDEX(Data!$L$2051:$L$2550,$M105)) -> 10 | I105: =IF($M105=0,"",INDEX(Data!$T$2051:$T$2550,$M105)) -> 43 | J105: =IF($M105=0,"",INDEX(Data!$U$2051:$U$2550,$M105)) -> Listed | K105: =IF($M105=0,"",INDEX(Data!$AA$2051:$AA$2550,$M105)) -> 91% economic need; 0.33 mi fresh access; 10 nearby resources | L105: =IF($M105=0,"",IF(INDEX(Data!$AN$2051:$AN$2550,$M105)=0,"",IF(INDEX(Data!$U$41:$U$540,INDEX(Data!$AN$2051:$AN$2550,$M105))="","",INDEX(Data!$U$41:$U$540,INDEX(Data!$AN$2051:$AN$2550,$M105))))) -> 215-400-7140 | M105: =IF(COUNTIFS(Data!$AV$2051:$AV$2550,93)=1,MATCH(93,Data!$AV$2051:$AV$2550,0),0) -> 193 | N105: =IF($M105=0,"",IF(INDEX(Data!$I$2051:$I$2550,$M105)=0,"Add ID","Row "&(INDEX(Data!$I$2051:$I$2550,$M105)+7))) -> Row 178
A106: =IF($M106=0,"",INDEX(Data!$W$2051:$W$2550,$M106)) -> 94 | B106: =IF($M106=0,"",INDEX(Data!$B$2051:$B$2550,$M106)) -> William H. Hunter School | C106: =IF($M106=0,"",INDEX(Data!$C$2051:$C$2550,$M106)) -> District | D106: =IF($M106=0,"",INDEX(Data!$D$2051:$D$2550,$M106)) -> Elementary-Middle | E106: =IF($M106=0,"",INDEX(Data!$G$2051:$G$2550,$M106)) -> 0.9031 | F106: =IF($M106=0,"",INDEX(Data!$F$2051:$F$2550,$M106)) -> 357 | G106: =IF($M106=0,"",INDEX(Data!$K$2051:$K$2550,$M106)) -> 0.26515505 | H106: =IF($M106=0,"",INDEX(Data!$L$2051:$L$2550,$M106)) -> 12 | I106: =IF($M106=0,"",INDEX(Data!$T$2051:$T$2550,$M106)) -> 43 | J106: =IF($M106=0,"",INDEX(Data!$U$2051:$U$2550,$M106)) -> Listed | K106: =IF($M106=0,"",INDEX(Data!$AA$2051:$AA$2550,$M106)) -> 90% economic need; 0.27 mi fresh access; 12 nearby resources | L106: =IF($M106=0,"",IF(INDEX(Data!$AN$2051:$AN$2550,$M106)=0,"",IF(INDEX(Data!$U$41:$U$540,INDEX(Data!$AN$2051:$AN$2550,$M106))="","",INDEX(Data!$U$41:$U$540,INDEX(Data!$AN$2051:$AN$2550,$M106))))) -> 215-400-7110 | M106: =IF(COUNTIFS(Data!$AV$2051:$AV$2550,94)=1,MATCH(94,Data!$AV$2051:$AV$2550,0),0) -> 196 | N106: =IF($M106=0,"",IF(INDEX(Data!$I$2051:$I$2550,$M106)=0,"Add ID","Row "&(INDEX(Data!$I$2051:$I$2550,$M106)+7))) -> Row 324
...

Sheet Data
A1: School ID | B1: School name | C1: Governance | D1: Title I | E1: Level | F1: Address | G1: City | H1: ZIP | I1: Latitude | J1: Longitude | K1: Enrollment | L1: Economic disadvantage | M1: Listed food sites ≤1mi | N1: School year | O1: Retrieved | P1: Dataset | Q1: PA school code | R1: AUN | T1: Setting | U1: Value
A2: 1010 | B2: John Bartram High School | C2: District | D2: Yes | E2: High | F2: 2401 S 67TH ST | G2: PHILADELPHIA | H2: 19142 | I2: 39.921497 | J2: -75.234056 | K2: 594 | L2: 0.8053 | M2: 4 | N2: 2025-2026 | O2: 2026-10-09 | P2: Live | Q2: 3847 | R2: 126515001 | T2: SchoolURL | U2: https://cdn.philasd.org/offices/performance/Open_Data/School_Information/School_List/2026-2027%20Master%20School%20List%20(20260928).csv
A3: 1020 | B3: West Philadelphia High School | C3: District | D3: Yes | E3: High | F3: 4901 CHESTNUT ST | G3: PHILADELPHIA | H3: 19139 | I3: 39.95811 | J3: -75.219654 | K3: 729 | L3: 0.8456 | M3: 14 | N3: 2025-2026 | O3: 2026-10-09 | P3: Live | Q3: 3860 | R3: 126515001 | T3: EnrollmentURL | U3: https://cdn.philasd.org/offices/performance/Open_Data/School_Information/Enrollment_Demographics_School/2025-2026%20Enrollment%20%26%20Demographics.csv
A4: 1030 | B4: High School of the Future | C4: District | D4: Yes | E4: High | F4: 4021 PARKSIDE AVE | G4: PHILADELPHIA | H4: 19104 | I4: 39.974658 | J4: -75.204757 | K4: 648 | L4: 0.8416 | M4: 9 | N4: 2025-2026 | O4: 2026-10-09 | P4: Live | Q4: 7903 | R4: 126515001 | T4: EconomicURL | U4: https://www.pa.gov/content/dam/copapwp-pagov/en/education/documents/data-and-reporting/loan-cancellation/public/2526%20public%20schools%20percent%20low%20income.xlsx
A5: 1050 | B5: Paul Robeson High School for Human Services | C5: District | D5: Yes | E5: High | F5: 4125 LUDLOW ST | G5: PHILADELPHIA | H5: 19104 | I5: 39.956796 | J5: -75.204763 | K5: 300 | L5: 0.7533 | M5: 12 | N5: 2025-2026 | O5: 2026-10-09 | P5: Live | Q5: 7780 | R5: 126515001 | T5: FoodURL | U5: https://services.arcgis.com/fLeGjb7u4uXqeF9q/ArcGIS/rest/services/free_meal_sites/FeatureServer/0/query?where=1%3D1&outFields=*&outSR=4326&f=json
A6: 1100 | B6: William L. Sayre High School | C6: District | D6: Yes | E6: High | F6: 5800 WALNUT ST | G6: PHILADELPHIA | H6: 19139 | I6: 39.957594 | J6: -75.238594 | K6: 439 | L6: 0.8084 | M6: 13 | N6: 2025-2026 | O6: 2026-10-09 | P6: Live | Q6: 7245 | R6: 126515001 | T6: TitleHistoryURL | U6: https://cdn.philasd.org/offices/performance/Open_Data/School_Information/School_List/2025-2026%20Master%20School%20List%20(20251001).csv
A7: 1130 | B7: William T. Tilden Middle School | C7: District | D7: Yes | E7: Middle | F7: 6601 ELMWOOD AVE | G7: PHILADELPHIA | H7: 19142 | I7: 39.920936 | J7: -75.232276 | K7: 230 | L7: 0.8787 | M7: 4 | N7: 2025-2026 | O7: 2026-10-09 | P7: Live | Q7: 8297 | R7: 126515001 | T7: DirectoryYear | U7: 2026-2027
A8: 1190 | B8: Motivation High School | C8: District | D8: Yes | E8: High | F8: 5900 BALTIMORE AVE | G8: PHILADELPHIA | H8: 19143 | I8: 39.944532 | J8: -75.241844 | K8: 151 | L8: 0.8344 | M8: 5 | N8: 2025-2026 | O8: 2026-10-09 | P8: Live | Q8: 7815 | R8: 126515001 | T8: EconomicSheet | U8: 2026 LIP by School
A9: 1200 | B9: John Barry School | C9: District | D9: Yes | E9: Elementary-Middle | F9: 5900 RACE ST | G9: PHILADELPHIA | H9: 19139 | I9: 39.964375 | J9: -75.238604 | K9: 442 | L9: 0.9118 | M9: 11 | N9: 2025-2026 | O9: 2026-10-09 | P9: Live | Q9: 8029 | R9: 126515001
A10: 1230 | B10: William C. Bryant School | C10: District | D10: Yes | E10: Elementary-Middle | F10: 6001 CEDAR AVE | G10: PHILADELPHIA | H10: 19143 | I10: 39.952687 | J10: -75.243691 | K10: 332 | L10: 0.9023 | M10: 5 | N10: 2025-2026 | O10: 2026-10-09 | P10: Live | Q10: 3601 | R10: 126515001
A11: 1250 | B11: Joseph W. Catharine School | C11: District | D11: Yes | E11: Elementary | F11: 6600 CHESTER AVE | G11: PHILADELPHIA | H11: 19142 | I11: 39.927435 | J11: -75.239911 | K11: 377 | L11: 0.782 | M11: 5 | N11: 2025-2026 | O11: 2026-10-09 | P11: Live | Q11: 3602 | R11: 126515001
A12: 1260 | B12: Benjamin B. Comegys School | C12: District | D12: Yes | E12: Elementary-Middle | F12: 5100 GREENWAY AVE | G12: PHILADELPHIA | H12: 19143 | I12: 39.94052 | J12: -75.216289 | K12: 213 | L12: 0.9014 | M12: 7 | N12: 2025-2026 | O12: 2026-10-09 | P12: Live | Q12: 3782 | R12: 126515001 | T12: Method | U12: Definition
A13: 1280 | B13: Sadie T.M. Alexander UPenn Partnership School | C13: District | D13: Yes | E13: Elementary-Middle | F13: 4209 SPRUCE ST | G13: PHILADELPHIA | H13: 19104 | I13: 39.953099 | J13: -75.208187 | K13: 601 | L13: 0.2288 | M13: 10 | N13: 2025-2026 | O13: 2026-10-09 | P13: Live | Q13: 7706 | R13: 126515001 | T13: Scope | U13: Philadelphia district schools and charters with last-published Title I status. Contracted schools excluded.
A14: 1290 | B14: Andrew Hamilton School | C14: District | D14: Yes | E14: Elementary-Middle | F14: 5640 SPRUCE ST | G14: PHILADELPHIA | H14: 19139 | I14: 39.955438 | J14: -75.235543 | K14: 366 | L14: 0.9013 | M14: 10 | N14: 2025-2026 | O14: 2026-10-09 | P14: Live | Q14: 5185 | R14: 126515001 | T14: Directory | U14: 2026–27 current school directory; demographics use 2025–26 published files.
A15: 1300 | B15: Avery D. Harrington School | C15: District | D15: Yes | E15: Elementary-Middle | F15: 5300 BALTIMORE AVE | G15: PHILADELPHIA | H15: 19143 | I15: 39.947365 | J15: -75.230595 | K15: 259 | L15: 0.874 | M15: 11 | N15: 2025-2026 | O15: 2026-10-09 | P15: Live | Q15: 6528 | R15: 126515001 | T15: Title I gap | U15: 2026–27 and May 2026 directories omit charter Title I. Last populated October 2025 designation is matched on ULCS + AUN + PA code. Confirm charter eligibility before commitment.
A16: 1340 | B16: Henry C. Lea School | C16: District | D16: Yes | E16: Elementary-Middle | F16: 4700 LOCUST ST | G16: PHILADELPHIA | H16: 19139 | I16: 39.954515 | J16: -75.216347 | K16: 463 | L16: 0.7081 | M16: 12 | N16: 2025-2026 | O16: 2026-10-09 | P16: Live | Q16: 6530 | R16: 126515001 | T16: Fresh access | U16: Nearest USDA-listed SNAP supermarket/superstore. Smaller groceries and produce affordability are not established.
A17: 1350 | B17: William C. Longstreth School | C17: District | D17: Yes | E17: Elementary-Middle | F17: 5700 WILLOWS AVE | G17: PHILADELPHIA | H17: 19143 | I17: 39.940908 | J17: -75.232373 | K17: 259 | L17: 0.8958 | M17: 8 | N17: 2025-2026 | O17: 2026-10-09 | P17: Live | Q17: 6533 | R17: 126515001 | T17: Food resources | U17: Distinct active City Food Site addresses within 1 mile, excluding closure flags. Recurrence, eligibility and neighboring jurisdictions require review.
A18: 1360 | B18: Morton McMichael School | C18: District | D18: Yes | E18: Elementary-Middle | F18: 3543 FAIRMOUNT AVE | G18: PHILADELPHIA | H18: 19104 | I18: 39.966197 | J18: -75.194115 | K18: 286 | L18: 0.9264 | M18: 11 | N18: 2025-2026 | O18: 2026-10-09 | P18: Live | Q18: 3611 | R18: 126515001 | T18: Review overrides | U18: Dated, nonnegative staff inputs with evidence replace the corresponding source proxy for 180 days by default. Zero is valid.
A19: 1370 | B19: S. Weir Mitchell School | C19: District | D19: Yes | E19: Elementary-Middle | F19: 5500 KINGSESSING AVE | G19: PHILADELPHIA | H19: 19143 | I19: 39.936814 | J19: -75.223291 | K19: 271 | L19: 0.8726 | M19: 9 | N19: 2025-2026 | O19: 2026-10-09 | P19: Live | Q19: 3798 | R19: 126515001 | T19: Already served | U19: Staff flag only. No means unchecked, not proof the organization has never served the school. Yes excludes it immediately.
A20: 1380 | B20: Thomas G. Morton School | C20: District | D20: Yes | E20: Elementary | F20: 2501 S 63RD ST | G20: PHILADELPHIA | H20: 19142 | I20: 39.923468 | J20: -75.2269 | K20: 363 | L20: 0.8457 | M20: 5 | N20: 2025-2026 | O20: 2026-10-09 | P20: Live | Q20: 6535 | R20: 126515001 | T20: Rank order | U20: Active score descending, then economic disadvantage descending, enrollment descending, then school ID ascending. Equal scores still share a need rank.
A21: 1390 | B21: Samuel Powel School | C21: District | D21: Yes | E21: Elementary | F21: 3610 WARREN ST | G21: PHILADELPHIA | H21: 19104 | I21: 39.957963 | J21: -75.193918 | K21: 342 | L21: 0.4736 | M21: 10 | N21: 2025-2026 | O21: 2026-10-09 | P21: Live | Q21: 3783 | R21: 126515001 | T21: Tier | U21: Baseline rubric only: 70+ Tier 1, 55+ Tier 2, 40+ Tier 3, below 40 Tier 4.
A22: 1400 | B22: John M. Patterson School | C22: District | D22: Yes | E22: Elementary | F22: 7000 BUIST AVE | G22: PHILADELPHIA | H22: 19142 | I22: 39.916095 | J22: -75.236762 | K22: 353 | L22: 0.8425 | M22: 3 | N22: 2025-2026 | O22: 2026-10-09 | P22: Live | Q22: 3613 | R22: 126515001 | T22: Missing data | U22: Missing economic %, enrollment or access input prevents a complete score. No imputation.
A23: 1410 | B23: James Rhoads School | C23: District | D23: Yes | E23: Elementary-Middle | F23: 4901 PARRISH ST | G23: PHILADELPHIA | H23: 19139 | I23: 39.967339 | J23: -75.220063 | K23: 415 | L23: 0.927 | M23: 12 | N23: 2025-2026 | O23: 2026-10-09 | P23: Live | Q23: 3614 | R23: 126515001 | T23: Refresh | U23: Native query installation is required once on Windows. Then Data > Refresh All. See kit.
... A27: 1470 | B27: Alain Locke School | C27: District | D27: Yes | E27: Elementary-Middle | F27: 4550 HAVERFORD AVE | G27: PHILADELPHIA | H27: 19139 | I27: 39.962624 | J27: -75.212451 | K27: 276 | L27: 0.829 | M27: 15 | N27: 2025-2026 | O27: 2026-10-09 | P27: Live | Q27: 4732 | R27: 126515001 | T27: Notes | U27: Straight-line Haversine miles (earth radius 3958.7613). Estimates guide outreach; listed access is not verified availability.
A28: 1490 | B28: Rudolph Blankenburg School | C28: District | D28: Yes | E28: Elementary-Middle | F28: 4600 W GIRARD AVE | G28: PHILADELPHIA | H28: 19131 | I28: 39.972963 | J28: -75.213889 | K28: 228 | L28: 0.8979 | M28: 9 | N28: 2025-2026 | O28: 2026-10-09 | P28: Live | Q28: 3663 | R28: 126515001
A29: 1580 | B29: Middle Years Alternative School | C29: District | D29: Yes | E29: Middle | F29: 4725 FAIRMOUNT AVE | G29: PHILADELPHIA | H29: 19139 | I29: 39.964254 | J29: -75.215467 | K29: 122 | L29: 0.8 | M29: 14 | N29: 2025-2026 | O29: 2026-10-09 | P29: Live | Q29: 7022 | R29: 126515001
A30: 2000 | B30: South Philadelphia High School | C30: District | D30: Yes | E30: High | F30: 2101 S BROAD ST | G30: PHILADELPHIA | H30: 19148 | I30: 39.923899 | J30: -75.169106 | K30: 647 | L30: 0.7803 | M30: 10 | N30: 2025-2026 | O30: 2026-10-09 | P30: Live | Q30: 3859 | R30: 126515001
A31: 2010 | B31: Benjamin Franklin High School | C31: District | D31: Yes | E31: High | F31: 550 N BROAD ST | G31: PHILADELPHIA | H31: 19130 | I31: 39.96353 | J31: -75.16164 | K31: 530 | L31: 0.831 | M31: 10 | N31: 2025-2026 | O31: 2026-10-09 | P31: Live | Q31: 3851 | R31: 126515001
A32: 2020 | B32: High School for Creative and Performing Arts | C32: District | D32: Yes | E32: High | F32: 901 S BROAD ST | G32: PHILADELPHIA | H32: 19147 | I32: 39.93942 | J32: -75.165484 | K32: 597 | L32: 0.4815 | M32: 13 | N32: 2025-2026 | O32: 2026-10-09 | P32: Live | Q32: 6996 | R32: 126515001
A33: 2050 | B33: Science Leadership Academy Middle School | C33: District | D33: Yes | E33: Middle | F33: 3610 WARREN ST | G33: PHILADELPHIA | H33: 19104 | I33: 39.957963 | J33: -75.193918 | K33: 351 | L33: 0.51 | M33: 10 | N33: 2025-2026 | O33: 2026-10-09 | P33: Live | Q33: 8387 | R33: 126515001
A34: 2140 | B34: Julia R. Masterman High School | C34: District | D34: Yes | E34: Middle-High | F34: 1699 SPRING GARDEN ST | G34: PHILADELPHIA | H34: 19130 | I34: 39.9632 | J34: -75.166208 | K34: 1221 | L34: 0.3778 | M34: 8 | N34: 2025-2026 | O34: 2026-10-09 | P34: Live | Q34: 3808 | R34: 126515001
A35: 2160 | B35: Horace Furness High School | C35: District | D35: Yes | E35: High | F35: 1900 S 3RD ST | G35: PHILADELPHIA | H35: 19148 | I35: 39.923762 | J35: -75.150585 | K35: 836 | L35: 0.6889 | M35: 6 | N35: 2025-2026 | O35: 2026-10-09 | P35: Live | Q35: 3818 | R35: 126515001
A36: 2190 | B36: D. Newlin Fell School | C36: District | D36: Yes | E36: Elementary-Middle | F36: 900 W OREGON AVE | G36: PHILADELPHIA | H36: 19148 | I36: 39.915586 | J36: -75.163009 | K36: 519 | L36: 0.7552 | M36: 5 | N36: 2025-2026 | O36: 2026-10-09 | P36: Live | Q36: 7226 | R36: 126515001 | T36: DONOT CHANGE ANY VARIABLES
A37: 2210 | B37: Bache-Martin School | C37: District | D37: Yes | E37: Elementary-Middle | F37: 2201 BROWN ST | G37: PHILADELPHIA | H37: 19130 | I37: 39.969678 | J37: -75.173847 | K37: 622 | L37: 0.5334 | M37: 7 | N37: 2025-2026 | O37: 2026-10-09 | P37: Live | Q37: 3618 | R37: 126515001
A38: 2240 | B38: F. Amedee Bregy School | C38: District | D38: Yes | E38: Elementary-Middle | F38: 1700 BIGLER ST | G38: PHILADELPHIA | H38: 19145 | I38: 39.914699 | J38: -75.176674 | K38: 244 | L38: 0.8191 | M38: 1 | N38: 2025-2026 | O38: 2026-10-09 | P38: Live | Q38: 3620 | R38: 126515001
A39: 2260 | B39: George W. Childs School | C39: District | D39: Yes | E39: Elementary-Middle | F39: 1599 WHARTON ST | G39: PHILADELPHIA | H39: 19146 | I39: 39.934637 | J39: -75.170493 | K39: 443 | L39: 0.7626 | M39: 16 | N39: 2025-2026 | O39: 2026-10-09 | P39: Live | Q39: 3622 | R39: 126515001
A40: 2290 | B40: Franklin Learning Center | C40: District | D40: Yes | E40: High | F40: 616 N 15TH ST | G40: PHILADELPHIA | H40: 19130 | I40: 39.965049 | J40: -75.162753 | K40: 975 | L40: 0.7603 | M40: 10 | N40: 2025-2026 | O40: 2026-10-09 | P40: Live | Q40: 6822 | R40: 126515001 | T40: School ID | U40: Phone | V40: Website | W40: Directory year | X40: Title I source year | Y40: Published Title I value used | Z40: Current directory Title I | AA40: Contact name/title | AB40: Contact email
A41: 2310 | B41: Achieve Academy of Philadelphia | C41: Contracted | D41: No | E41: Transition/Overage School | F41: 1435 N 26TH ST | G41: PHILADELPHIA | H41: 19121 | I41: 39.978134 | J41: -75.177658 | K41: 49 | M41: 12 | N41: 2025-2026 | O41: 2026-10-09 | P41: Live | Q41: 9999 | R41: 126515001 | T41: 1010 | U41: 215-400-8100 | V41: https://bartram.philasd.org/ | W41: 2026-2027 | X41: 2026-2027 | Y41: 1 | Z41: 1
A42: 2320 | B42: Stephen Girard School | C42: District | D42: Yes | E42: Elementary | F42: 1800 SNYDER AVE | G42: PHILADELPHIA | H42: 19145 | I42: 39.925059 | J42: -75.176611 | K42: 304 | L42: 0.8411 | M42: 12 | N42: 2025-2026 | O42: 2026-10-09 | P42: Live | Q42: 3776 | R42: 126515001 | T42: 1020 | U42: 215-400-7900 | V42: https://wphs.philasd.org/ | W42: 2026-2027 | X42: 2026-2027 | Y42: 1 | Z42: 1
A43: 2340 | B43: General George A. McCall School | C43: District | D43: Yes | E43: Elementary-Middle | F43: 325 S 7TH ST | G43: PHILADELPHIA | H43: 19106 | I43: 39.944635 | J43: -75.15318 | K43: 667 | L43: 0.4009 | M43: 7 | N43: 2025-2026 | O43: 2026-10-09 | P43: Live | Q43: 3648 | R43: 126515001 | T43: 1030 | U43: 215-400-7790 | V43: https://sof.philasd.org/ | W43: 2026-2027 | X43: 2026-2027 | Y43: 1 | Z43: 1
A44: 2370 | B44: Delaplaine McDaniel School | C44: District | D44: Yes | E44: Elementary-Middle | F44: 1801 S 22ND ST | G44: PHILADELPHIA | H44: 19145 | I44: 39.929592 | J44: -75.181793 | K44: 240 | L44: 0.8547 | M44: 11 | N44: 2025-2026 | O44: 2026-10-09 | P44: Live | Q44: 3629 | R44: 126515001 | T44: 1050 | U44: 215-400-7780 | V44: https://robeson.philasd.org/ | W44: 2026-2027 | X44: 2026-2027 | Y44: 1 | Z44: 1
A45: 2380 | B45: William M. Meredith School | C45: District | D45: No | E45: Elementary-Middle | F45: 725 S 5TH ST | G45: PHILADELPHIA | H45: 19147 | I45: 39.939749 | J45: -75.151133 | K45: 579 | L45: 0.1539 | M45: 6 | N45: 2025-2026 | O45: 2026-10-09 | P45: Live | Q45: 3649 | R45: 126515001 | T45: 1100 | U45: 215-400-7800 | V45: https://sayre.philasd.org/ | W45: 2026-2027 | X45: 2026-2027 | Y45: 1 | Z45: 1
A46: 2390 | B46: Robert Morris School | C46: District | D46: Yes | E46: Elementary-Middle | F46: 2600 W THOMPSON ST | G46: PHILADELPHIA | H46: 19121 | I46: 39.975439 | J46: -75.17866 | K46: 216 | L46: 0.9023 | M46: 9 | N46: 2025-2026 | O46: 2026-10-09 | P46: Live | Q46: 4868 | R46: 126515001 | T46: 1130 | U46: 215-400-8170 | V46: https://tilden.philasd.org/ | W46: 2026-2027 | X46: 2026-2027 | Y46: 1 | Z46: 1
A47: 2410 | B47: Girard Academic Music Program High School | C47: District | D47: Yes | E47: Middle-High | F47: 2136 W RITNER ST, GAMP | G47: PHILADELPHIA | H47: 19145 | I47: 39.922105 | J47: -75.182564 | K47: 666 | M47: 7 | N47: 2025-2026 | O47: 2026-10-09 | P47: Live | Q47: 007664 | R47: 126515001 | T47: 1190 | U47: 215-400-7930 | V47: https://motivationhs.philasd.org/ | W47: 2026-2027 | X47: 2026-2027 | Y47: 1 | Z47: 1
A48: 2450 | B48: Edwin M. Stanton School | C48: District | D48: Yes | E48: Elementary-Middle | F48: 901 S. 17TH ST. | G48: PHILADELPHIA | H48: 19146 | I48: 39.940503 | J48: -75.171017 | K48: 316 | L48: 0.6497 | M48: 15 | N48: 2025-2026 | O48: 2026-10-09 | P48: Live | Q48: 3635 | R48: 126515001 | T48: 1200 | U48: 215-400-7640 | V48: https://barry.philasd.org/ | W48: 2026-2027 | X48: 2026-2027 | Y48: 1 | Z48: 1
